Workbook

Sheet  911 Admin
A1: City of Altamonte Springs, Florida
A2: ='[1]Admin Summary'!A2:K2 -> Fiscal Year 2026 / 2027 Annual Budget
A4: Leisure and Maintenance Services Department
A5: Administration Division
A6: General Fund (00109110)
M8: ='[1]WS 818'!M8 -> 2027
G9: ='[1]WS 818'!G9 -> 2024 | I9: ='[1]WS 818'!I9 -> 2025 | K9: ='[1]WS 818'!K9 -> 2026 | M9: Department | O9: Manager | Q9: Commission
B10: Org | C10: Obj | D10: Proj | G10: Actual | I10: Actual | K10: Budget | M10: Requested | O10: Recommended | Q10: Adopted | R10: Notes
A11: PERSONNEL SERVICES
A12: Regular Salaries & Wages Base: 9 Positions | B12: 00109110 | C12: 501201 | E12: =_xlfn.CONCAT(B12,C12,D12) -> 00109110501201 | F12: $ | G12: =ROUND(IFERROR(VLOOKUP(_xlfn.CONCAT($B12,$C12,$D12),$A$73:$C$9993,3,FALSE),0),0) -> 682482 | H12: $ | I12: =ROUND(IFERROR(VLOOKUP(_xlfn.CONCAT($B12,$C12,$D12),$A$73:$C$9993,2,FALSE),0),0) -> 715227 | J12: $ | K12: 673169 | L12: $ | M12: ='[1]Payroll Summary by Department'!C60 -> 673169 | N12: $ | O12: ='[1]Payroll Summary by Department'!C60 -> 673169 | P12: $ | Q12: =O12 -> 673169
A13: Limited Term - Intern | B13: 00109110 | C13: 501315 | E13: =_xlfn.CONCAT(B13,C13,D13) -> 00109110501315 | G13: =ROUND(IFERROR(VLOOKUP(_xlfn.CONCAT($B13,$C13,$D13),$A$73:$C$9993,3,FALSE),0),0) -> 7823 | I13: =ROUND(IFERROR(VLOOKUP(_xlfn.CONCAT($B13,$C13,$D13),$A$73:$C$9993,2,FALSE),0),0) -> 11689 | K13: 21000 | M13: 21000 | O13: =M13 -> 21000 | Q13: =O13 -> 21000
A14: Overtime | B14: 00109110 | C14: 501400 | E14: =_xlfn.CONCAT(B14,C14,D14) -> 00109110501400 | G14: =ROUND(IFERROR(VLOOKUP(_xlfn.CONCAT($B14,$C14,$D14),$A$73:$C$9993,3,FALSE),0),0) -> 1100 | I14: =ROUND(IFERROR(VLOOKUP(_xlfn.CONCAT($B14,$C14,$D14),$A$73:$C$9993,2,FALSE),0),0) -> 2658 | K14: 1000 | M14: 1000 | O14: =M14 -> 1000 | Q14: =O14 -> 1000
A15: On-Call | B15: 00109110 | C15: 501401 | E15: =_xlfn.CONCAT(B15,C15,D15) -> 00109110501401 | G15: =ROUND(IFERROR(VLOOKUP(_xlfn.CONCAT($B15,$C15,$D15),$A$73:$C$9993,3,FALSE),0),0) -> 0 | I15: =ROUND(IFERROR(VLOOKUP(_xlfn.CONCAT($B15,$C15,$D15),$A$73:$C$9993,2,FALSE),0),0) -> 0 | K15: 0 | M15: 0 | O15: =M15 -> 0 | Q15: =O15 -> 0
A16: Add Pays | B16: 00109110 | C16: 501600 | E16: =_xlfn.CONCAT(B16,C16,D16) -> 00109110501600 | G16: =ROUND(IFERROR(VLOOKUP(_xlfn.CONCAT($B16,$C16,$D16),$A$73:$C$9993,3,FALSE),0),0) -> 0 | I16: =ROUND(IFERROR(VLOOKUP(_xlfn.CONCAT($B16,$C16,$D16),$A$73:$C$9993,2,FALSE),0),0) -> 0 | K16: 0 | M16: ='[1]Payroll Summary by Department'!I60 -> 0 | O16: =M16 -> 0 | Q16: =O16 -> 0
A17: Auto Allowance | B17: 00109110 | C17: 501701 | E17: =_xlfn.CONCAT(B17,C17,D17) -> 00109110501701 | G17: =ROUND(IFERROR(VLOOKUP(_xlfn.CONCAT($B17,$C17,$D17),$A$73:$C$9993,3,FALSE),0),0) -> 12040 | I17: =ROUND(IFERROR(VLOOKUP(_xlfn.CONCAT($B17,$C17,$D17),$A$73:$C$9993,2,FALSE),0),0) -> 12049 | K17: 12000 | M17: ='[1]Payroll Summary by Department'!K60 -> 12000 | O17: =M17 -> 12000 | Q17: =O17 -> 12000
A18: Cell Phone Allowance | B18: 00109110 | C18: 501702 | E18: =_xlfn.CONCAT(B18,C18,D18) -> 00109110501702 | G18: =ROUND(IFERROR(VLOOKUP(_xlfn.CONCAT($B18,$C18,$D18),$A$73:$C$9993,3,FALSE),0),0) -> 6623 | I18: =ROUND(IFERROR(VLOOKUP(_xlfn.CONCAT($B18,$C18,$D18),$A$73:$C$9993,2,FALSE),0),0) -> 6811 | K18: 6600 | M18: ='[1]Payroll Summary by Department'!L60 -> 6600 | O18: =M18 -> 6600 | Q18: =O18 -> 6600
A19: Uniform Allowance | B19: 00109110 | C19: 501800 | E19: =_xlfn.CONCAT(B19,C19,D19) -> 00109110501800 | G19: =ROUND(IFERROR(VLOOKUP(_xlfn.CONCAT($B19,$C19,$D19),$A$73:$C$9993,3,FALSE),0),0) -> 0 | I19: =ROUND(IFERROR(VLOOKUP(_xlfn.CONCAT($B19,$C19,$D19),$A$73:$C$9993,2,FALSE),0),0) -> 0 | K19: 50 | M19: 50 | O19: =M19 -> 50 | Q19: =O19 -> 50
A20: FICA Taxes | B20: 00109110 | C20: 502100 | E20: =_xlfn.CONCAT(B20,C20,D20) -> 00109110502100 | G20: =ROUND(IFERROR(VLOOKUP(_xlfn.CONCAT($B20,$C20,$D20),$A$73:$C$9993,3,FALSE),0),0) -> 53677 | I20: =ROUND(IFERROR(VLOOKUP(_xlfn.CONCAT($B20,$C20,$D20),$A$73:$C$9993,2,FALSE),0),0) -> 56288 | K20: 54607 | M20: ='[1]Payroll Summary by Department'!N60 -> 54607 | O20: ='[1]Payroll Summary by Department'!N60 -> 54607 | Q20: =O20 -> 54607
A21: Retirement Contributions | B21: 00109110 | C21: 502200 | E21: =_xlfn.CONCAT(B21,C21,D21) -> 00109110502200 | G21: =ROUND(IFERROR(VLOOKUP(_xlfn.CONCAT($B21,$C21,$D21),$A$73:$C$9993,3,FALSE),0),0) -> 83410 | I21: =ROUND(IFERROR(VLOOKUP(_xlfn.CONCAT($B21,$C21,$D21),$A$73:$C$9993,2,FALSE),0),0) -> 84375 | K21: 100961 | M21: ='[1]Payroll Summary by Department'!O60+'[1]Payroll Summary by Department'!P60 -> 100961 | O21: ='[1]Payroll Summary by Department'!O60+'[1]Payroll Summary by Department'!P60 -> 100961 | Q21: =O21 -> 100961
A22: Health Insurance | B22: 00109110 | C22: 502300 | E22: =_xlfn.CONCAT(B22,C22,D22) -> 00109110502300 | G22: =ROUND(IFERROR(VLOOKUP(_xlfn.CONCAT($B22,$C22,$D22),$A$73:$C$9993,3,FALSE),0),0) -> 82199 | I22: =ROUND(IFERROR(VLOOKUP(_xlfn.CONCAT($B22,$C22,$D22),$A$73:$C$9993,2,FALSE),0),0) -> 87748 | K22: 102160 | M22: ='[1]Payroll Summary by Department'!Q60 -> 102160 | O22: ='[1]Payroll Summary by Department'!Q60 -> 102160 | Q22: =O22 -> 102160
A23: Life Insurance | B23: 00109110 | C23: 502400 | E23: =_xlfn.CONCAT(B23,C23,D23) -> 00109110502400 | G23: =ROUND(IFERROR(VLOOKUP(_xlfn.CONCAT($B23,$C23,$D23),$A$73:$C$9993,3,FALSE),0),0) -> 1388 | I23: =ROUND(IFERROR(VLOOKUP(_xlfn.CONCAT($B23,$C23,$D23),$A$73:$C$9993,2,FALSE),0),0) -> 1409 | K23: 1272 | M23: ='[1]Payroll Summary by Department'!R60 -> 1272 | O23: ='[1]Payroll Summary by Department'!R60 -> 1272 | Q23: =O23 -> 1272
A24: Total Personnel Services | E24: =_xlfn.CONCAT(B24,C24,D24) | F24: $ | G24: =SUM(G12:G23) -> 930742 | H24: $ | I24: =SUM(I12:I23) -> 978254 | J24: $ | K24: =SUM(K12:K23) -> 972819 | L24: $ | M24: =SUM(M12:M23) -> 972819 | N24: $ | O24: =SUM(O12:O23) -> 972819 | P24: $ | Q24: =SUM(Q12:Q23) -> 972819
A25: POSITION ROSTER | E25: =_xlfn.CONCAT(B25,C25,D25)
A26: Full-Time Employees | E26: =_xlfn.CONCAT(B26,C26,D26)
A27: Director of Leisure Services | C27: 1D | E27: =_xlfn.CONCAT(B27,C27,D27) -> 1D | G27: 1 | I27: 1 | K27: =I27 -> 1 | M27: =K27 -> 1 | O27: =M27 -> 1 | Q27: =O27 -> 1
A28: Recreation Division Director | C28: 2A | E28: =_xlfn.CONCAT(B28,C28,D28) -> 2A | G28: 1 | I28: 1 | K28: =I28 -> 1 | M28: =K28 -> 1 | O28: =M28 -> 1 | Q28: =O28 -> 1
A29: Parks & Grounds Div. Director | C29: 2A | E29: =_xlfn.CONCAT(B29,C29,D29) -> 2A | G29: 1 | I29: 1 | K29: =I29 -> 1 | M29: =K29 -> 1 | O29: =M29 -> 1 | Q29: =O29 -> 1
A30: Fleet & Facilities Division Director | C30: 2A | E30: =_xlfn.CONCAT(B30,C30,D30) -> 2A | G30: 1 | I30: 1 | K30: =I30 -> 1 | M30: =K30 -> 1 | O30: =M30 -> 1 | Q30: =O30 -> 1
A31: Administrative Manager | C31: 3C | E31: =_xlfn.CONCAT(B31,C31,D31) -> 3C | G31: 1 | I31: 1 | K31: =I31 -> 1 | M31: =K31 -> 1 | O31: =M31 -> 1 | Q31: =O31 -> 1
A32: Fiscal Manager | C32: 3B | E32: =_xlfn.CONCAT(B32,C32,D32) -> 3B | G32: 1 | I32: 1 | K32: =I32 -> 1 | M32: =K32 -> 1 | O32: =M32 -> 1 | Q32: =O32 -> 1
A33: Office Administrator | C33: 3B | E33: =_xlfn.CONCAT(B33,C33,D33) -> 3B | G33: 0 | I33: 0 | K33: =I33 -> 0 | M33: =K33 -> 0 | O33: =M33 -> 0 | Q33: =O33 -> 0
A34: Staff Assistant | C34: 4C | E34: =_xlfn.CONCAT(B34,C34,D34) -> 4C | G34: 2 | I34: 2 | K34: =I34 -> 2 | M34: =K34 -> 2 | O34: =M34 -> 2 | Q34: =O34 -> 2
A35: Deputy Director | C35: 2B | E35: =_xlfn.CONCAT(B35,C35,D35) -> 2B | G35: 0 | I35: 0 | K35: =I35 -> 0 | M35: =K35 -> 0 | O35: =M35 -> 0 | Q35: =O35 -> 0
A36: Recreation Support Administrator | C36: 3B | E36: =_xlfn.CONCAT(B36,C36,D36) -> 3B | G36: 1 | I36: 1 | K36: =I36 -> 1 | M36: =K36 -> 1 | O36: =M36 -> 1 | Q36: =O36 -> 1
A37: PLMO Specialist | C37: 4C | E37: =_xlfn.CONCAT(B37,C37,D37) -> 4C | G37: 1 | I37: 1 | K37: =I37 -> 1 | M37: =K37 -> 1 | O37: =M37 -> 1 | Q37: =O37 -> 1
E38: =_xlfn.CONCAT(B38,C38,D38)
A39: Total Positions | E39: =_xlfn.CONCAT(B39,C39,D39) | G39: =SUM(G27:G38) -> 10 | I39: =SUM(I27:I38) -> 10 | K39: =SUM(K27:K38) -> 10 | M39: =SUM(M27:M38) -> 10 | O39: =SUM(O27:O38) -> 10 | Q39: =SUM(Q27:Q38) -> 10
A40: OPERATING EXPENDITURES | E40: =_xlfn.CONCAT(B40,C40,D40)
A41: Other Services-Software Subscriptions | B41: 00109110 | C41: 503403 | E41: =_xlfn.CONCAT(B41,C41,D41) -> 00109110503403 | F41: $ | G41: =ROUND(IFERROR(VLOOKUP(_xlfn.CONCAT($B41,$C41,$D41),$A$73:$C$9993,3,FALSE),0),0) -> 2717 | H41: $ | I41: =ROUND(IFERROR(VLOOKUP(_xlfn.CONCAT($B41,$C41,$D41),$A$73:$C$9993,2,FALSE),0),0) -> 2807 | J41: $ | K41: 0 | L41: $ | M41: 0 | N41: $ | O41: =M41 -> 0 | P41: $ | Q41: =O41 -> 0
A42: All Parks-Playgrd Inspec. Software | B42: 00109110 | E42: =_xlfn.CONCAT(B42,C42,D42) -> 00109110 | G42: =ROUND(IFERROR(VLOOKUP(_xlfn.CONCAT($B42,$C42,$D42),$A$73:$C$9993,3,FALSE),0),0) -> 0 | I42: =ROUND(IFERROR(VLOOKUP(_xlfn.CONCAT($B42,$C42,$D42),$A$73:$C$9993,2,FALSE),0),0) -> 0 | K42: 2500 | M42: 2500 | O42: =M42 -> 2500 | Q42: =O42 -> 2500
A43: Thorguard Software License | B43: 00109110 | E43: =_xlfn.CONCAT(B43,C43,D43) -> 00109110 | G43: =ROUND(IFERROR(VLOOKUP(_xlfn.CONCAT($B43,$C43,$D43),$A$73:$C$9993,3,FALSE),0),0) -> 0 | I43: =ROUND(IFERROR(VLOOKUP(_xlfn.CONCAT($B43,$C43,$D43),$A$73:$C$9993,2,FALSE),0),0) -> 0 | K43: 1875 | M43: 1875 | O43: =M43 -> 1875 | Q43: =O43 -> 1875
A44: AI Software Subscription | B44: 00109110 | E44: =_xlfn.CONCAT(B44,C44,D44) -> 00109110 | G44: =ROUND(IFERROR(VLOOKUP(_xlfn.CONCAT($B44,$C44,$D44),$A$73:$C$9993,3,FALSE),0),0) -> 0 | I44: =ROUND(IFERROR(VLOOKUP(_xlfn.CONCAT($B44,$C44,$D44),$A$73:$C$9993,2,FALSE),0),0) -> 0 | K44: 1200 | M44: 1200 | O44: =M44 -> 1200 | Q44: =O44 -> 1200
A45: Fingerprint Software | B45: 00109110 | E45: =_xlfn.CONCAT(B45,C45,D45) -> 00109110 | G45: =ROUND(IFERROR(VLOOKUP(_xlfn.CONCAT($B45,$C45,$D45),$A$73:$C$9993,3,FALSE),0),0) -> 0 | I45: =ROUND(IFERROR(VLOOKUP(_xlfn.CONCAT($B45,$C45,$D45),$A$73:$C$9993,2,FALSE),0),0) -> 0 | K45: 750 | M45: 750 | O45: =M45 -> 750 | Q45: =O45 -> 750
A46: Background Checks | B46: 00109110 | C46: 503470 | E46: =_xlfn.CONCAT(B46,C46,D46) -> 00109110503470 | G46: =ROUND(IFERROR(VLOOKUP(_xlfn.CONCAT($B46,$C46,$D46),$A$73:$C$9993,3,FALSE),0),0) -> 0 | I46: =ROUND(IFERROR(VLOOKUP(_xlfn.CONCAT($B46,$C46,$D46),$A$73:$C$9993,2,FALSE),0),0) -> 0 | K46: 0 | M46: 0 | O46: =M46 -> 0 | Q46: =O46 -> 0
A47: Educational Incentive | B47: 00109110 | C47: 503901 | E47: =_xlfn.CONCAT(B47,C47,D47) -> 00109110503901 | G47: =ROUND(IFERROR(VLOOKUP(_xlfn.CONCAT($B47,$C47,$D47),$A$73:$C$9993,3,FALSE),0),0) -> 0 | I47: =ROUND(IFERROR(VLOOKUP(_xlfn.CONCAT($B47,$C47,$D47),$A$73:$C$9993,2,FALSE),0),0) -> 442 | K47: 0 | M47: 0 | O47: =M47 -> 0 | Q47: =O47 -> 0
A48: Conferences/Seminars/Meetings | B48: 00109110 | E48: =_xlfn.CONCAT(B48,C48,D48) -> 00109110 | G48: =ROUND(IFERROR(VLOOKUP(_xlfn.CONCAT($B48,$C48,$D48),$A$73:$C$9993,3,FALSE),0),0) -> 0 | I48: =ROUND(IFERROR(VLOOKUP(_xlfn.CONCAT($B48,$C48,$D48),$A$73:$C$9993,2,FALSE),0),0) -> 0 | K48: 0 | M48: 0 | O48: =M48 -> 0 | Q48: =O48 -> 0
A49: Non-Travel Training | B49: 00109110 | C49: 504060 | E49: =_xlfn.CONCAT(B49,C49,D49) -> 00109110504060 | G49: =ROUND(IFERROR(VLOOKUP(_xlfn.CONCAT($B49,$C49,$D49),$A$73:$C$9993,3,FALSE),0),0) -> 1555 | I49: =ROUND(IFERROR(VLOOKUP(_xlfn.CONCAT($B49,$C49,$D49),$A$73:$C$9993,2,FALSE),0),0) -> 7090 | K49: 2500 | M49: 2500 | O49: =M49 -> 2500 | Q49: =O49 -> 2500
A50: Travel Training | B50: 00109110 | C50: 504070 | E50: =_xlfn.CONCAT(B50,C50,D50) -> 00109110504070 | G50: =ROUND(IFERROR(VLOOKUP(_xlfn.CONCAT($B50,$C50,$D50),$A$73:$C$9993,3,FALSE),0),0) -> 2819 | I50: =ROUND(IFERROR(VLOOKUP(_xlfn.CONCAT($B50,$C50,$D50),$A$73:$C$9993,2,FALSE),0),0) -> 5920 | K50: 7000 | M50: 7000 | O50: =M50 -> 7000 | Q50: =O50 -> 7000
A51: Cell Phone, Air Cards, Pagers | B51: 00109110 | E51: =_xlfn.CONCAT(B51,C51,D51) -> 00109110 | G51: =ROUND(IFERROR(VLOOKUP(_xlfn.CONCAT($B51,$C51,$D51),$A$73:$C$9993,3,FALSE),0),0) -> 0 | I51: =ROUND(IFERROR(VLOOKUP(_xlfn.CONCAT($B51,$C51,$D51),$A$73:$C$9993,2,FALSE),0),0) -> 0 | K51: 0 | M51: 0 | O51: =M51 -> 0 | Q51: =O51 -> 0
A52: Communications-Radios | B52: 00109110 | C52: 504124 | E52: =_xlfn.CONCAT(B52,C52,D52) -> 00109110504124 | G52: =ROUND(IFERROR(VLOOKUP(_xlfn.CONCAT($B52,$C52,$D52),$A$73:$C$9993,3,FALSE),0),0) -> 6994 | I52: =ROUND(IFERROR(VLOOKUP(_xlfn.CONCAT($B52,$C52,$D52),$A$73:$C$9993,2,FALSE),0),0) -> 7385 | K52: 8000 | M52: 8000 | O52: =M52 -> 8000 | Q52: =O52 -> 8000
A53: Rentals & Leases-Other | B53: 00109110 | C53: 504401 | E53: =_xlfn.CONCAT(B53,C53,D53) -> 00109110504401 | G53: =ROUND(IFERROR(VLOOKUP(_xlfn.CONCAT($B53,$C53,$D53),$A$73:$C$9993,3,FALSE),0),0) -> 0 | I53: =ROUND(IFERROR(VLOOKUP(_xlfn.CONCAT($B53,$C53,$D53),$A$73:$C$9993,2,FALSE),0),0) -> 0 | K53: 0 | M53: 0 | O53: =M53 -> 0 | Q53: =O53 -> 0
A54: Rental/Lease-Facilities | B54: 00109110 | C54: 504450 | E54: =_xlfn.CONCAT(B54,C54,D54) -> 00109110504450 | G54: =ROUND(IFERROR(VLOOKUP(_xlfn.CONCAT($B54,$C54,$D54),$A$73:$C$9993,3,FALSE),0),0) -> 0 | I54: =ROUND(IFERROR(VLOOKUP(_xlfn.CONCAT($B54,$C54,$D54),$A$73:$C$9993,2,FALSE),0),0) -> 0 | K54: 0 | M54: 0 | O54: =M54 -> 0 | Q54: =O54 -> 0
A55: Printing & Binding | B55: 00109110 | C55: 504710 | E55: =_xlfn.CONCAT(B55,C55,D55) -> 00109110504710 | G55: =ROUND(IFERROR(VLOOKUP(_xlfn.CONCAT($B55,$C55,$D55),$A$73:$C$9993,3,FALSE),0),0) -> 431 | I55: =ROUND(IFERROR(VLOOKUP(_xlfn.CONCAT($B55,$C55,$D55),$A$73:$C$9993,2,FALSE),0),0) -> 316 | K55: 1000 | M55: 1000 | O55: =M55 -> 1000 | Q55: =O55 -> 1000
A56: Office Supplies | B56: 00109110 | C56: 505101 | E56: =_xlfn.CONCAT(B56,C56,D56) -> 00109110505101 | G56: =ROUND(IFERROR(VLOOKUP(_xlfn.CONCAT($B56,$C56,$D56),$A$73:$C$9993,3,FALSE),0),0) -> 4689 | I56: =ROUND(IFERROR(VLOOKUP(_xlfn.CONCAT($B56,$C56,$D56),$A$73:$C$9993,2,FALSE),0),0) -> 5622 | K56: 6000 | M56: 6000 | O56: =M56 -> 6000 | Q56: =O56 -> 6000
A57: Operating Supplies | B57: 00109110 | C57: 505201 | E57: =_xlfn.CONCAT(B57,C57,D57) -> 00109110505201 | G57: =ROUND(IFERROR(VLOOKUP(_xlfn.CONCAT($B57,$C57,$D57),$A$73:$C$9993,3,FALSE),0),0) -> 0 | I57: =ROUND(IFERROR(VLOOKUP(_xlfn.CONCAT($B57,$C57,$D57),$A$73:$C$9993,2,FALSE),0),0) -> 0 | K57: 0 | M57: 0 | O57: =M57 -> 0 | Q57: =O57 -> 0
A58: Safety/First Aid Supplies | B58: 00109110 | C58: 505260 | E58: =_xlfn.CONCAT(B58,C58,D58) -> 00109110505260 | G58: =ROUND(IFERROR(VLOOKUP(_xlfn.CONCAT($B58,$C58,$D58),$A$73:$C$9993,3,FALSE),0),0) -> 373 | I58: =ROUND(IFERROR(VLOOKUP(_xlfn.CONCAT($B58,$C58,$D58),$A$73:$C$9993,2,FALSE),0),0) -> 0 | K58: 2000 | M58: 2000 | O58: =M58 -> 2000 | Q58: =O58 -> 2000
A59: Books/Pubs/Subscrs/Membs | B59: 00109110 | C59: 505401 | E59: =_xlfn.CONCAT(B59,C59,D59) -> 00109110505401 | G59: =ROUND(IFERROR(VLOOKUP(_xlfn.CONCAT($B59,$C59,$D59),$A$73:$C$9993,3,FALSE),0),0)-1 -> 1794 | I59: =ROUND(IFERROR(VLOOKUP(_xlfn.CONCAT($B59,$C59,$D59),$A$73:$C$9993,2,FALSE),0),0)-1 -> 1508 | K59: 2500 | M59: 2500 | O59: =M59 -> 2500 | Q59: =O59 -> 2500
A60: Purchased Uniforms | B60: 00109110 | C60: 505550 | E60: =_xlfn.CONCAT(B60,C60,D60) -> 00109110505550 | G60: =ROUND(IFERROR(VLOOKUP(_xlfn.CONCAT($B60,$C60,$D60),$A$73:$C$9993,3,FALSE),0),0) -> 0 | I60: =ROUND(IFERROR(VLOOKUP(_xlfn.CONCAT($B60,$C60,$D60),$A$73:$C$9993,2,FALSE),0),0) -> 57 | K60: 330 | M60: 330 | O60: =M60 -> 330 | Q60: =O60 -> 330
A61: Office Furn/Fixtures < $5,000 | B61: 00109110 | C61: 505710 | E61: =_xlfn.CONCAT(B61,C61,D61) -> 00109110505710 | G61: =ROUND(IFERROR(VLOOKUP(_xlfn.CONCAT($B61,$C61,$D61),$A$73:$C$9993,3,FALSE),0),0) -> 0 | I61: =ROUND(IFERROR(VLOOKUP(_xlfn.CONCAT($B61,$C61,$D61),$A$73:$C$9993,2,FALSE),0),0) -> 0 | K61: 1500 | M61: 1500 | O61: =M61 -> 1500 | Q61: =O61 -> 1500
A62: Technology Items < $5,000 | B62: 00109110 | C62: 505801 | E62: =_xlfn.CONCAT(B62,C62,D62) -> 00109110505801 | G62: =ROUND(IFERROR(VLOOKUP(_xlfn.CONCAT($B62,$C62,$D62),$A$73:$C$9993,3,FALSE),0),0) -> 0 | I62: =ROUND(IFERROR(VLOOKUP(_xlfn.CONCAT($B62,$C62,$D62),$A$73:$C$9993,2,FALSE),0),0) -> 0 | K62: 0 | M62: 0 | O62: =M62 -> 0 | Q62: =O62 -> 0
A64: Total Operating Expenditures | F64: $ | G64: =SUM(G41:G63) -> 21372 | H64: $ | I64: =SUM(I41:I63) -> 31147 | J64: $ | K64: =SUM(K41:K63) -> 37155 | L64: $ | M64: =SUM(M41:M63) -> 37155 | N64: $ | O64: =SUM(O41:O63) -> 37155 | P64: $ | Q64: =SUM(Q41:Q63) -> 37155
A65: TOTAL BUDGET | F65: $ | G65: =+G64+G24 -> 952114 | H65: $ | I65: =+I64+I24 -> 1009401 | J65: $ | K65: =+K64+K24 -> 1009974 | L65: $ | M65: =+M64+M24 -> 1009974 | N65: $ | O65: =+O64+O24 -> 1009974 | P65: $ | Q65: =+Q64+Q24 -> 1009974
A68: Per GL | G68: 952114 | I68: 1009401
A69: Diff | G69: =G65-G68 -> 0 | I69: =I65-I68 -> 0
B72: 2025 Actual | C72: 2024 Actual | G72: Missing Accounts Check?
A73: 00109110501201 | B73: 715227.03 | C73: 682481.86 | G73: =VLOOKUP(A73,E:E,1,FALSE) -> 00109110501201
A74: 00109110501315 | B74: 11688.75 | C74: 7822.5 | G74: =VLOOKUP(A74,E:E,1,FALSE) -> 00109110501315
A75: 00109110501400 | B75: 2658.12 | C75: 1100.4 | G75: =VLOOKUP(A75,E:E,1,FALSE) -> 00109110501400
A76: 00109110501401 | B76: 0 | C76: 0 | G76: =VLOOKUP(A76,E:E,1,FALSE) -> 00109110501401
A77: 00109110501600 | B77: 0 | C77: 0 | G77: =VLOOKUP(A77,E:E,1,FALSE) -> 00109110501600
A78: 00109110501701 | B78: 12048.89 | C78: 12040.18 | G78: =VLOOKUP(A78,E:E,1,FALSE) -> 00109110501701
A79: 00109110501702 | B79: 6810.57 | C79: 6623.18 | G79: =VLOOKUP(A79,E:E,1,FALSE) -> 00109110501702
A80: 00109110501800 | B80: 0 | C80: 0 | G80: =VLOOKUP(A80,E:E,1,FALSE) -> 00109110501800
A81: 00109110502100 | B81: 56287.76 | C81: 53676.55 | G81: =VLOOKUP(A81,E:E,1,FALSE) -> 00109110502100
A82: 00109110502100CIALS | B82: 0 | C82: 0 | G82: =VLOOKUP(A82,E:E,1,FALSE) -> #N/A
A83: 00109110502200 | B83: 84375.34 | C83: 83410.28 | G83: =VLOOKUP(A83,E:E,1,FALSE) -> 00109110502200
A84: 00109110502300 | B84: 87747.99 | C84: 82198.65 | G84: =VLOOKUP(A84,E:E,1,FALSE) -> 00109110502300
... A108: 00109110999999 | B108: 0 | C108: 0 | G108: =VLOOKUP(A108,E:E,1,FALSE) -> #N/A

Sheet 912 Eastmonte
A1: City of Altamonte Springs, Florida
A2: ='[1]Admin Summary'!A2:K2 -> Fiscal Year 2026 / 2027 Annual Budget
A4: Leisure and Maintenance Services Department
A5: Eastmonte Park
A6: General Fund (00109120)
M8: =' 911 Admin'!M8 -> 2027
G9: =' 911 Admin'!G9 -> 2024 | I9: =' 911 Admin'!I9 -> 2025 | K9: =' 911 Admin'!K9 -> 2026 | M9: Department | O9: Manager | Q9: Commission
B10: Org | C10: Obj | D10: Proj | G10: Actual | I10: Actual | K10: Budget | M10: Requested | O10: Recommended | Q10: Adopted | R10: Notes
A11: PERSONNEL SERVICES
A12: Regular Salaries & Wages | B12: 00109120 | C12: 501201 | E12: =_xlfn.CONCAT(B12,C12,D12) -> 00109120501201 | F12: $ | G12: =ROUND(IFERROR(VLOOKUP(_xlfn.CONCAT($B12,$C12,$D12),$A$66:$C$9993,3,FALSE),0),0) -> 0 | H12: $ | I12: =ROUND(IFERROR(VLOOKUP(_xlfn.CONCAT($B12,$C12,$D12),$A$66:$C$9993,2,FALSE),0),0) -> 428 | J12: $ | K12: 0 | L12: $ | M12: ='[1]Payroll Summary by Department'!C61 -> 0 | N12: $ | O12: =M12 -> 0 | P12: $ | Q12: =O12 -> 0
A13: Limited Term Employee Wages | B13: 00109120 | C13: 501305 | E13: =_xlfn.CONCAT(B13,C13,D13) -> 00109120501305 | G13: =ROUND(IFERROR(VLOOKUP(_xlfn.CONCAT($B13,$C13,$D13),$A$66:$C$9993,3,FALSE),0),0) -> 18236 | I13: =ROUND(IFERROR(VLOOKUP(_xlfn.CONCAT($B13,$C13,$D13),$A$66:$C$9993,2,FALSE),0),0) -> 20223 | K13: 25000 | M13: 25000 | O13: =M13 -> 25000 | Q13: =O13 -> 25000
A14: Overtime | B14: 00109120 | C14: 501400 | E14: =_xlfn.CONCAT(B14,C14,D14) -> 00109120501400 | G14: =ROUND(IFERROR(VLOOKUP(_xlfn.CONCAT($B14,$C14,$D14),$A$66:$C$9993,3,FALSE),0),0) -> 43 | I14: =ROUND(IFERROR(VLOOKUP(_xlfn.CONCAT($B14,$C14,$D14),$A$66:$C$9993,2,FALSE),0),0) -> 275 | K14: 0 | M14: 0 | O14: =M14 -> 0 | Q14: =O14 -> 0
A15: Add Pays | B15: 00109120 | C15: 501600 | E15: =_xlfn.CONCAT(B15,C15,D15) -> 00109120501600 | G15: =ROUND(IFERROR(VLOOKUP(_xlfn.CONCAT($B15,$C15,$D15),$A$66:$C$9993,3,FALSE),0),0) -> 0 | I15: =ROUND(IFERROR(VLOOKUP(_xlfn.CONCAT($B15,$C15,$D15),$A$66:$C$9993,2,FALSE),0),0) -> 0 | K15: 0 | M15: ='[1]Payroll Summary by Department'!I61 -> 0 | O15: =M15 -> 0 | Q15: =O15 -> 0
A16: Uniform Allowance | B16: 00109120 | C16: 501800 | E16: =_xlfn.CONCAT(B16,C16,D16) -> 00109120501800 | G16: =ROUND(IFERROR(VLOOKUP(_xlfn.CONCAT($B16,$C16,$D16),$A$66:$C$9993,3,FALSE),0),0) -> 0 | I16: =ROUND(IFERROR(VLOOKUP(_xlfn.CONCAT($B16,$C16,$D16),$A$66:$C$9993,2,FALSE),0),0) -> 0 | K16: 0 | M16: 0 | O16: =M16 -> 0 | Q16: =O16 -> 0
A17: FICA Taxes | B17: 00109120 | C17: 502100 | E17: =_xlfn.CONCAT(B17,C17,D17) -> 00109120502100 | G17: =ROUND(IFERROR(VLOOKUP(_xlfn.CONCAT($B17,$C17,$D17),$A$66:$C$9993,3,FALSE),0),0) -> 1398 | I17: =ROUND(IFERROR(VLOOKUP(_xlfn.CONCAT($B17,$C17,$D17),$A$66:$C$9993,2,FALSE),0),0) -> 1601 | K17: 1913 | M17: ='[1]Payroll Summary by Department'!N61 -> 1913 | O17: =M17 -> 1913 | Q17: =O17 -> 1913
A18: Retirement Contributions | B18: 00109120 | C18: 502200 | E18: =_xlfn.CONCAT(B18,C18,D18) -> 00109120502200 | G18: =ROUND(IFERROR(VLOOKUP(_xlfn.CONCAT($B18,$C18,$D18),$A$66:$C$9993,3,FALSE),0),0) -> 0 | I18: =ROUND(IFERROR(VLOOKUP(_xlfn.CONCAT($B18,$C18,$D18),$A$66:$C$9993,2,FALSE),0),0) -> 0 | K18: 0 | M18: ='[1]Payroll Summary by Department'!O61+'[1]Payroll Summary by Department'!P61 -> 0 | O18: =M18 -> 0 | Q18: =O18 -> 0
A19: Health Insurance | B19: 00109120 | C19: 502300 | E19: =_xlfn.CONCAT(B19,C19,D19) -> 00109120502300 | G19: =ROUND(IFERROR(VLOOKUP(_xlfn.CONCAT($B19,$C19,$D19),$A$66:$C$9993,3,FALSE),0),0) -> 0 | I19: =ROUND(IFERROR(VLOOKUP(_xlfn.CONCAT($B19,$C19,$D19),$A$66:$C$9993,2,FALSE),0),0) -> 0 | K19: 0 | M19: ='[1]Payroll Summary by Department'!Q61 -> 0 | O19: =M19 -> 0 | Q19: =O19 -> 0
A20: Life Insurance | B20: 00109120 | C20: 502400 | E20: =_xlfn.CONCAT(B20,C20,D20) -> 00109120502400 | G20: =ROUND(IFERROR(VLOOKUP(_xlfn.CONCAT($B20,$C20,$D20),$A$66:$C$9993,3,FALSE),0),0) -> 0 | I20: =ROUND(IFERROR(VLOOKUP(_xlfn.CONCAT($B20,$C20,$D20),$A$66:$C$9993,2,FALSE),0),0) -> 0 | K20: 0 | M20: ='[1]Payroll Summary by Department'!R61 -> 0 | O20: =M20 -> 0 | Q20: =O20 -> 0
A21: Total Personnel Services | E21: =_xlfn.CONCAT(B21,C21,D21) | F21: $ | G21: =SUM(G12:G20) -> 19677 | H21: $ | I21: =SUM(I12:I20) -> 22527 | J21: $ | K21: =SUM(K12:K20) -> 26913 | L21: $ | M21: =SUM(M12:M20) -> 26913 | N21: $ | O21: =SUM(O12:O20) -> 26913 | P21: $ | Q21: =SUM(Q12:Q20) -> 26913
A22: POSITION ROSTER | E22: =_xlfn.CONCAT(B22,C22,D22)
A23: Full-Time Employees | E23: =_xlfn.CONCAT(B23,C23,D23)
A24: Staff Assistant | C24: 4C | E24: =_xlfn.CONCAT(B24,C24,D24) -> 4C | G24: 0 | I24: 0 | K24: 0 | M24: 0 | O24: =M24 -> 0 | Q24: =O24 -> 0
A25: Total Positions | E25: =_xlfn.CONCAT(B25,C25,D25) | G25: =SUM(G24:G24) -> 0 | I25: =SUM(I24:I24) -> 0 | K25: =SUM(K24:K24) -> 0 | M25: =SUM(M24:M24) -> 0 | O25: =SUM(O24:O24) -> 0 | Q25: =SUM(Q24:Q24) -> 0
A26: OPERATING EXPENDITURES | E26: =_xlfn.CONCAT(B26,C26,D26)
A27: Other Services-Bank Fees | B27: 00109120 | C27: 503415 | E27: =_xlfn.CONCAT(B27,C27,D27) -> 00109120503415 | F27: $ | G27: =ROUND(IFERROR(VLOOKUP(_xlfn.CONCAT($B27,$C27,$D27),$A$66:$C$9993,3,FALSE),0),0) -> 0 | H27: $ | I27: =ROUND(IFERROR(VLOOKUP(_xlfn.CONCAT($B27,$C27,$D27),$A$66:$C$9993,2,FALSE),0),0) -> 0 | J27: $ | K27: 0 | L27: $ | M27: 0 | N27: $ | O27: =M27 -> 0 | P27: $ | Q27: =O27 -> 0
A28: Other Services-Temporary Labor | B28: 00109120 | C28: 503450 | E28: =_xlfn.CONCAT(B28,C28,D28) -> 00109120503450 | G28: =ROUND(IFERROR(VLOOKUP(_xlfn.CONCAT($B28,$C28,$D28),$A$66:$C$9993,3,FALSE),0),0) -> 0 | I28: =ROUND(IFERROR(VLOOKUP(_xlfn.CONCAT($B28,$C28,$D28),$A$66:$C$9993,2,FALSE),0),0) -> 0 | K28: 0 | M28: 0 | O28: =M28 -> 0 | Q28: =O28 -> 0
A29: Other Contractural Services | B29: 00109120 | C29: 503499 | E29: =_xlfn.CONCAT(B29,C29,D29) -> 00109120503499 | F29: $ | G29: =ROUND(IFERROR(VLOOKUP(_xlfn.CONCAT($B29,$C29,$D29),$A$66:$C$9993,3,FALSE),0),0) -> 0 | H29: $ | I29: =ROUND(IFERROR(VLOOKUP(_xlfn.CONCAT($B29,$C29,$D29),$A$66:$C$9993,2,FALSE),0),0) -> 0 | J29: $ | K29: 1600 | L29: $ | M29: 1600 | N29: $ | O29: =M29 -> 1600 | P29: $ | Q29: =O29 -> 1600
A30: Rental/Lease-Equipment | B30: 00109120 | C30: 504430 | E30: =_xlfn.CONCAT(B30,C30,D30) -> 00109120504430 | G30: =ROUND(IFERROR(VLOOKUP(_xlfn.CONCAT($B30,$C30,$D30),$A$66:$C$9993,3,FALSE),0),0) -> 0 | I30: =ROUND(IFERROR(VLOOKUP(_xlfn.CONCAT($B30,$C30,$D30),$A$66:$C$9993,2,FALSE),0),0) -> 0 | K30: 0 | M30: 0 | O30: =M30 -> 0 | Q30: =O30 -> 0
A31: Repair/Maint-Bldgs/ Facilities | B31: 00109120 | C31: 504601 | E31: =_xlfn.CONCAT(B31,C31,D31) -> 00109120504601 | G31: =ROUND(IFERROR(VLOOKUP(_xlfn.CONCAT($B31,$C31,$D31),$A$66:$C$9993,3,FALSE),0),0) -> 0 | I31: =ROUND(IFERROR(VLOOKUP(_xlfn.CONCAT($B31,$C31,$D31),$A$66:$C$9993,2,FALSE),0),0) -> 2997 | K31: 0 | M31: 0 | O31: =M31 -> 0 | Q31: =O31 -> 0
A32: Replace Signage | B32: 00109120 | E32: =_xlfn.CONCAT(B32,C32,D32) -> 00109120 | G32: =ROUND(IFERROR(VLOOKUP(_xlfn.CONCAT($B32,$C32,$D32),$A$66:$C$9993,3,FALSE),0),0) -> 0 | I32: =ROUND(IFERROR(VLOOKUP(_xlfn.CONCAT($B32,$C32,$D32),$A$66:$C$9993,2,FALSE),0),0) -> 0 | K32: 3000 | M32: 3000 | O32: =M32 -> 3000 | Q32: =O32 -> 3000
A33: Repair/Maint-Fencing/Security | B33: 00109120 | C33: 504602 | E33: =_xlfn.CONCAT(B33,C33,D33) -> 00109120504602 | G33: =ROUND(IFERROR(VLOOKUP(_xlfn.CONCAT($B33,$C33,$D33),$A$66:$C$9993,3,FALSE),0),0) -> 720 | I33: =ROUND(IFERROR(VLOOKUP(_xlfn.CONCAT($B33,$C33,$D33),$A$66:$C$9993,2,FALSE),0),0) -> 360 | K33: 5000 | M33: 5000 | O33: =M33 -> 5000 | Q33: =O33 -> 5000
A34: Repair/Maint-Civic Center | B34: 00109120 | C34: 504605 | E34: =_xlfn.CONCAT(B34,C34,D34) -> 00109120504605 | G34: =ROUND(IFERROR(VLOOKUP(_xlfn.CONCAT($B34,$C34,$D34),$A$66:$C$9993,3,FALSE),0),0) -> 0 | I34: =ROUND(IFERROR(VLOOKUP(_xlfn.CONCAT($B34,$C34,$D34),$A$66:$C$9993,2,FALSE),0),0) -> 79 | K34: 0 | M34: 0 | O34: =M34 -> 0 | Q34: =O34 -> 0
A35: Repair/Maint-Ballfield | B35: 00109120 | C35: 504610 | E35: =_xlfn.CONCAT(B35,C35,D35) -> 00109120504610 | G35: =ROUND(IFERROR(VLOOKUP(_xlfn.CONCAT($B35,$C35,$D35),$A$66:$C$9993,3,FALSE),0),0) -> 9860 | I35: =ROUND(IFERROR(VLOOKUP(_xlfn.CONCAT($B35,$C35,$D35),$A$66:$C$9993,2,FALSE),0),0) -> 6525 | K35: 0 | M35: 0 | O35: =M35 -> 0 | Q35: =O35 -> 0
A36: Synthetic Turf Maintenance Program | B36: 00109120 | E36: =_xlfn.CONCAT(B36,C36,D36) -> 00109120 | G36: =ROUND(IFERROR(VLOOKUP(_xlfn.CONCAT($B36,$C36,$D36),$A$66:$C$9993,3,FALSE),0),0) -> 0 | I36: =ROUND(IFERROR(VLOOKUP(_xlfn.CONCAT($B36,$C36,$D36),$A$66:$C$9993,2,FALSE),0),0) -> 0 | K36: 5500 | M36: 5500 | O36: =M36 -> 5500 | Q36: =O36 -> 5500
A37: Synthetic Turf Crumb Rubber | B37: 00109120 | E37: =_xlfn.CONCAT(B37,C37,D37) -> 00109120 | G37: =ROUND(IFERROR(VLOOKUP(_xlfn.CONCAT($B37,$C37,$D37),$A$66:$C$9993,3,FALSE),0),0) -> 0 | I37: =ROUND(IFERROR(VLOOKUP(_xlfn.CONCAT($B37,$C37,$D37),$A$66:$C$9993,2,FALSE),0),0) -> 0 | K37: 3000 | M37: 3000 | O37: =M37 -> 3000 | Q37: =O37 -> 3000
A38: Repair/Maint-Equipment | B38: 00109120 | C38: 504620 | E38: =_xlfn.CONCAT(B38,C38,D38) -> 00109120504620 | G38: =ROUND(IFERROR(VLOOKUP(_xlfn.CONCAT($B38,$C38,$D38),$A$66:$C$9993,3,FALSE),0),0) -> 5621 | I38: =ROUND(IFERROR(VLOOKUP(_xlfn.CONCAT($B38,$C38,$D38),$A$66:$C$9993,2,FALSE),0),0) -> 5322 | K38: 0 | M38: 0 | O38: =M38 -> 0 | Q38: =O38 -> 0
A39: Playground | B39: 00109120 | E39: =_xlfn.CONCAT(B39,C39,D39) -> 00109120 | G39: =ROUND(IFERROR(VLOOKUP(_xlfn.CONCAT($B39,$C39,$D39),$A$66:$C$9993,3,FALSE),0),0) -> 0 | I39: =ROUND(IFERROR(VLOOKUP(_xlfn.CONCAT($B39,$C39,$D39),$A$66:$C$9993,2,FALSE),0),0) -> 0 | K39: 5000 | M39: 5000 | O39: =M39 -> 5000 | Q39: =O39 -> 5000
A40: Groundcover | B40: 00109120 | E40: =_xlfn.CONCAT(B40,C40,D40) -> 00109120 | G40: =ROUND(IFERROR(VLOOKUP(_xlfn.CONCAT($B40,$C40,$D40),$A$66:$C$9993,3,FALSE),0),0) -> 0 | I40: =ROUND(IFERROR(VLOOKUP(_xlfn.CONCAT($B40,$C40,$D40),$A$66:$C$9993,2,FALSE),0),0) -> 0 | K40: 5000 | M40: 5000 | O40: =M40 -> 5000 | Q40: =O40 -> 5000
A41: ThorGuard | B41: 00109120 | E41: =_xlfn.CONCAT(B41,C41,D41) -> 00109120 | G41: =ROUND(IFERROR(VLOOKUP(_xlfn.CONCAT($B41,$C41,$D41),$A$66:$C$9993,3,FALSE),0),0) -> 0 | I41: =ROUND(IFERROR(VLOOKUP(_xlfn.CONCAT($B41,$C41,$D41),$A$66:$C$9993,2,FALSE),0),0) -> 0 | K41: 5000 | M41: 5000 | O41: =M41 -> 5000 | Q41: =O41 -> 5000
A42: Repair/Maint-Hardscape | B42: 00109120 | C42: 504675 | E42: =_xlfn.CONCAT(B42,C42,D42) -> 00109120504675 | G42: =ROUND(IFERROR(VLOOKUP(_xlfn.CONCAT($B42,$C42,$D42),$A$66:$C$9993,3,FALSE),0),0) -> 0 | I42: =ROUND(IFERROR(VLOOKUP(_xlfn.CONCAT($B42,$C42,$D42),$A$66:$C$9993,2,FALSE),0),0) -> 0 | K42: 6000 | M42: 6000 | O42: =M42 -> 6000 | Q42: =O42 -> 6000
A43: Repair/Maint-Technology | B43: 00109120 | C43: 504683 | E43: =_xlfn.CONCAT(B43,C43,D43) -> 00109120504683 | G43: =ROUND(IFERROR(VLOOKUP(_xlfn.CONCAT($B43,$C43,$D43),$A$66:$C$9993,3,FALSE),0),0) -> 2220 | I43: =ROUND(IFERROR(VLOOKUP(_xlfn.CONCAT($B43,$C43,$D43),$A$66:$C$9993,2,FALSE),0),0) -> 8763 | K43: 0 | M43: 0 | O43: =M43 -> 0 | Q43: =O43 -> 0
A44: Audio/Visual | B44: 00109120 | E44: =_xlfn.CONCAT(B44,C44,D44) -> 00109120 | G44: =ROUND(IFERROR(VLOOKUP(_xlfn.CONCAT($B44,$C44,$D44),$A$66:$C$9993,3,FALSE),0),0) -> 0 | I44: =ROUND(IFERROR(VLOOKUP(_xlfn.CONCAT($B44,$C44,$D44),$A$66:$C$9993,2,FALSE),0),0) -> 0 | K44: 3000 | M44: 3000 | O44: =M44 -> 3000 | Q44: =O44 -> 3000
A45: Repair/Maint-Other | B45: 00109120 | C45: 504699 | E45: =_xlfn.CONCAT(B45,C45,D45) -> 00109120504699 | G45: =ROUND(IFERROR(VLOOKUP(_xlfn.CONCAT($B45,$C45,$D45),$A$66:$C$9993,3,FALSE),0),0) -> 6540 | I45: =ROUND(IFERROR(VLOOKUP(_xlfn.CONCAT($B45,$C45,$D45),$A$66:$C$9993,2,FALSE),0),0) -> 3668 | K45: 4000 | M45: 4000 | O45: =M45 -> 4000 | Q45: =O45 -> 4000
A46: Operating Supplies | B46: 00109120 | C46: 505201 | E46: =_xlfn.CONCAT(B46,C46,D46) -> 00109120505201 | G46: =ROUND(IFERROR(VLOOKUP(_xlfn.CONCAT($B46,$C46,$D46),$A$66:$C$9993,3,FALSE),0),0) -> 1875 | I46: =ROUND(IFERROR(VLOOKUP(_xlfn.CONCAT($B46,$C46,$D46),$A$66:$C$9993,2,FALSE),0),0) -> 313 | K46: 0 | M46: 0 | O46: =M46 -> 0 | Q46: =O46 -> 0
A47: Rental Uniforms | B47: 00109120 | C47: 505505 | E47: =_xlfn.CONCAT(B47,C47,D47) -> 00109120505505 | G47: =ROUND(IFERROR(VLOOKUP(_xlfn.CONCAT($B47,$C47,$D47),$A$66:$C$9993,3,FALSE),0),0) -> 0 | I47: =ROUND(IFERROR(VLOOKUP(_xlfn.CONCAT($B47,$C47,$D47),$A$66:$C$9993,2,FALSE),0),0) -> 0 | K47: 0 | M47: 0 | O47: =M47 -> 0 | Q47: =O47 -> 0
A48: Boots/Shoes | B48: 00109120 | C48: 505532 | E48: =_xlfn.CONCAT(B48,C48,D48) -> 00109120505532 | G48: =ROUND(IFERROR(VLOOKUP(_xlfn.CONCAT($B48,$C48,$D48),$A$66:$C$9993,3,FALSE),0),0) -> 0 | I48: =ROUND(IFERROR(VLOOKUP(_xlfn.CONCAT($B48,$C48,$D48),$A$66:$C$9993,2,FALSE),0),0) -> 0 | K48: 0 | M48: 0 | O48: =M48 -> 0 | Q48: =O48 -> 0
A49: Safety Uniforms | B49: 00109120 | C49: 505540 | E49: =_xlfn.CONCAT(B49,C49,D49) -> 00109120505540 | G49: =ROUND(IFERROR(VLOOKUP(_xlfn.CONCAT($B49,$C49,$D49),$A$66:$C$9993,3,FALSE),0),0) -> 0 | I49: =ROUND(IFERROR(VLOOKUP(_xlfn.CONCAT($B49,$C49,$D49),$A$66:$C$9993,2,FALSE),0),0) -> 0 | K49: 0 | M49: 0 | O49: =M49 -> 0 | Q49: =O49 -> 0
A50: Purchased Uniforms | B50: 00109120 | C50: 505550 | E50: =_xlfn.CONCAT(B50,C50,D50) -> 00109120505550 | G50: =ROUND(IFERROR(VLOOKUP(_xlfn.CONCAT($B50,$C50,$D50),$A$66:$C$9993,3,FALSE),0),0) -> 0 | I50: =ROUND(IFERROR(VLOOKUP(_xlfn.CONCAT($B50,$C50,$D50),$A$66:$C$9993,2,FALSE),0),0) -> 0 | K50: 0 | M50: 0 | O50: =M50 -> 0 | Q50: =O50 -> 0
A51: Propane/Diesel | B51: 00109120 | C51: 505602 | E51: =_xlfn.CONCAT(B51,C51,D51) -> 00109120505602 | G51: =ROUND(IFERROR(VLOOKUP(_xlfn.CONCAT($B51,$C51,$D51),$A$66:$C$9993,3,FALSE),0),0) -> 0 | I51: =ROUND(IFERROR(VLOOKUP(_xlfn.CONCAT($B51,$C51,$D51),$A$66:$C$9993,2,FALSE),0),0) -> 91 | K51: 200 | M51: 200 | O51: =M51 -> 200 | Q51: =O51 -> 200
A52: Office Furn/Fixtures < $5,000 | B52: 00109120 | C52: 505710 | E52: =_xlfn.CONCAT(B52,C52,D52) -> 00109120505710 | G52: =ROUND(IFERROR(VLOOKUP(_xlfn.CONCAT($B52,$C52,$D52),$A$66:$C$9993,3,FALSE),0),0) -> 0 | I52: =ROUND(IFERROR(VLOOKUP(_xlfn.CONCAT($B52,$C52,$D52),$A$66:$C$9993,2,FALSE),0),0) -> 3708 | K52: 0 | M52: 0 | O52: =M52 -> 0 | Q52: =O52 -> 0
A53: Park Equipment < $5,000 | B53: 00109120 | C53: 505750 | E53: =_xlfn.CONCAT(B53,C53,D53) -> 00109120505750 | G53: =ROUND(IFERROR(VLOOKUP(_xlfn.CONCAT($B53,$C53,$D53),$A$66:$C$9993,3,FALSE),0),0) -> 1939 | I53: =ROUND(IFERROR(VLOOKUP(_xlfn.CONCAT($B53,$C53,$D53),$A$66:$C$9993,2,FALSE),0),0) -> 8252 | K53: 1300 | M53: 1300 | O53: =M53 -> 1300 | Q53: =O53 -> 1300
A54: Auditorium Tables/Chairs | B54: 00109120 | E54: =_xlfn.CONCAT(B54,C54,D54) -> 00109120 | G54: =ROUND(IFERROR(VLOOKUP(_xlfn.CONCAT($B54,$C54,$D54),$A$66:$C$9993,3,FALSE),0),0) -> 0 | I54: =ROUND(IFERROR(VLOOKUP(_xlfn.CONCAT($B54,$C54,$D54),$A$66:$C$9993,2,FALSE),0),0) -> 0 | K54: 6000 | M54: 6000 | O54: =M54 -> 6000 | Q54: =O54 -> 6000
A55: Technology Items < $5,000 | B55: 00109120 | C55: 505801 | E55: =_xlfn.CONCAT(B55,C55,D55) -> 00109120505801 | G55: =ROUND(IFERROR(VLOOKUP(_xlfn.CONCAT($B55,$C55,$D55),$A$66:$C$9993,3,FALSE),0),0) -> 1725 | I55: =ROUND(IFERROR(VLOOKUP(_xlfn.CONCAT($B55,$C55,$D55),$A$66:$C$9993,2,FALSE),0),0)-2 -> 2840 | K55: 0 | M55: 0 | O55: =M55 -> 0 | Q55: =O55 -> 0
A57: Total Operating Expenditures | F57: $ | G57: =SUM(G27:G56) -> 30500 | H57: $ | I57: =SUM(I27:I56) -> 42918 | J57: $ | K57: =SUM(K27:K56) -> 53600 | L57: $ | M57: =SUM(M27:M56) -> 53600 | N57: $ | O57: =SUM(O27:O56) -> 53600 | P57: $ | Q57: =SUM(Q27:Q56) -> 53600
A58: TOTAL BUDGET | F58: $ | G58: =+G21+G57 -> 50177 | H58: $ | I58: =+I21+I57 -> 65445 | J58: $ | K58: =+K21+K57 -> 80513 | L58: $ | M58: =+M21+M57 -> 80513 | N58: $ | O58: =+O21+O57 -> 80513 | P58: $ | Q58: =+Q21+Q57 -> 80513
A61: Per GL | G61: 50177 | I61: 65445
A62: Diff | G62: =G58-G61 -> 0 | I62: =I58-I61 -> 0
B65: 2025 Actual | C65: 2024 Actual | G65: Missing Accounts Check?
A66: 00109120501201 | B66: 427.5 | C66: 0 | G66: =VLOOKUP(A66,E:E,1,FALSE) -> 00109120501201
A67: 00109120501305 | B67: 20222.58 | C67: 18236.08 | G67: =VLOOKUP(A67,E:E,1,FALSE) -> 00109120501305
A68: 00109120501400 | B68: 274.61 | C68: 43 | G68: =VLOOKUP(A68,E:E,1,FALSE) -> 00109120501400
A69: 00109120501600 | B69: 0 | C69: 0 | G69: =VLOOKUP(A69,E:E,1,FALSE) -> 00109120501600
A70: 00109120501800 | B70: 0 | C70: 0 | G70: =VLOOKUP(A70,E:E,1,FALSE) -> 00109120501800
A71: 00109120502100 | B71: 1600.8 | C71: 1398.38 | G71: =VLOOKUP(A71,E:E,1,FALSE) -> 00109120502100
A72: 00109120502200 | B72: 0 | C72: 0 | G72: =VLOOKUP(A72,E:E,1,FALSE) -> 00109120502200
A73: 00109120502300 | B73: 0 | C73: 0 | G73: =VLOOKUP(A73,E:E,1,FALSE) -> 00109120502300
A74: 00109120502400 | B74: 0 | C74: 0 | G74: =VLOOKUP(A74,E:E,1,FALSE) -> 00109120502400
A75: 00109120503415 | B75: 0 | C75: 0 | G75: =VLOOKUP(A75,E:E,1,FALSE) -> 00109120503415
A76: 00109120503450 | B76: 0 | C76: 0 | G76: =VLOOKUP(A76,E:E,1,FALSE) -> 00109120503450
A77: 00109120503499 | B77: 0 | C77: 0 | G77: =VLOOKUP(A77,E:E,1,FALSE) -> 00109120503499
... A102: 00109120999999 | B102: 0 | C102: 0 | G102: =VLOOKUP(A102,E:E,1,FALSE) -> #N/A

Sheet  913 Merrill
A1: City of Altamonte Springs, Florida
A2: ='[1]Admin Summary'!A2:K2 -> Fiscal Year 2026 / 2027 Annual Budget
A4: Leisure and Maintenance Services Department
A5: Merrill Park
A6: General Fund (00109130)
M8: =' 911 Admin'!M8 -> 2027
G9: =' 911 Admin'!G9 -> 2024 | I9: =' 911 Admin'!I9 -> 2025 | K9: =' 911 Admin'!K9 -> 2026 | M9: Department | O9: Manager | Q9: Commission
B10: Org | C10: Obj | D10: Proj | G10: Actual | I10: Actual | K10: Budget | M10: Requested | O10: Recommended | Q10: Adopted | R10: Notes
A11: PERSONAL SERVICES
A12: Regular Salaries & Wages | B12: 00109130 | C12: 501201 | E12: =_xlfn.CONCAT(B12,C12,D12) -> 00109130501201 | F12: $ | G12: =ROUND(IFERROR(VLOOKUP(_xlfn.CONCAT($B12,$C12,$D12),$A$53:$C$9993,3,FALSE),0),0) -> 0 | H12: $ | I12: =ROUND(IFERROR(VLOOKUP(_xlfn.CONCAT($B12,$C12,$D12),$A$53:$C$9993,2,FALSE),0),0) -> 0 | J12: $ | K12: 0 | L12: $ | M12: ='[1]Payroll Summary by Department'!C62 -> 0 | N12: $ | O12: =M12 -> 0 | P12: $ | Q12: =O12 -> 0
A13: Overtime | B13: 00109130 | C13: 501400 | E13: =_xlfn.CONCAT(B13,C13,D13) -> 00109130501400 | G13: =ROUND(IFERROR(VLOOKUP(_xlfn.CONCAT($B13,$C13,$D13),$A$53:$C$9993,3,FALSE),0),0) -> 0 | I13: =ROUND(IFERROR(VLOOKUP(_xlfn.CONCAT($B13,$C13,$D13),$A$53:$C$9993,2,FALSE),0),0) -> 0 | K13: 0 | M13: 0 | O13: =M13 -> 0 | Q13: =O13 -> 0
A14: Uniform Allowance | B14: 00109130 | C14: 501800 | E14: =_xlfn.CONCAT(B14,C14,D14) -> 00109130501800 | G14: =ROUND(IFERROR(VLOOKUP(_xlfn.CONCAT($B14,$C14,$D14),$A$53:$C$9993,3,FALSE),0),0) -> 0 | I14: =ROUND(IFERROR(VLOOKUP(_xlfn.CONCAT($B14,$C14,$D14),$A$53:$C$9993,2,FALSE),0),0) -> 0 | K14: 0 | M14: 0 | O14: =M14 -> 0 | Q14: =O14 -> 0
A15: FICA Taxes | B15: 00109130 | C15: 502100 | E15: =_xlfn.CONCAT(B15,C15,D15) -> 00109130502100 | G15: =ROUND(IFERROR(VLOOKUP(_xlfn.CONCAT($B15,$C15,$D15),$A$53:$C$9993,3,FALSE),0),0) -> 0 | I15: =ROUND(IFERROR(VLOOKUP(_xlfn.CONCAT($B15,$C15,$D15),$A$53:$C$9993,2,FALSE),0),0) -> 0 | K15: 0 | M15: ='[1]Payroll Summary by Department'!N62 -> 0 | O15: =M15 -> 0 | Q15: =O15 -> 0
A16: Retirement Contributions | B16: 00109130 | C16: 502200 | E16: =_xlfn.CONCAT(B16,C16,D16) -> 00109130502200 | G16: =ROUND(IFERROR(VLOOKUP(_xlfn.CONCAT($B16,$C16,$D16),$A$53:$C$9993,3,FALSE),0),0) -> 0 | I16: =ROUND(IFERROR(VLOOKUP(_xlfn.CONCAT($B16,$C16,$D16),$A$53:$C$9993,2,FALSE),0),0) -> 0 | K16: 0 | M16: ='[1]Payroll Summary by Department'!O62+'[1]Payroll Summary by Department'!P62 -> 0 | O16: =M16 -> 0 | Q16: =O16 -> 0
A17: Health Insurance | B17: 00109130 | C17: 502300 | E17: =_xlfn.CONCAT(B17,C17,D17) -> 00109130502300 | G17: =ROUND(IFERROR(VLOOKUP(_xlfn.CONCAT($B17,$C17,$D17),$A$53:$C$9993,3,FALSE),0),0) -> 0 | I17: =ROUND(IFERROR(VLOOKUP(_xlfn.CONCAT($B17,$C17,$D17),$A$53:$C$9993,2,FALSE),0),0) -> 0 | K17: 0 | M17: ='[1]Payroll Summary by Department'!Q62 -> 0 | O17: =M17 -> 0 | Q17: =O17 -> 0
A18: Life Insurance | B18: 00109130 | C18: 502400 | E18: =_xlfn.CONCAT(B18,C18,D18) -> 00109130502400 | G18: =ROUND(IFERROR(VLOOKUP(_xlfn.CONCAT($B18,$C18,$D18),$A$53:$C$9993,3,FALSE),0),0) -> 0 | I18: =ROUND(IFERROR(VLOOKUP(_xlfn.CONCAT($B18,$C18,$D18),$A$53:$C$9993,2,FALSE),0),0) -> 0 | K18: 0 | M18: ='[1]Payroll Summary by Department'!R62 -> 0 | O18: =M18 -> 0 | Q18: =O18 -> 0
A19: Total Personal Services | E19: =_xlfn.CONCAT(B19,C19,D19) | F19: $ | G19: =SUM(G12:G18) -> 0 | H19: $ | I19: =SUM(I12:I18) -> 0 | J19: $ | K19: =SUM(K12:K18) -> 0 | L19: $ | M19: =SUM(M12:M18) -> 0 | N19: $ | O19: =SUM(O12:O18) -> 0 | P19: $ | Q19: =SUM(Q12:Q18) -> 0
A20: POSITION ROSTER | E20: =_xlfn.CONCAT(B20,C20,D20)
A21: Full Time Employees | E21: =_xlfn.CONCAT(B21,C21,D21) | G21: 0 | I21: 0 | K21: 0 | M21: 0 | O21: =M21 -> 0
A22: Total Positions | E22: =_xlfn.CONCAT(B22,C22,D22) | G22: =SUM(G21:G21) -> 0 | I22: =SUM(I21:I21) -> 0 | K22: =SUM(K21:K21) -> 0 | M22: =SUM(M21:M21) -> 0 | O22: =SUM(O21:O21) -> 0
A23: OPERATING EXPENDITURES | E23: =_xlfn.CONCAT(B23,C23,D23)
A24: Professional Services-Architectural | B24: 00109130 | C24: 503140 | E24: =_xlfn.CONCAT(B24,C24,D24) -> 00109130503140 | F24: $ | G24: =ROUND(IFERROR(VLOOKUP(_xlfn.CONCAT($B24,$C24,$D24),$A$53:$C$9993,3,FALSE),0),0) -> 0 | H24: $ | I24: =ROUND(IFERROR(VLOOKUP(_xlfn.CONCAT($B24,$C24,$D24),$A$53:$C$9993,2,FALSE),0),0) -> 0 | J24: $ | K24: 0 | L24: $ | M24: 0 | N24: $ | O24: =M24 -> 0 | P24: $ | Q24: =O24 -> 0
A25: Other Contractual Services | B25: 00109130 | C25: 503499 | E25: =_xlfn.CONCAT(B25,C25,D25) -> 00109130503499 | F25: $ | G25: =ROUND(IFERROR(VLOOKUP(_xlfn.CONCAT($B25,$C25,$D25),$A$53:$C$9993,3,FALSE),0),0) -> 0 | H25: $ | I25: =ROUND(IFERROR(VLOOKUP(_xlfn.CONCAT($B25,$C25,$D25),$A$53:$C$9993,2,FALSE),0),0) -> 0 | J25: $ | K25: 1400 | L25: $ | M25: 1400 | N25: $ | O25: =M25 -> 1400 | P25: $ | Q25: =O25 -> 1400
A26: Repair/Maint-Bldgs/ Facilities | B26: 00109130 | C26: 504601 | E26: =_xlfn.CONCAT(B26,C26,D26) -> 00109130504601 | G26: =ROUND(IFERROR(VLOOKUP(_xlfn.CONCAT($B26,$C26,$D26),$A$53:$C$9993,3,FALSE),0),0) -> 0 | I26: =ROUND(IFERROR(VLOOKUP(_xlfn.CONCAT($B26,$C26,$D26),$A$53:$C$9993,2,FALSE),0),0) -> 2293 | K26: 2000 | M26: 2000 | O26: =M26 -> 2000 | Q26: =O26 -> 2000
A27: Repair/Maint-Fencing/Security | B27: 00109130 | C27: 504602 | E27: =_xlfn.CONCAT(B27,C27,D27) -> 00109130504602 | G27: =ROUND(IFERROR(VLOOKUP(_xlfn.CONCAT($B27,$C27,$D27),$A$53:$C$9993,3,FALSE),0),0) -> 2745 | I27: =ROUND(IFERROR(VLOOKUP(_xlfn.CONCAT($B27,$C27,$D27),$A$53:$C$9993,2,FALSE),0),0) -> 2574 | K27: 3000 | M27: 3000 | O27: =M27 -> 3000 | Q27: =O27 -> 3000
A28: Repair/Maint-Equipment | B28: 00109130 | C28: 504620 | E28: =_xlfn.CONCAT(B28,C28,D28) -> 00109130504620 | G28: =ROUND(IFERROR(VLOOKUP(_xlfn.CONCAT($B28,$C28,$D28),$A$53:$C$9993,3,FALSE),0),0) -> 2390 | I28: =ROUND(IFERROR(VLOOKUP(_xlfn.CONCAT($B28,$C28,$D28),$A$53:$C$9993,2,FALSE),0),0) -> 7851 | K28: 0 | M28: 0 | O28: =M28 -> 0 | Q28: =O28 -> 0
A29: Playground | B29: 00109130 | E29: =_xlfn.CONCAT(B29,C29,D29) -> 00109130 | G29: =ROUND(IFERROR(VLOOKUP(_xlfn.CONCAT($B29,$C29,$D29),$A$53:$C$9993,3,FALSE),0),0) -> 0 | I29: =ROUND(IFERROR(VLOOKUP(_xlfn.CONCAT($B29,$C29,$D29),$A$53:$C$9993,2,FALSE),0),0) -> 0 | K29: 5000 | M29: 5000 | O29: =M29 -> 5000 | Q29: =O29 -> 5000
A30: Groundcover | B30: 00109130 | E30: =_xlfn.CONCAT(B30,C30,D30) -> 00109130 | G30: =ROUND(IFERROR(VLOOKUP(_xlfn.CONCAT($B30,$C30,$D30),$A$53:$C$9993,3,FALSE),0),0) -> 0 | I30: =ROUND(IFERROR(VLOOKUP(_xlfn.CONCAT($B30,$C30,$D30),$A$53:$C$9993,2,FALSE),0),0) -> 0 | K30: 5000 | M30: 5000 | O30: =M30 -> 5000 | Q30: =O30 -> 5000
A31: Repair/Maint-Hardscape | B31: 00109130 | C31: 504675 | E31: =_xlfn.CONCAT(B31,C31,D31) -> 00109130504675 | G31: =ROUND(IFERROR(VLOOKUP(_xlfn.CONCAT($B31,$C31,$D31),$A$53:$C$9993,3,FALSE),0),0) -> 5622 | I31: =ROUND(IFERROR(VLOOKUP(_xlfn.CONCAT($B31,$C31,$D31),$A$53:$C$9993,2,FALSE),0),0) -> 2993 | K31: 6000 | M31: 6000 | O31: =M31 -> 6000 | Q31: =O31 -> 6000
A32: Repair/Maint-Technology | B32: 00109130 | C32: 504683 | E32: =_xlfn.CONCAT(B32,C32,D32) -> 00109130504683 | G32: =ROUND(IFERROR(VLOOKUP(_xlfn.CONCAT($B32,$C32,$D32),$A$53:$C$9993,3,FALSE),0),0) -> 0 | I32: =ROUND(IFERROR(VLOOKUP(_xlfn.CONCAT($B32,$C32,$D32),$A$53:$C$9993,2,FALSE),0),0) -> 2946
A33: Audio/Visual | B33: 00109130 | E33: =_xlfn.CONCAT(B33,C33,D33) -> 00109130 | G33: =ROUND(IFERROR(VLOOKUP(_xlfn.CONCAT($B33,$C33,$D33),$A$53:$C$9993,3,FALSE),0),0) -> 0 | I33: =ROUND(IFERROR(VLOOKUP(_xlfn.CONCAT($B33,$C33,$D33),$A$53:$C$9993,2,FALSE),0),0) -> 0 | K33: 2000 | M33: 2000 | O33: =M33 -> 2000 | Q33: =O33 -> 2000
A34: Repair/Maint-Other | B34: 00109130 | C34: 504699 | E34: =_xlfn.CONCAT(B34,C34,D34) -> 00109130504699 | G34: =ROUND(IFERROR(VLOOKUP(_xlfn.CONCAT($B34,$C34,$D34),$A$53:$C$9993,3,FALSE),0),0) -> 148 | I34: =ROUND(IFERROR(VLOOKUP(_xlfn.CONCAT($B34,$C34,$D34),$A$53:$C$9993,2,FALSE),0),0) -> 385 | K34: 4000 | M34: 4000 | O34: =M34 -> 4000 | Q34: =O34 -> 4000
A35: Printing and Binding | B35: 00109130 | C35: 504710 | E35: =_xlfn.CONCAT(B35,C35,D35) -> 00109130504710 | G35: =ROUND(IFERROR(VLOOKUP(_xlfn.CONCAT($B35,$C35,$D35),$A$53:$C$9993,3,FALSE),0),0) -> 0 | I35: =ROUND(IFERROR(VLOOKUP(_xlfn.CONCAT($B35,$C35,$D35),$A$53:$C$9993,2,FALSE),0),0) -> 0 | K35: 0 | M35: 0 | O35: =M35 -> 0 | Q35: =O35 -> 0
A36: Operating Supplies | B36: 00109130 | C36: 505201 | E36: =_xlfn.CONCAT(B36,C36,D36) -> 00109130505201 | G36: =ROUND(IFERROR(VLOOKUP(_xlfn.CONCAT($B36,$C36,$D36),$A$53:$C$9993,3,FALSE),0),0) -> 0 | I36: =ROUND(IFERROR(VLOOKUP(_xlfn.CONCAT($B36,$C36,$D36),$A$53:$C$9993,2,FALSE),0),0) -> 0 | K36: 0 | M36: 0 | O36: =M36 -> 0 | Q36: =O36 -> 0
A37: Rental Uniforms | B37: 00109130 | C37: 505505 | E37: =_xlfn.CONCAT(B37,C37,D37) -> 00109130505505 | G37: =ROUND(IFERROR(VLOOKUP(_xlfn.CONCAT($B37,$C37,$D37),$A$53:$C$9993,3,FALSE),0),0) -> 0 | I37: =ROUND(IFERROR(VLOOKUP(_xlfn.CONCAT($B37,$C37,$D37),$A$53:$C$9993,2,FALSE),0),0) -> 0 | K37: 0 | M37: 0 | O37: =M37 -> 0 | Q37: =O37 -> 0
A38: Boots/Shoes | B38: 00109130 | C38: 505532 | E38: =_xlfn.CONCAT(B38,C38,D38) -> 00109130505532 | G38: =ROUND(IFERROR(VLOOKUP(_xlfn.CONCAT($B38,$C38,$D38),$A$53:$C$9993,3,FALSE),0),0) -> 0 | I38: =ROUND(IFERROR(VLOOKUP(_xlfn.CONCAT($B38,$C38,$D38),$A$53:$C$9993,2,FALSE),0),0) -> 0 | K38: 0 | M38: 0 | O38: =M38 -> 0 | Q38: =O38 -> 0
A39: Safety Uniforms | B39: 00109130 | C39: 505540 | E39: =_xlfn.CONCAT(B39,C39,D39) -> 00109130505540 | G39: =ROUND(IFERROR(VLOOKUP(_xlfn.CONCAT($B39,$C39,$D39),$A$53:$C$9993,3,FALSE),0),0) -> 0 | I39: =ROUND(IFERROR(VLOOKUP(_xlfn.CONCAT($B39,$C39,$D39),$A$53:$C$9993,2,FALSE),0),0) -> 0 | K39: 0 | M39: 0 | O39: =M39 -> 0 | Q39: =O39 -> 0
A40: Purchased Uniforms | B40: 00109130 | C40: 505550 | E40: =_xlfn.CONCAT(B40,C40,D40) -> 00109130505550 | G40: =ROUND(IFERROR(VLOOKUP(_xlfn.CONCAT($B40,$C40,$D40),$A$53:$C$9993,3,FALSE),0),0) -> 0 | I40: =ROUND(IFERROR(VLOOKUP(_xlfn.CONCAT($B40,$C40,$D40),$A$53:$C$9993,2,FALSE),0),0) -> 0 | K40: 0 | M40: 0 | O40: =M40 -> 0 | Q40: =O40 -> 0
A41: Park Equipment < $5,000 | B41: 00109130 | C41: 505750 | E41: =_xlfn.CONCAT(B41,C41,D41) -> 00109130505750 | G41: =ROUND(IFERROR(VLOOKUP(_xlfn.CONCAT($B41,$C41,$D41),$A$53:$C$9993,3,FALSE),0),0) -> 1100 | I41: =ROUND(IFERROR(VLOOKUP(_xlfn.CONCAT($B41,$C41,$D41),$A$53:$C$9993,2,FALSE),0),0) -> 0 | K41: 1300 | M41: 1300 | O41: =M41 -> 1300 | Q41: =O41 -> 1300
A42: Technology Items < $5,000 | B42: 00109130 | C42: 505801 | E42: =_xlfn.CONCAT(B42,C42,D42) -> 00109130505801 | G42: =ROUND(IFERROR(VLOOKUP(_xlfn.CONCAT($B42,$C42,$D42),$A$53:$C$9993,3,FALSE),0),0) -> 0 | I42: =ROUND(IFERROR(VLOOKUP(_xlfn.CONCAT($B42,$C42,$D42),$A$53:$C$9993,2,FALSE),0),0) -> 0 | K42: 0 | M42: 0 | O42: =M42 -> 0 | Q42: =O42 -> 0
A44: Total Operating Expenditures | F44: $ | G44: =SUM(G24:G43) -> 12005 | H44: $ | I44: =SUM(I24:I43) -> 19042 | J44: $ | K44: =SUM(K24:K43) -> 29700 | L44: $ | M44: =SUM(M24:M43) -> 29700 | N44: $ | O44: =SUM(O24:O43) -> 29700 | P44: $ | Q44: =SUM(Q24:Q43) -> 29700
A45: TOTAL BUDGET | F45: $ | G45: =G19+G44 -> 12005 | H45: $ | I45: =I19+I44 -> 19042 | J45: $ | K45: =K19+K44 -> 29700 | L45: $ | M45: =M19+M44 -> 29700 | N45: $ | O45: =O19+O44 -> 29700 | P45: $ | Q45: =Q19+Q44 -> 29700
A48: Per GL | G48: 12004 | I48: 19042
A49: Diff | G49: =G45-G48 -> 1 | I49: =I45-I48 -> 0
B52: 2025 Actual | C52: 2024 Actual | G52: Missing Accounts Check?
A53: 00109130501201 | B53: 0 | C53: 0 | G53: =VLOOKUP(A53,E:E,1,FALSE) -> 00109130501201
A54: 00109130501400 | B54: 0 | C54: 0 | G54: =VLOOKUP(A54,E:E,1,FALSE) -> 00109130501400
A55: 00109130501800 | B55: 0 | C55: 0 | G55: =VLOOKUP(A55,E:E,1,FALSE) -> 00109130501800
A56: 00109130502100 | B56: 0 | C56: 0 | G56: =VLOOKUP(A56,E:E,1,FALSE) -> 00109130502100
A57: 00109130502200 | B57: 0 | C57: 0 | G57: =VLOOKUP(A57,E:E,1,FALSE) -> 00109130502200
A58: 00109130502300 | B58: 0 | C58: 0 | G58: =VLOOKUP(A58,E:E,1,FALSE) -> 00109130502300
A59: 00109130502400 | B59: 0 | C59: 0 | G59: =VLOOKUP(A59,E:E,1,FALSE) -> 00109130502400
A60: 00109130503140 | B60: 0 | C60: 0 | G60: =VLOOKUP(A60,E:E,1,FALSE) -> 00109130503140
A61: 00109130503499 | B61: 0 | C61: 0 | G61: =VLOOKUP(A61,E:E,1,FALSE) -> 00109130503499
A62: 00109130504601 | B62: 2293.2 | C62: 0 | G62: =VLOOKUP(A62,E:E,1,FALSE) -> 00109130504601
A63: 00109130504602 | B63: 2573.82 | C63: 2745 | G63: =VLOOKUP(A63,E:E,1,FALSE) -> 00109130504602
A64: 00109130504620 | B64: 7850.73 | C64: 2390 | G64: =VLOOKUP(A64,E:E,1,FALSE) -> 00109130504620
... A79: 00109130999999 | B79: 0 | C79: 0 | G79: =VLOOKUP(A79,E:E,1,FALSE) -> #N/A

Sheet  914 Westmonte
A1: City of Altamonte Springs, Florida
A2: ='[1]Admin Summary'!A2:K2 -> Fiscal Year 2026 / 2027 Annual Budget
A4: Leisure and Maintenance Services Department
A5: Westmonte Park
A6: General Fund (00109140)
M8: =' 911 Admin'!M8 -> 2027
G9: =' 911 Admin'!G9 -> 2024 | I9: =' 911 Admin'!I9 -> 2025 | K9: =' 911 Admin'!K9 -> 2026 | M9: Department | O9: Manager | Q9: Commission
B10: Org | C10: Obj | D10: Proj | G10: Actual | I10: Actual | K10: Budget | M10: Requested | O10: Recommended | Q10: Adopted | R10: Notes
A11: PERSONNEL SERVICES
A12: Regular Salaries & Wages | B12: 00109140 | C12: 501201 | E12: =_xlfn.CONCAT(B12,C12,D12) -> 00109140501201 | F12: $ | G12: =ROUND(IFERROR(VLOOKUP(_xlfn.CONCAT($B12,$C12,$D12),$A$71:$C$9993,3,FALSE),0),0) -> 0 | H12: $ | I12: =ROUND(IFERROR(VLOOKUP(_xlfn.CONCAT($B12,$C12,$D12),$A$71:$C$9993,2,FALSE),0),0) -> 0 | J12: $ | K12: 0 | L12: $ | M12: ='[1]Payroll Summary by Department'!C63 -> 0 | N12: $ | O12: =M12 -> 0 | P12: $ | Q12: =O12 -> 0
A13: Limited Term-Recreation | B13: 00109140 | C13: 501305 | E13: =_xlfn.CONCAT(B13,C13,D13) -> 00109140501305 | G13: =ROUND(IFERROR(VLOOKUP(_xlfn.CONCAT($B13,$C13,$D13),$A$71:$C$9993,3,FALSE),0),0) -> 0 | I13: =ROUND(IFERROR(VLOOKUP(_xlfn.CONCAT($B13,$C13,$D13),$A$71:$C$9993,2,FALSE),0),0) -> 0 | K13: 0 | M13: 0 | O13: =M13 -> 0 | Q13: =O13 -> 0
A14: Overtime | B14: 00109140 | C14: 201400 | E14: =_xlfn.CONCAT(B14,C14,D14) -> 00109140201400 | G14: =ROUND(IFERROR(VLOOKUP(_xlfn.CONCAT($B14,$C14,$D14),$A$71:$C$9993,3,FALSE),0),0) -> 0 | I14: =ROUND(IFERROR(VLOOKUP(_xlfn.CONCAT($B14,$C14,$D14),$A$71:$C$9993,2,FALSE),0),0) -> 0 | K14: 0 | M14: 0 | O14: =M14 -> 0 | Q14: =O14 -> 0
A15: Add Pays | B15: 00109140 | C15: 501600 | E15: =_xlfn.CONCAT(B15,C15,D15) -> 00109140501600 | G15: =ROUND(IFERROR(VLOOKUP(_xlfn.CONCAT($B15,$C15,$D15),$A$71:$C$9993,3,FALSE),0),0) -> 0 | I15: =ROUND(IFERROR(VLOOKUP(_xlfn.CONCAT($B15,$C15,$D15),$A$71:$C$9993,2,FALSE),0),0) -> 0 | K15: 0 | M15: ='[1]Payroll Summary by Department'!I63 -> 0 | O15: =M15 -> 0 | Q15: =O15 -> 0
A16: Uniform Allowance | B16: 00109140 | C16: 501800 | E16: =_xlfn.CONCAT(B16,C16,D16) -> 00109140501800 | G16: =ROUND(IFERROR(VLOOKUP(_xlfn.CONCAT($B16,$C16,$D16),$A$71:$C$9993,3,FALSE),0),0) -> 0 | I16: =ROUND(IFERROR(VLOOKUP(_xlfn.CONCAT($B16,$C16,$D16),$A$71:$C$9993,2,FALSE),0),0) -> 0 | K16: 0 | M16: 0 | O16: =M16 -> 0 | Q16: =O16 -> 0
A17: FICA Taxes | B17: 00109140 | C17: 502100 | E17: =_xlfn.CONCAT(B17,C17,D17) -> 00109140502100 | G17: =ROUND(IFERROR(VLOOKUP(_xlfn.CONCAT($B17,$C17,$D17),$A$71:$C$9993,3,FALSE),0),0) -> 0 | I17: =ROUND(IFERROR(VLOOKUP(_xlfn.CONCAT($B17,$C17,$D17),$A$71:$C$9993,2,FALSE),0),0) -> 0 | K17: 0 | M17: ='[1]Payroll Summary by Department'!N63 -> 0 | O17: =M17 -> 0 | Q17: =O17 -> 0
A18: Retirement Contributions | B18: 00109140 | C18: 502200 | E18: =_xlfn.CONCAT(B18,C18,D18) -> 00109140502200 | G18: =ROUND(IFERROR(VLOOKUP(_xlfn.CONCAT($B18,$C18,$D18),$A$71:$C$9993,3,FALSE),0),0) -> 0 | I18: =ROUND(IFERROR(VLOOKUP(_xlfn.CONCAT($B18,$C18,$D18),$A$71:$C$9993,2,FALSE),0),0) -> 0 | K18: 0 | M18: ='[1]Payroll Summary by Department'!O63+'[1]Payroll Summary by Department'!P63 -> 0 | O18: =M18 -> 0 | Q18: =O18 -> 0
A19: Health Insurance | B19: 00109140 | C19: 502300 | E19: =_xlfn.CONCAT(B19,C19,D19) -> 00109140502300 | G19: =ROUND(IFERROR(VLOOKUP(_xlfn.CONCAT($B19,$C19,$D19),$A$71:$C$9993,3,FALSE),0),0) -> 0 | I19: =ROUND(IFERROR(VLOOKUP(_xlfn.CONCAT($B19,$C19,$D19),$A$71:$C$9993,2,FALSE),0),0) -> 0 | K19: 0 | M19: ='[1]Payroll Summary by Department'!Q63 -> 0 | O19: =M19 -> 0 | Q19: =O19 -> 0
A20: Life Insurance | B20: 00109140 | C20: 502400 | E20: =_xlfn.CONCAT(B20,C20,D20) -> 00109140502400 | G20: =ROUND(IFERROR(VLOOKUP(_xlfn.CONCAT($B20,$C20,$D20),$A$71:$C$9993,3,FALSE),0),0) -> 0 | I20: =ROUND(IFERROR(VLOOKUP(_xlfn.CONCAT($B20,$C20,$D20),$A$71:$C$9993,2,FALSE),0),0) -> 0 | K20: 0 | M20: ='[1]Payroll Summary by Department'!R63 -> 0 | O20: =M20 -> 0 | Q20: =O20 -> 0
A21: Total Personnel Services | E21: =_xlfn.CONCAT(B21,C21,D21) | F21: $ | G21: =SUM(G12:G20) -> 0 | H21: $ | I21: =SUM(I12:I20) -> 0 | J21: $ | K21: =SUM(K12:K20) -> 0 | L21: $ | M21: =SUM(M12:M20) -> 0 | N21: $ | O21: =SUM(O12:O20) -> 0 | P21: $ | Q21: =SUM(Q12:Q20) -> 0
A22: POSITION ROSTER | E22: =_xlfn.CONCAT(B22,C22,D22)
A23: Full-Time Employees | E23: =_xlfn.CONCAT(B23,C23,D23)
A24: Staff Assistant | C24: 4C | E24: =_xlfn.CONCAT(B24,C24,D24) -> 4C | G24: 0 | I24: 0 | K24: 0 | M24: 0 | O24: =M24 -> 0 | Q24: =O24 -> 0
A25: Total Positions | E25: =_xlfn.CONCAT(B25,C25,D25) | G25: =SUM(G24:G24) -> 0 | I25: =SUM(I24:I24) -> 0 | K25: =SUM(K24:K24) -> 0 | M25: =SUM(M24:M24) -> 0 | O25: =SUM(O24:O24) -> 0 | Q25: =SUM(Q24:Q24) -> 0
A26: OPERATING EXPENDITURES | E26: =_xlfn.CONCAT(B26,C26,D26)
A27: Other Services-Temporary Labor | B27: 00109140 | C27: 503450 | E27: =_xlfn.CONCAT(B27,C27,D27) -> 00109140503450 | F27: $ | G27: =ROUND(IFERROR(VLOOKUP(_xlfn.CONCAT($B27,$C27,$D27),$A$71:$C$9993,3,FALSE),0),0) -> 0 | H27: $ | I27: =ROUND(IFERROR(VLOOKUP(_xlfn.CONCAT($B27,$C27,$D27),$A$71:$C$9993,2,FALSE),0),0) -> 0 | J27: $ | K27: 0 | L27: $ | M27: 0 | N27: $ | O27: =M27 -> 0 | P27: $ | Q27: =O27 -> 0
A28: Other Services-Trash Disposal | B28: 00109140 | C28: 503460 | E28: =_xlfn.CONCAT(B28,C28,D28) -> 00109140503460 | F28: $ | G28: =ROUND(IFERROR(VLOOKUP(_xlfn.CONCAT($B28,$C28,$D28),$A$71:$C$9993,3,FALSE),0),0) -> 210 | H28: $ | I28: =ROUND(IFERROR(VLOOKUP(_xlfn.CONCAT($B28,$C28,$D28),$A$71:$C$9993,2,FALSE),0),0) -> 221 | J28: $ | K28: 300 | L28: $ | M28: 300 | N28: $ | O28: =M28 -> 300 | P28: $ | Q28: =O28 -> 300
A29: Rental/Lease-Equipment | B29: 00109140 | C29: 504430 | E29: =_xlfn.CONCAT(B29,C29,D29) -> 00109140504430 | G29: =ROUND(IFERROR(VLOOKUP(_xlfn.CONCAT($B29,$C29,$D29),$A$71:$C$9993,3,FALSE),0),0) -> 0 | I29: =ROUND(IFERROR(VLOOKUP(_xlfn.CONCAT($B29,$C29,$D29),$A$71:$C$9993,2,FALSE),0),0) -> 0 | K29: 0 | M29: 0 | O29: =M29 -> 0 | Q29: =O29 -> 0
A30: Rental/Lease-Network Connect | B30: 00109140 | C30: 504440 | E30: =_xlfn.CONCAT(B30,C30,D30) -> 00109140504440 | G30: =ROUND(IFERROR(VLOOKUP(_xlfn.CONCAT($B30,$C30,$D30),$A$71:$C$9993,3,FALSE),0),0) -> 2408 | I30: =ROUND(IFERROR(VLOOKUP(_xlfn.CONCAT($B30,$C30,$D30),$A$71:$C$9993,2,FALSE),0),0) -> 2707 | K30: 0 | M30: 0 | O30: =M30 -> 0 | Q30: =O30 -> 0
A31: Spectrum | B31: 00109140 | E31: =_xlfn.CONCAT(B31,C31,D31) -> 00109140 | G31: =ROUND(IFERROR(VLOOKUP(_xlfn.CONCAT($B31,$C31,$D31),$A$71:$C$9993,3,FALSE),0),0) -> 0 | I31: =ROUND(IFERROR(VLOOKUP(_xlfn.CONCAT($B31,$C31,$D31),$A$71:$C$9993,2,FALSE),0),0) -> 0 | K31: 3200 | M31: 3200 | O31: =M31 -> 3200 | Q31: =O31 -> 3200
A32: Repair/Maint-Bldgs/Facilities | B32: 00109140 | C32: 504601 | E32: =_xlfn.CONCAT(B32,C32,D32) -> 00109140504601 | G32: =ROUND(IFERROR(VLOOKUP(_xlfn.CONCAT($B32,$C32,$D32),$A$71:$C$9993,3,FALSE),0),0) -> 754 | I32: =ROUND(IFERROR(VLOOKUP(_xlfn.CONCAT($B32,$C32,$D32),$A$71:$C$9993,2,FALSE),0),0) -> 260 | K32: 1000 | M32: 1000 | O32: =M32 -> 1000 | Q32: =O32 -> 1000
A33: Repair/Maint-Fencing/Security | B33: 00109140 | C33: 504602 | E33: =_xlfn.CONCAT(B33,C33,D33) -> 00109140504602 | G33: =ROUND(IFERROR(VLOOKUP(_xlfn.CONCAT($B33,$C33,$D33),$A$71:$C$9993,3,FALSE),0),0) -> 6855 | I33: =ROUND(IFERROR(VLOOKUP(_xlfn.CONCAT($B33,$C33,$D33),$A$71:$C$9993,2,FALSE),0),0) -> 6073 | K33: 5000 | M33: 5000 | O33: =M33 -> 5000 | Q33: =O33 -> 5000
A34: Repair/Maint-Civic Center | B34: 00109140 | C34: 504605 | E34: =_xlfn.CONCAT(B34,C34,D34) -> 00109140504605 | G34: =ROUND(IFERROR(VLOOKUP(_xlfn.CONCAT($B34,$C34,$D34),$A$71:$C$9993,3,FALSE),0),0) -> 0 | I34: =ROUND(IFERROR(VLOOKUP(_xlfn.CONCAT($B34,$C34,$D34),$A$71:$C$9993,2,FALSE),0),0) -> 0 | K34: 0 | M34: 0 | O34: =M34 -> 0 | Q34: =O34 -> 0
A35: Repair/Maint-Ballfield | B35: 00109140 | C35: 504610 | E35: =_xlfn.CONCAT(B35,C35,D35) -> 00109140504610 | G35: =ROUND(IFERROR(VLOOKUP(_xlfn.CONCAT($B35,$C35,$D35),$A$71:$C$9993,3,FALSE),0),0) -> 0 | I35: =ROUND(IFERROR(VLOOKUP(_xlfn.CONCAT($B35,$C35,$D35),$A$71:$C$9993,2,FALSE),0),0) -> 0 | K35: 0 | M35: 0 | O35: =M35 -> 0 | Q35: =O35 -> 0
A36: Repair/Maint-Equipment | B36: 00109140 | C36: 504620 | E36: =_xlfn.CONCAT(B36,C36,D36) -> 00109140504620 | G36: =ROUND(IFERROR(VLOOKUP(_xlfn.CONCAT($B36,$C36,$D36),$A$71:$C$9993,3,FALSE),0),0) -> 82 | I36: =ROUND(IFERROR(VLOOKUP(_xlfn.CONCAT($B36,$C36,$D36),$A$71:$C$9993,2,FALSE),0),0) -> 0 | K36: 0 | M36: 0 | O36: =M36 -> 0 | Q36: =O36 -> 0
A37: Playground | B37: 00109140 | E37: =_xlfn.CONCAT(B37,C37,D37) -> 00109140 | G37: =ROUND(IFERROR(VLOOKUP(_xlfn.CONCAT($B37,$C37,$D37),$A$71:$C$9993,3,FALSE),0),0) -> 0 | I37: =ROUND(IFERROR(VLOOKUP(_xlfn.CONCAT($B37,$C37,$D37),$A$71:$C$9993,2,FALSE),0),0) -> 0 | K37: 2000 | M37: 2000 | O37: =M37 -> 2000 | Q37: =O37 -> 2000
A38: Thorguard | B38: 00109140 | E38: =_xlfn.CONCAT(B38,C38,D38) -> 00109140 | G38: =ROUND(IFERROR(VLOOKUP(_xlfn.CONCAT($B38,$C38,$D38),$A$71:$C$9993,3,FALSE),0),0) -> 0 | I38: =ROUND(IFERROR(VLOOKUP(_xlfn.CONCAT($B38,$C38,$D38),$A$71:$C$9993,2,FALSE),0),0) -> 0 | K38: 2500 | M38: 2500 | O38: =M38 -> 2500 | Q38: =O38 -> 2500
A39: Repair/Maint-Hardscape | B39: 00109140 | C39: 504675 | E39: =_xlfn.CONCAT(B39,C39,D39) -> 00109140504675 | G39: =ROUND(IFERROR(VLOOKUP(_xlfn.CONCAT($B39,$C39,$D39),$A$71:$C$9993,3,FALSE),0),0) -> 0 | I39: =ROUND(IFERROR(VLOOKUP(_xlfn.CONCAT($B39,$C39,$D39),$A$71:$C$9993,2,FALSE),0),0) -> 0 | K39: 3500 | M39: 3500 | O39: =M39 -> 3500 | Q39: =O39 -> 3500
A40: Repair/Maint-Service Contracts | B40: 00109140 | C40: 504680 | E40: =_xlfn.CONCAT(B40,C40,D40) -> 00109140504680 | G40: =ROUND(IFERROR(VLOOKUP(_xlfn.CONCAT($B40,$C40,$D40),$A$71:$C$9993,3,FALSE),0),0) -> 27713 | I40: =ROUND(IFERROR(VLOOKUP(_xlfn.CONCAT($B40,$C40,$D40),$A$71:$C$9993,2,FALSE),0),0) -> 17516 | K40: 0 | M40: 0 | O40: =M40 -> 0 | Q40: =O40 -> 0
A41: Pool Maintenance Services | B41: 00109140 | E41: =_xlfn.CONCAT(B41,C41,D41) -> 00109140 | G41: =ROUND(IFERROR(VLOOKUP(_xlfn.CONCAT($B41,$C41,$D41),$A$71:$C$9993,3,FALSE),0),0) -> 0 | I41: =ROUND(IFERROR(VLOOKUP(_xlfn.CONCAT($B41,$C41,$D41),$A$71:$C$9993,2,FALSE),0),0) -> 0 | K41: 40000 | M41: 40000 | O41: =M41 -> 40000 | Q41: =O41 -> 40000
A42: Repair/Maint-Technology | B42: 00109140 | C42: 504683 | E42: =_xlfn.CONCAT(B42,C42,D42) -> 00109140504683 | G42: =ROUND(IFERROR(VLOOKUP(_xlfn.CONCAT($B42,$C42,$D42),$A$71:$C$9993,3,FALSE),0),0) -> 3623 | I42: =ROUND(IFERROR(VLOOKUP(_xlfn.CONCAT($B42,$C42,$D42),$A$71:$C$9993,2,FALSE),0),0) -> 1050 | K42: 2000 | M42: 2000 | O42: =M42 -> 2000 | Q42: =O42 -> 2000
A43: Repair/Maint-Other | B43: 00109140 | C43: 504699 | E43: =_xlfn.CONCAT(B43,C43,D43) -> 00109140504699 | G43: =ROUND(IFERROR(VLOOKUP(_xlfn.CONCAT($B43,$C43,$D43),$A$71:$C$9993,3,FALSE),0),0) -> 801 | I43: =ROUND(IFERROR(VLOOKUP(_xlfn.CONCAT($B43,$C43,$D43),$A$71:$C$9993,2,FALSE),0),0) -> 634 | K43: 4000 | M43: 4000 | O43: =M43 -> 4000 | Q43: =O43 -> 4000
A44: Promo Activity-Community Programs | B44: 00109140 | C44: 504810 | E44: =_xlfn.CONCAT(B44,C44,D44) -> 00109140504810 | G44: =ROUND(IFERROR(VLOOKUP(_xlfn.CONCAT($B44,$C44,$D44),$A$71:$C$9993,3,FALSE),0),0) -> 2865 | I44: =ROUND(IFERROR(VLOOKUP(_xlfn.CONCAT($B44,$C44,$D44),$A$71:$C$9993,2,FALSE),0),0) -> 0 | K44: 0 | M44: 0 | O44: =M44 -> 0 | Q44: =O44 -> 0
A45: Christmas Trees | B45: 00109140 | E45: =_xlfn.CONCAT(B45,C45,D45) -> 00109140 | G45: =ROUND(IFERROR(VLOOKUP(_xlfn.CONCAT($B45,$C45,$D45),$A$71:$C$9993,3,FALSE),0),0) -> 0 | I45: =ROUND(IFERROR(VLOOKUP(_xlfn.CONCAT($B45,$C45,$D45),$A$71:$C$9993,2,FALSE),0),0) -> 0 | K45: 0 | M45: 0 | O45: =M45 -> 0 | Q45: =O45 -> 0
A46: Promo Activity-Marketing | B46: 00109140 | C46: 504870 | E46: =_xlfn.CONCAT(B46,C46,D46) -> 00109140504870 | G46: =ROUND(IFERROR(VLOOKUP(_xlfn.CONCAT($B46,$C46,$D46),$A$71:$C$9993,3,FALSE),0),0) -> 0 | I46: =ROUND(IFERROR(VLOOKUP(_xlfn.CONCAT($B46,$C46,$D46),$A$71:$C$9993,2,FALSE),0),0) -> 0 | K46: 0 | M46: 0 | O46: =M46 -> 0 | Q46: =O46 -> 0
A47: Operating Supplies | B47: 00109140 | C47: 505201 | E47: =_xlfn.CONCAT(B47,C47,D47) -> 00109140505201 | G47: =ROUND(IFERROR(VLOOKUP(_xlfn.CONCAT($B47,$C47,$D47),$A$71:$C$9993,3,FALSE),0),0) -> 2159 | I47: =ROUND(IFERROR(VLOOKUP(_xlfn.CONCAT($B47,$C47,$D47),$A$71:$C$9993,2,FALSE),0),0) -> 505 | K47: 0 | M47: 0 | O47: =M47 -> 0 | Q47: =O47 -> 0
A48: Chemicals | B48: 00109140 | C48: 505220 | E48: =_xlfn.CONCAT(B48,C48,D48) -> 00109140505220 | G48: =ROUND(IFERROR(VLOOKUP(_xlfn.CONCAT($B48,$C48,$D48),$A$71:$C$9993,3,FALSE),0),0) -> 52140 | I48: =ROUND(IFERROR(VLOOKUP(_xlfn.CONCAT($B48,$C48,$D48),$A$71:$C$9993,2,FALSE),0),0) -> 40953 | K48: 0 | M48: 0 | O48: =M48 -> 0 | Q48: =O48 -> 0
A49: Pool Chemicals | B49: 00109140 | E49: =_xlfn.CONCAT(B49,C49,D49) -> 00109140 | G49: =ROUND(IFERROR(VLOOKUP(_xlfn.CONCAT($B49,$C49,$D49),$A$71:$C$9993,3,FALSE),0),0) -> 0 | I49: =ROUND(IFERROR(VLOOKUP(_xlfn.CONCAT($B49,$C49,$D49),$A$71:$C$9993,2,FALSE),0),0) -> 0 | K49: 50000 | M49: 50000 | O49: =M49 -> 50000 | Q49: =O49 -> 50000
A50: Program Supplies | B50: 00109140 | C50: 505250 | E50: =_xlfn.CONCAT(B50,C50,D50) -> 00109140505250 | G50: =ROUND(IFERROR(VLOOKUP(_xlfn.CONCAT($B50,$C50,$D50),$A$71:$C$9993,3,FALSE),0),0) -> 0 | I50: =ROUND(IFERROR(VLOOKUP(_xlfn.CONCAT($B50,$C50,$D50),$A$71:$C$9993,2,FALSE),0),0) -> 0 | K50: 0 | M50: 0 | O50: =M50 -> 0 | Q50: =O50 -> 0
A51: Safety/First Aid Supplies | B51: 00109140 | C51: 505260 | E51: =_xlfn.CONCAT(B51,C51,D51) -> 00109140505260 | G51: =ROUND(IFERROR(VLOOKUP(_xlfn.CONCAT($B51,$C51,$D51),$A$71:$C$9993,3,FALSE),0),0) -> 0 | I51: =ROUND(IFERROR(VLOOKUP(_xlfn.CONCAT($B51,$C51,$D51),$A$71:$C$9993,2,FALSE),0),0) -> 0 | K51: 0 | M51: 0 | O51: =M51 -> 0 | Q51: =O51 -> 0
A52: Rental Uniforms | B52: 00109140 | C52: 505505 | E52: =_xlfn.CONCAT(B52,C52,D52) -> 00109140505505 | G52: =ROUND(IFERROR(VLOOKUP(_xlfn.CONCAT($B52,$C52,$D52),$A$71:$C$9993,3,FALSE),0),0) -> 0 | I52: =ROUND(IFERROR(VLOOKUP(_xlfn.CONCAT($B52,$C52,$D52),$A$71:$C$9993,2,FALSE),0),0) -> 0 | K52: 0 | M52: 0 | O52: =M52 -> 0 | Q52: =O52 -> 0
A53: Boots/Shoes | B53: 00109140 | C53: 505532 | E53: =_xlfn.CONCAT(B53,C53,D53) -> 00109140505532 | G53: =ROUND(IFERROR(VLOOKUP(_xlfn.CONCAT($B53,$C53,$D53),$A$71:$C$9993,3,FALSE),0),0) -> 0 | I53: =ROUND(IFERROR(VLOOKUP(_xlfn.CONCAT($B53,$C53,$D53),$A$71:$C$9993,2,FALSE),0),0) -> 0 | K53: 0 | M53: 0 | O53: =M53 -> 0 | Q53: =O53 -> 0
A54: Safety Uniforms | B54: 00109140 | C54: 505540 | E54: =_xlfn.CONCAT(B54,C54,D54) -> 00109140505540 | G54: =ROUND(IFERROR(VLOOKUP(_xlfn.CONCAT($B54,$C54,$D54),$A$71:$C$9993,3,FALSE),0),0) -> 0 | I54: =ROUND(IFERROR(VLOOKUP(_xlfn.CONCAT($B54,$C54,$D54),$A$71:$C$9993,2,FALSE),0),0) -> 0 | K54: 0 | M54: 0 | O54: =M54 -> 0 | Q54: =O54 -> 0
A55: Purchased Uniforms | B55: 00109140 | C55: 505550 | E55: =_xlfn.CONCAT(B55,C55,D55) -> 00109140505550 | G55: =ROUND(IFERROR(VLOOKUP(_xlfn.CONCAT($B55,$C55,$D55),$A$71:$C$9993,3,FALSE),0),0) -> 0 | I55: =ROUND(IFERROR(VLOOKUP(_xlfn.CONCAT($B55,$C55,$D55),$A$71:$C$9993,2,FALSE),0),0) -> 0 | K55: 0 | M55: 0 | O55: =M55 -> 0 | Q55: =O55 -> 0
A56: Propane\Diesel | B56: 00109140 | C56: 505602 | E56: =_xlfn.CONCAT(B56,C56,D56) -> 00109140505602 | G56: =ROUND(IFERROR(VLOOKUP(_xlfn.CONCAT($B56,$C56,$D56),$A$71:$C$9993,3,FALSE),0),0) -> 57794 | I56: =ROUND(IFERROR(VLOOKUP(_xlfn.CONCAT($B56,$C56,$D56),$A$71:$C$9993,2,FALSE),0),0) -> 44014 | K56: 65000 | M56: 65000 | O56: =M56 -> 65000 | Q56: =O56 -> 65000
A57: Office Furn/Fixtures < $5,000 | B57: 00109140 | C57: 505710 | E57: =_xlfn.CONCAT(B57,C57,D57) -> 00109140505710 | G57: =ROUND(IFERROR(VLOOKUP(_xlfn.CONCAT($B57,$C57,$D57),$A$71:$C$9993,3,FALSE),0),0) -> 0 | I57: =ROUND(IFERROR(VLOOKUP(_xlfn.CONCAT($B57,$C57,$D57),$A$71:$C$9993,2,FALSE),0),0) -> 0 | K57: 0 | M57: 0 | O57: =M57 -> 0 | Q57: =O57 -> 0
A58: Park Equipment < $5,000 | B58: 00109140 | C58: 505750 | E58: =_xlfn.CONCAT(B58,C58,D58) -> 00109140505750 | G58: =ROUND(IFERROR(VLOOKUP(_xlfn.CONCAT($B58,$C58,$D58),$A$71:$C$9993,3,FALSE),0),0)+1 -> 1402 | I58: =ROUND(IFERROR(VLOOKUP(_xlfn.CONCAT($B58,$C58,$D58),$A$71:$C$9993,2,FALSE),0),0)-1 -> 3002 | K58: 1300 | M58: 1300 | O58: =M58 -> 1300 | Q58: =O58 -> 1300
A59: Multipurpose Room Chairs | B59: 00109140 | E59: =_xlfn.CONCAT(B59,C59,D59) -> 00109140 | G59: =ROUND(IFERROR(VLOOKUP(_xlfn.CONCAT($B59,$C59,$D59),$A$71:$C$9993,3,FALSE),0),0) -> 0 | I59: =ROUND(IFERROR(VLOOKUP(_xlfn.CONCAT($B59,$C59,$D59),$A$71:$C$9993,2,FALSE),0),0) -> 0 | K59: 2000 | M59: 2000 | O59: =M59 -> 2000 | Q59: =O59 -> 2000
A60: Technology Items < $5,000 | B60: 00109140 | C60: 505801 | E60: =_xlfn.CONCAT(B60,C60,D60) -> 00109140505801 | G60: =ROUND(IFERROR(VLOOKUP(_xlfn.CONCAT($B60,$C60,$D60),$A$71:$C$9993,3,FALSE),0),0) -> 5999 | I60: =ROUND(IFERROR(VLOOKUP(_xlfn.CONCAT($B60,$C60,$D60),$A$71:$C$9993,2,FALSE),0),0) -> 0 | K60: 0 | M60: 0 | O60: =M60 -> 0 | Q60: =O60 -> 0
A62: Total Operating Expenditures | F62: $ | G62: =SUM(G27:G61) -> 164805 | H62: $ | I62: =SUM(I27:I61) -> 116935 | J62: $ | K62: =SUM(K27:K61) -> 181800 | L62: $ | M62: =SUM(M27:M61) -> 181800 | N62: $ | O62: =SUM(O27:O61) -> 181800 | P62: $ | Q62: =SUM(Q27:Q61) -> 181800
A63: TOTAL BUDGET | F63: $ | G63: =+G21+G62 -> 164805 | H63: $ | I63: =+I21+I62 -> 116935 | J63: $ | K63: =+K21+K62 -> 181800 | L63: $ | M63: =+M21+M62 -> 181800 | N63: $ | O63: =+O21+O62 -> 181800 | P63: $ | Q63: =+Q21+Q62 -> 181800
A66: Per GL | G66: 164805 | I66: 116935
A67: Diff | G67: =G63-G66 -> 0 | I67: =I63-I66 -> 0
B70: 2025 Actual | C70: 2024 Actual | G70: Missing Accounts Check?
A71: 00109140501201 | B71: 0 | C71: 0 | G71: =VLOOKUP(A71,E:E,1,FALSE) -> 00109140501201
A72: 00109140501305 | B72: 0 | C72: 0 | G72: =VLOOKUP(A72,E:E,1,FALSE) -> 00109140501305
A73: 00109140501400 | B73: 0 | C73: 0 | G73: =VLOOKUP(A73,E:E,1,FALSE) -> #N/A
A74: 00109140501600 | B74: 0 | C74: 0 | G74: =VLOOKUP(A74,E:E,1,FALSE) -> 00109140501600
A75: 00109140501800 | B75: 0 | C75: 0 | G75: =VLOOKUP(A75,E:E,1,FALSE) -> 00109140501800
A76: 00109140502100 | B76: 0 | C76: 0 | G76: =VLOOKUP(A76,E:E,1,FALSE) -> 00109140502100
A77: 00109140502200 | B77: 0 | C77: 0 | G77: =VLOOKUP(A77,E:E,1,FALSE) -> 00109140502200
A78: 00109140502300 | B78: 0 | C78: 0 | G78: =VLOOKUP(A78,E:E,1,FALSE) -> 00109140502300
A79: 00109140502400 | B79: 0 | C79: 0 | G79: =VLOOKUP(A79,E:E,1,FALSE) -> 00109140502400
A80: 00109140503450 | B80: 0 | C80: 0 | G80: =VLOOKUP(A80,E:E,1,FALSE) -> 00109140503450
A81: 00109140503460 | B81: 220.6 | C81: 210 | G81: =VLOOKUP(A81,E:E,1,FALSE) -> 00109140503460
A82: 00109140504430 | B82: 0 | C82: 0 | G82: =VLOOKUP(A82,E:E,1,FALSE) -> 00109140504430
... A110: 00109140999999 | B110: 0 | C110: 0 | G110: =VLOOKUP(A110,E:E,1,FALSE) -> #N/A

Sheet 916 Alta Rec
A1: City of Altamonte Springs, Florida
A2: ='[1]Admin Summary'!A2:K2 -> Fiscal Year 2026 / 2027 Annual Budget
A4: Leisure and Maintenance Services Department
A5: Altamonte Recreation
A6: General Fund (00109160)
M8: =' 911 Admin'!M8 -> 2027
G9: =' 911 Admin'!G9 -> 2024 | I9: =' 911 Admin'!I9 -> 2025 | K9: =' 911 Admin'!K9 -> 2026 | M9: Department | O9: Manager | Q9: Commission
B10: Org | C10: Obj | D10: Proj | G10: Actual | I10: Actual | K10: Budget | M10: Requested | O10: Recommended | Q10: Adopted | R10: Notes
A11: PERSONNEL SERVICES
A12: Regular Salaries & Wages Base: 16 Positions | B12: 00109160 | C12: 501201 | E12: =_xlfn.CONCAT(B12,C12,D12) -> 00109160501201 | F12: $ | G12: =ROUND(IFERROR(VLOOKUP(_xlfn.CONCAT($B12,$C12,$D12),$A$134:$C$9994,3,FALSE),0),0) -> 726081 | H12: $ | I12: =ROUND(IFERROR(VLOOKUP(_xlfn.CONCAT($B12,$C12,$D12),$A$134:$C$9994,2,FALSE),0),0) -> 777930 | J12: $ | K12: 790775 | L12: $ | M12: ='[1]Payroll Summary by Department'!C64 -> 790775 | N12: $ | O12: =M12 -> 790775 | P12: $ | Q12: =O12 -> 790775
A13: Sign Incentive Award | B13: 00109160 | C13: 501290 | E13: =_xlfn.CONCAT(B13,C13,D13) -> 00109160501290 | G13: =ROUND(IFERROR(VLOOKUP(_xlfn.CONCAT($B13,$C13,$D13),$A$134:$C$9994,3,FALSE),0),0) -> 0 | I13: =ROUND(IFERROR(VLOOKUP(_xlfn.CONCAT($B13,$C13,$D13),$A$134:$C$9994,2,FALSE),0),0) -> 0 | K13: 0 | M13: 0 | O13: =M13 -> 0 | Q13: =O13 -> 0
A14: Limited Term - Recreation | B14: 00109160 | C14: 501305 | E14: =_xlfn.CONCAT(B14,C14,D14) -> 00109160501305 | G14: =ROUND(IFERROR(VLOOKUP(_xlfn.CONCAT($B14,$C14,$D14),$A$134:$C$9994,3,FALSE),0),0) -> 871410 | I14: =ROUND(IFERROR(VLOOKUP(_xlfn.CONCAT($B14,$C14,$D14),$A$134:$C$9994,2,FALSE),0),0) -> 149587 | K14: 0 | M14: 0 | O14: =M14 -> 0 | Q14: =O14 -> 0
A15: Baseball Instructors | B15: 00109160 | C15: 501305 | D15: ABAIN | E15: =_xlfn.CONCAT(B15,C15,D15) -> 00109160501305ABAIN | G15: =ROUND(IFERROR(VLOOKUP(_xlfn.CONCAT($B15,$C15,$D15),$A$134:$C$9994,3,FALSE),0),0) -> 0 | I15: =ROUND(IFERROR(VLOOKUP(_xlfn.CONCAT($B15,$C15,$D15),$A$134:$C$9994,2,FALSE),0),0) -> 213636 | K15: 225000 | M15: 225000 | O15: =M15 -> 225000 | Q15: =O15 -> 225000
A16: Softball Instructors | B16: 00109160 | C16: 501305 | D16: AFAIN | E16: =_xlfn.CONCAT(B16,C16,D16) -> 00109160501305AFAIN | G16: =ROUND(IFERROR(VLOOKUP(_xlfn.CONCAT($B16,$C16,$D16),$A$134:$C$9994,3,FALSE),0),0) -> 0 | I16: =ROUND(IFERROR(VLOOKUP(_xlfn.CONCAT($B16,$C16,$D16),$A$134:$C$9994,2,FALSE),0),0) -> 53685 | K16: 75000 | M16: 75000 | O16: =M16 -> 75000 | Q16: =O16 -> 75000
A17: Teen Leaders | B17: 00109160 | C17: 501305 | D17: TEENL | E17: =_xlfn.CONCAT(B17,C17,D17) -> 00109160501305TEENL | G17: =ROUND(IFERROR(VLOOKUP(_xlfn.CONCAT($B17,$C17,$D17),$A$134:$C$9994,3,FALSE),0),0) -> 0 | I17: =ROUND(IFERROR(VLOOKUP(_xlfn.CONCAT($B17,$C17,$D17),$A$134:$C$9994,2,FALSE),0),0) -> 13306 | K17: 12600 | M17: 12600 | O17: =M17 -> 12600 | Q17: =O17 -> 12600
A18: Teen Aides | B18: 00109160 | C18: 501305 | D18: TEENA | E18: =_xlfn.CONCAT(B18,C18,D18) -> 00109160501305TEENA | G18: =ROUND(IFERROR(VLOOKUP(_xlfn.CONCAT($B18,$C18,$D18),$A$134:$C$9994,3,FALSE),0),0) -> 0 | I18: =ROUND(IFERROR(VLOOKUP(_xlfn.CONCAT($B18,$C18,$D18),$A$134:$C$9994,2,FALSE),0),0) -> 10350 | K18: 11500 | M18: 11500 | O18: =M18 -> 11500 | Q18: =O18 -> 11500
A19: Bus Driver | B19: 00109160 | C19: 501305 | D19: BUSDR | E19: =_xlfn.CONCAT(B19,C19,D19) -> 00109160501305BUSDR | G19: =ROUND(IFERROR(VLOOKUP(_xlfn.CONCAT($B19,$C19,$D19),$A$134:$C$9994,3,FALSE),0),0) -> 0 | I19: =ROUND(IFERROR(VLOOKUP(_xlfn.CONCAT($B19,$C19,$D19),$A$134:$C$9994,2,FALSE),0),0) -> 8134 | K19: 10000 | M19: 10000 | O19: =M19 -> 10000 | Q19: =O19 -> 10000
A20: Playground Leaders | B20: 00109160 | C20: 501305 | D20: PLAYL | E20: =_xlfn.CONCAT(B20,C20,D20) -> 00109160501305PLAYL | G20: =ROUND(IFERROR(VLOOKUP(_xlfn.CONCAT($B20,$C20,$D20),$A$134:$C$9994,3,FALSE),0),0) -> 0 | I20: =ROUND(IFERROR(VLOOKUP(_xlfn.CONCAT($B20,$C20,$D20),$A$134:$C$9994,2,FALSE),0),0) -> 29850 | K20: 28000 | M20: 28000 | O20: =M20 -> 28000 | Q20: =O20 -> 28000
A21: Playground Aides | B21: 00109160 | C21: 501305 | D21: PLAYA | E21: =_xlfn.CONCAT(B21,C21,D21) -> 00109160501305PLAYA | G21: =ROUND(IFERROR(VLOOKUP(_xlfn.CONCAT($B21,$C21,$D21),$A$134:$C$9994,3,FALSE),0),0) -> 0 | I21: =ROUND(IFERROR(VLOOKUP(_xlfn.CONCAT($B21,$C21,$D21),$A$134:$C$9994,2,FALSE),0),0) -> 111330 | K21: 124000 | M21: 124000 | O21: =M21 -> 124000 | Q21: =O21 -> 124000
A22: Exercise Instructors | B22: 00109160 | C22: 501305 | D22: EXERC | E22: =_xlfn.CONCAT(B22,C22,D22) -> 00109160501305EXERC | G22: =ROUND(IFERROR(VLOOKUP(_xlfn.CONCAT($B22,$C22,$D22),$A$134:$C$9994,3,FALSE),0),0) -> 0 | I22: =ROUND(IFERROR(VLOOKUP(_xlfn.CONCAT($B22,$C22,$D22),$A$134:$C$9994,2,FALSE),0),0) -> 76190 | K22: 81000 | M22: 81000 | O22: =M22 -> 81000 | Q22: =O22 -> 81000
A23: Recreation Workers | B23: 00109160 | C23: 501305 | D23: RECW | E23: =_xlfn.CONCAT(B23,C23,D23) -> 00109160501305RECW | G23: =ROUND(IFERROR(VLOOKUP(_xlfn.CONCAT($B23,$C23,$D23),$A$134:$C$9994,3,FALSE),0),0) -> 0 | I23: =ROUND(IFERROR(VLOOKUP(_xlfn.CONCAT($B23,$C23,$D23),$A$134:$C$9994,2,FALSE),0),0) -> 35398 | K23: 58500 | M23: 58500 | O23: =M23 -> 58500 | Q23: =O23 -> 58500
A24: Basketball Instructor | B24: 00109160 | C24: 501305 | D24: ABLIN | E24: =_xlfn.CONCAT(B24,C24,D24) -> 00109160501305ABLIN | G24: =ROUND(IFERROR(VLOOKUP(_xlfn.CONCAT($B24,$C24,$D24),$A$134:$C$9994,3,FALSE),0),0) -> 0 | I24: =ROUND(IFERROR(VLOOKUP(_xlfn.CONCAT($B24,$C24,$D24),$A$134:$C$9994,2,FALSE),0),0) -> 14610 | K24: 30000 | M24: 30000 | O24: =M24 -> 30000 | Q24: =O24 -> 30000
A25: Park Rangers | B25: 00109160 | E25: =_xlfn.CONCAT(B25,C25,D25) -> 00109160 | G25: =ROUND(IFERROR(VLOOKUP(_xlfn.CONCAT($B25,$C25,$D25),$A$134:$C$9994,3,FALSE),0),0) -> 0 | I25: =ROUND(IFERROR(VLOOKUP(_xlfn.CONCAT($B25,$C25,$D25),$A$134:$C$9994,2,FALSE),0),0) -> 0 | K25: 0 | M25: 0 | O25: =M25 -> 0 | Q25: =O25 -> 0
A26: Limited Term-Lifeguards | B26: 00109160 | C26: 501312 | D26: LIFEG | E26: =_xlfn.CONCAT(B26,C26,D26) -> 00109160501312LIFEG | G26: =ROUND(IFERROR(VLOOKUP(_xlfn.CONCAT($B26,$C26,$D26),$A$134:$C$9994,3,FALSE),0),0)+ROUND(IFERROR(VLOOKUP("00109160501312",$A$134:$C$9994,3,FALSE),0),0) -> 244063 | I26: =ROUND(IFERROR(VLOOKUP(_xlfn.CONCAT($B26,$C26,$D26),$A$134:$C$9994,2,FALSE),0),0)+ROUND(IFERROR(VLOOKUP("00109160501312",$A$134:$C$9994,2,FALSE),0),0) -> 221714 | K26: 218000 | M26: 218000 | O26: =M26 -> 218000 | Q26: =O26 -> 218000
A27: Limited Term-Adapted Aquatics | B27: 00109160 | C27: 501313 | E27: =_xlfn.CONCAT(B27,C27,D27) -> 00109160501313 | G27: =ROUND(IFERROR(VLOOKUP(_xlfn.CONCAT($B27,$C27,$D27),$A$134:$C$9994,3,FALSE),0),0) -> 0 | I27: =ROUND(IFERROR(VLOOKUP(_xlfn.CONCAT($B27,$C27,$D27),$A$134:$C$9994,2,FALSE),0),0) -> 0 | K27: 0 | M27: 0 | O27: =M27 -> 0 | Q27: =O27 -> 0
A28: Limited Term-ABA/AFA Coach | B28: 00109160 | C28: 501314 | D28: TRVLB | E28: =_xlfn.CONCAT(B28,C28,D28) -> 00109160501314TRVLB | G28: =ROUND(IFERROR(VLOOKUP(_xlfn.CONCAT($B28,$C28,$D28),$A$134:$C$9994,3,FALSE),0),0) -> 0 | I28: =ROUND(IFERROR(VLOOKUP(_xlfn.CONCAT($B28,$C28,$D28),$A$134:$C$9994,2,FALSE),0),0) -> 61979 | K28: 98250 | M28: 98250 | O28: =M28 -> 98250 | Q28: =O28 -> 98250
A29: Limited Term-Babe Ruth Coach | B29: 00109160 | C29: 501314 | D29: BRUTH | E29: =_xlfn.CONCAT(B29,C29,D29) -> 00109160501314BRUTH | G29: =ROUND(IFERROR(VLOOKUP(_xlfn.CONCAT($B29,$C29,$D29),$A$134:$C$9994,3,FALSE),0),0)+ROUND(IFERROR(VLOOKUP("00109160501314",$A$134:$C$9994,3,FALSE),0),0) -> 114216 | I29: =ROUND(IFERROR(VLOOKUP(_xlfn.CONCAT($B29,$C29,$D29),$A$134:$C$9994,2,FALSE),0),0)+ROUND(IFERROR(VLOOKUP("00109160501314",$A$134:$C$9994,2,FALSE),0),0) -> 47537 | K29: 20000 | M29: 20000 | O29: =M29 -> 20000 | Q29: =O29 -> 20000
A30: Overtime | B30: 00109160 | C30: 501400 | E30: =_xlfn.CONCAT(B30,C30,D30) -> 00109160501400 | G30: =ROUND(IFERROR(VLOOKUP(_xlfn.CONCAT($B30,$C30,$D30),$A$134:$C$9994,3,FALSE),0),0) -> 8148 | I30: =ROUND(IFERROR(VLOOKUP(_xlfn.CONCAT($B30,$C30,$D30),$A$134:$C$9994,2,FALSE),0),0) -> 12828 | K30: 8000 | M30: 8000 | O30: =M30 -> 8000 | Q30: =O30 -> 8000
A31: Overtime-Playground Aides | B31: 00109160 | C31: 501400 | D31: PLAYA | E31: =_xlfn.CONCAT(B31,C31,D31) -> 00109160501400PLAYA | G31: =ROUND(IFERROR(VLOOKUP(_xlfn.CONCAT($B31,$C31,$D31),$A$134:$C$9994,3,FALSE),0),0) -> 0 | I31: =ROUND(IFERROR(VLOOKUP(_xlfn.CONCAT($B31,$C31,$D31),$A$134:$C$9994,2,FALSE),0),0) -> 360 | K31: 0 | M31: 0 | O31: =M31 -> 0 | Q31: =O31 -> 0
A32: On-Call | B32: 00109160 | C32: 501401 | E32: =_xlfn.CONCAT(B32,C32,D32) -> 00109160501401 | G32: =ROUND(IFERROR(VLOOKUP(_xlfn.CONCAT($B32,$C32,$D32),$A$134:$C$9994,3,FALSE),0),0) -> 0 | I32: =ROUND(IFERROR(VLOOKUP(_xlfn.CONCAT($B32,$C32,$D32),$A$134:$C$9994,2,FALSE),0),0) -> 0 | K32: 100 | M32: 100 | O32: =M32 -> 100 | Q32: =O32 -> 100
A33: Add Pays | B33: 00109160 | C33: 501600 | E33: =_xlfn.CONCAT(B33,C33,D33) -> 00109160501600 | G33: =ROUND(IFERROR(VLOOKUP(_xlfn.CONCAT($B33,$C33,$D33),$A$134:$C$9994,3,FALSE),0),0) -> 5454 | I33: =ROUND(IFERROR(VLOOKUP(_xlfn.CONCAT($B33,$C33,$D33),$A$134:$C$9994,2,FALSE),0),0) -> 1755 | K33: 5200 | M33: 5200 | O33: =M33 -> 5200 | Q33: =O33 -> 5200
A34: Auto Allowance | B34: 00109160 | C34: 501701 | E34: =_xlfn.CONCAT(B34,C34,D34) -> 00109160501701 | G34: =ROUND(IFERROR(VLOOKUP(_xlfn.CONCAT($B34,$C34,$D34),$A$134:$C$9994,3,FALSE),0),0) -> 0 | I34: =ROUND(IFERROR(VLOOKUP(_xlfn.CONCAT($B34,$C34,$D34),$A$134:$C$9994,2,FALSE),0),0) -> 0 | K34: 0 | M34: ='[1]Payroll Summary by Department'!K64 -> 0 | O34: =M34 -> 0 | Q34: =O34 -> 0
A35: Cell Phone Allowance | B35: 00109160 | C35: 501702 | E35: =_xlfn.CONCAT(B35,C35,D35) -> 00109160501702 | G35: =ROUND(IFERROR(VLOOKUP(_xlfn.CONCAT($B35,$C35,$D35),$A$134:$C$9994,3,FALSE),0),0) -> 4400 | I35: =ROUND(IFERROR(VLOOKUP(_xlfn.CONCAT($B35,$C35,$D35),$A$134:$C$9994,2,FALSE),0),0) -> 4981 | K35: 4800 | M35: ='[1]Payroll Summary by Department'!L64 -> 4800 | O35: =M35 -> 4800 | Q35: =O35 -> 4800
A36: Uniform Allowance | B36: 00109160 | C36: 501800 | E36: =_xlfn.CONCAT(B36,C36,D36) -> 00109160501800 | G36: =ROUND(IFERROR(VLOOKUP(_xlfn.CONCAT($B36,$C36,$D36),$A$134:$C$9994,3,FALSE),0),0) -> 0 | I36: =ROUND(IFERROR(VLOOKUP(_xlfn.CONCAT($B36,$C36,$D36),$A$134:$C$9994,2,FALSE),0),0) -> 0 | K36: 0 | M36: 0 | O36: =M36 -> 0 | Q36: =O36 -> 0
A37: ARPA Reimbursement Quarantine | B37: 00109160 | C37: 501900 | D37: 6.01N | E37: =_xlfn.CONCAT(B37,C37,D37) -> 001091605019006.01N | G37: =ROUND(IFERROR(VLOOKUP(_xlfn.CONCAT($B37,$C37,$D37),$A$134:$C$9994,3,FALSE),0),0) -> 0 | I37: =ROUND(IFERROR(VLOOKUP(_xlfn.CONCAT($B37,$C37,$D37),$A$134:$C$9994,2,FALSE),0),0) -> 0 | K37: 0 | M37: 0 | O37: =M37 -> 0 | Q37: =O37 -> 0
A38: ARPA Reimbursement Vaccine | B38: 00109160 | C38: 501900 | D38: 6.01O | E38: =_xlfn.CONCAT(B38,C38,D38) -> 001091605019006.01O | G38: =ROUND(IFERROR(VLOOKUP(_xlfn.CONCAT($B38,$C38,$D38),$A$134:$C$9994,3,FALSE),0),0) -> 0 | I38: =ROUND(IFERROR(VLOOKUP(_xlfn.CONCAT($B38,$C38,$D38),$A$134:$C$9994,2,FALSE),0),0) -> 0 | K38: 0 | M38: 0 | O38: =M38 -> 0 | Q38: =O38 -> 0
A39: FICA Taxes | B39: 00109160 | C39: 502100 | E39: =_xlfn.CONCAT(B39,C39,D39) -> 00109160502100 | G39: =ROUND(IFERROR(VLOOKUP(_xlfn.CONCAT($B39,$C39,$D39),$A$134:$C$9994,3,FALSE),0),0)+ROUND(IFERROR(VLOOKUP("00109160502100ABAIN",$A$134:$C$9994,3,FALSE),0),0)+ROUND(IFERROR(VLOOKUP("00109160502100ABLIN",$A$134:$C$9994,3,FALSE),0),0)+ROUND(IFERROR(VLOOKUP("00109160502100AFAIN",$A$134:$C$9994,3,FALSE),0),0)+ROUND(IFERROR(VLOOKUP("00109160502100BRUTH",$A$134:$C$9994,3,FALSE),0),0)+ROUND(IFERROR(VLOOKUP("00109160502100BUSDR",$A$134:$C$9994,3,FALSE),0),0)+ROUND(IFERROR(VLOOKUP("00109160502100CIALS",$A$134:$C$9994,3,FALSE),0),0)+ROUND(IFERROR(VLOOKUP("00109160502100EXERC",$A$134:$C$9994,3,FALSE),0),0)+ROUND(IFERROR(VLOOKUP("00109160502100LIFEG",$A$134:$C$9994,3,FALSE),0),0)+ROUND(IFERROR(VLOOKUP("00109160502100PLAYA",$A$134:$C$9994,3,FALSE),0),0)+ROUND(IFERROR(VLOOKUP("00109160502100PLAYL",$A$134:$C$9994,3,FALSE),0),0)+ROUND(IFERROR(VLOOKUP("00109160502100RECW",$A$134:$C$9994,3,FALSE),0),0)+ROUND(IFERROR(VLOOKUP("00109160502100TEENA",$A$134:$C$9994,3,FALSE),0),0)+ROUND(IFERROR(VLOOKUP("00109160502100TEENL",$A$134:$C$9994,3,FALSE),0),0)+ROUND(IFERROR(VLOOKUP("00109160502100TRVLB",$A$134:$C$9994,3,FALSE),0),0) -> 150086 | I39: =ROUND(IFERROR(VLOOKUP(_xlfn.CONCAT($B39,$C39,$D39),$A$134:$C$9994,2,FALSE),0),0)+ROUND(IFERROR(VLOOKUP("00109160502100ABAIN",$A$134:$C$9994,2,FALSE),0),0)+ROUND(IFERROR(VLOOKUP("00109160502100ABLIN",$A$134:$C$9994,2,FALSE),0),0)+ROUND(IFERROR(VLOOKUP("00109160502100AFAIN",$A$134:$C$9994,2,FALSE),0),0)+ROUND(IFERROR(VLOOKUP("00109160502100BRUTH",$A$134:$C$9994,2,FALSE),0),0)+ROUND(IFERROR(VLOOKUP("00109160502100BUSDR",$A$134:$C$9994,2,FALSE),0),0)+ROUND(IFERROR(VLOOKUP("00109160502100CIALS",$A$134:$C$9994,2,FALSE),0),0)+ROUND(IFERROR(VLOOKUP("00109160502100EXERC",$A$134:$C$9994,2,FALSE),0),0)+ROUND(IFERROR(VLOOKUP("00109160502100LIFEG",$A$134:$C$9994,2,FALSE),0),0)+ROUND(IFERROR(VLOOKUP("00109160502100PLAYA",$A$134:$C$9994,2,FALSE),0),0)+ROUND(IFERROR(VLOOKUP("00109160502100PLAYL",$A$134:$C$9994,2,FALSE),0),0)+ROUND(IFERROR(VLOOKUP("00109160502100RECW",$A$134:$C$9994,2,FALSE),0),0)+ROUND(IFERROR(VLOOKUP("00109160502100TEENA",$A$134:$C$9994,2,FALSE),0),0)+ROUND(IFERROR(VLOOKUP("00109160502100TEENL",$A$134:$C$9994,2,FALSE),0),0)+ROUND(IFERROR(VLOOKUP("00109160502100TRVLB",$A$134:$C$9994,2,FALSE),0),0) -> 140141 | K39: 130145 | M39: ='[1]Payroll Summary by Department'!N64 -> 130145 | O39: =M39 -> 130145 | Q39: =O39 -> 130145
A40: Retirement Contributions | B40: 00109160 | C40: 502200 | E40: =_xlfn.CONCAT(B40,C40,D40) -> 00109160502200 | G40: =ROUND(IFERROR(VLOOKUP(_xlfn.CONCAT($B40,$C40,$D40),$A$134:$C$9994,3,FALSE),0),0) -> 79846 | I40: =ROUND(IFERROR(VLOOKUP(_xlfn.CONCAT($B40,$C40,$D40),$A$134:$C$9994,2,FALSE),0),0) -> 75814 | K40: 99019 | M40: ='[1]Payroll Summary by Department'!O64+'[1]Payroll Summary by Department'!P64 -> 99019 | O40: =M40 -> 99019 | Q40: =O40 -> 99019
A41: Health Insurance | B41: 00109160 | C41: 502300 | E41: =_xlfn.CONCAT(B41,C41,D41) -> 00109160502300 | G41: =ROUND(IFERROR(VLOOKUP(_xlfn.CONCAT($B41,$C41,$D41),$A$134:$C$9994,3,FALSE),0),0) -> 137339 | I41: =ROUND(IFERROR(VLOOKUP(_xlfn.CONCAT($B41,$C41,$D41),$A$134:$C$9994,2,FALSE),0),0) -> 144290 | K41: 184288 | M41: ='[1]Payroll Summary by Department'!Q64 -> 184288 | O41: =M41 -> 184288 | Q41: =O41 -> 184288
A42: Life Insurance | B42: 00109160 | C42: 502400 | E42: =_xlfn.CONCAT(B42,C42,D42) -> 00109160502400 | G42: =ROUND(IFERROR(VLOOKUP(_xlfn.CONCAT($B42,$C42,$D42),$A$134:$C$9994,3,FALSE),0),0) -> 1408 | I42: =ROUND(IFERROR(VLOOKUP(_xlfn.CONCAT($B42,$C42,$D42),$A$134:$C$9994,2,FALSE),0),0) -> 1568 | K42: 1494 | M42: ='[1]Payroll Summary by Department'!R64 -> 1494 | O42: =M42 -> 1494 | Q42: =O42 -> 1494
A43: Total Personnel Services | E43: =_xlfn.CONCAT(B43,C43,D43) | F43: $ | G43: =SUM(G12:G42) -> 2342451 | H43: $ | I43: =SUM(I12:I42) -> 2206973 | J43: $ | K43: =SUM(K12:K42) -> 2215671 | L43: $ | M43: =SUM(M12:M42) -> 2215671 | N43: $ | O43: =SUM(O12:O42) -> 2215671 | P43: $ | Q43: =SUM(Q12:Q42) -> 2215671
A44: POSITION ROSTER | E44: =_xlfn.CONCAT(B44,C44,D44)
A45: Full-Time Employees | E45: =_xlfn.CONCAT(B45,C45,D45)
A46: Recreation Manager | C46: 3B | E46: =_xlfn.CONCAT(B46,C46,D46) -> 3B | G46: 3 | I46: 3 | K46: 4 | M46: 4 | O46: =M46 -> 4 | Q46: =O46 -> 4
A47: Program Specialist | C47: 3B | E47: =_xlfn.CONCAT(B47,C47,D47) -> 3B | G47: 1 | I47: 1 | K47: 1 | M47: 1 | O47: =M47 -> 1 | Q47: =O47 -> 1
A48: ABA Coordinator | C48: 3A | E48: =_xlfn.CONCAT(B48,C48,D48) -> 3A | G48: 0 | I48: 1 | K48: 1 | M48: 1 | O48: =M48 -> 1 | Q48: =O48 -> 1
A49: Aquatics Supervisor | C49: 3A | E49: =_xlfn.CONCAT(B49,C49,D49) -> 3A | G49: 1 | I49: 1 | K49: 1 | M49: 1 | O49: =M49 -> 1 | Q49: =O49 -> 1
A50: Recreation Supervisor | C50: 3A | E50: =_xlfn.CONCAT(B50,C50,D50) -> 3A | G50: 4 | I50: 4 | K50: 3 | M50: 3 | O50: =M50 -> 3 | Q50: =O50 -> 3
A51: Recreation Leader | C51: 4C | E51: =_xlfn.CONCAT(B51,C51,D51) -> 4C | G51: 5 | I51: 5 | K51: 5 | M51: 5 | O51: =M51 -> 5 | Q51: =O51 -> 5
A52: Aquatics Coordinator | C52: 4C | E52: =_xlfn.CONCAT(B52,C52,D52) -> 4C | G52: 1 | I52: 1 | K52: 1 | M52: 1 | O52: =M52 -> 1 | Q52: =O52 -> 1
A53: Operations Division Manager | C53: 3C | E53: =_xlfn.CONCAT(B53,C53,D53) -> 3C | G53: 0 | I53: 0 | K53: 0 | M53: 0 | O53: =M53 -> 0 | Q53: =O53 -> 0
A54: Recreation Division Manager | C54: 3B | E54: =_xlfn.CONCAT(B54,C54,D54) -> 3B | G54: 0 | I54: 0 | K54: 0 | M54: 0 | O54: =M54 -> 0 | Q54: =O54 -> 0
A55: Recreation Support Administrator | C55: 3B | E55: =_xlfn.CONCAT(B55,C55,D55) -> 3B | G55: 1 | I55: 0 | K55: 0 | M55: 0 | O55: =M55 -> 0 | Q55: =O55 -> 0
A56: Park Ranger Supervisor | C56: 3A | E56: =_xlfn.CONCAT(B56,C56,D56) -> 3A | G56: 0 | I56: 0 | K56: 0 | M56: 0 | O56: =M56 -> 0 | Q56: =O56 -> 0
A57: Staff Assistant | C57: 4C | E57: =_xlfn.CONCAT(B57,C57,D57) -> 4C | G57: 0 | I57: 0 | K57: 0 | M57: 0 | O57: =M57 -> 0 | Q57: =O57 -> 0
A58: Park Rangers | C58: 4C | E58: =_xlfn.CONCAT(B58,C58,D58) -> 4C | G58: 0 | I58: 0 | K58: 0 | M58: 0 | O58: =M58 -> 0 | Q58: =O58 -> 0
E59: =_xlfn.CONCAT(B59,C59,D59)
A60: Total Positions | E60: =_xlfn.CONCAT(B60,C60,D60) | G60: =SUM(G46:G59) -> 16 | I60: =SUM(I46:I59) -> 16 | K60: =SUM(K46:K59) -> 16 | M60: =SUM(M46:M59) -> 16 | O60: =SUM(O46:O59) -> 16 | Q60: =SUM(Q46:Q59) -> 16
A61: Part-Time Employees | E61: =_xlfn.CONCAT(B61,C61,D61)
E62: =_xlfn.CONCAT(B62,C62,D62) | G62: 0 | I62: 0 | K62: 0 | M62: 0 | O62: =M62 -> 0 | Q62: =O62 -> 0
A63: Total Part-Time Employees | E63: =_xlfn.CONCAT(B63,C63,D63) | G63: =SUM(G62:G62) -> 0 | I63: =SUM(I62:I62) -> 0 | K63: =SUM(K62:K62) -> 0 | M63: =SUM(M62:M62) -> 0 | O63: =SUM(O62:O62) -> 0 | Q63: =SUM(Q62:Q62) -> 0
A64: Total Positions | E64: =_xlfn.CONCAT(B64,C64,D64) | G64: =+G63+G60 -> 16 | I64: =+I63+I60 -> 16 | K64: =+K63+K60 -> 16 | M64: =+M63+M60 -> 16 | O64: =+O63+O60 -> 16 | Q64: =+Q63+Q60 -> 16
A65: OPERATING EXPENDITURES | E65: =_xlfn.CONCAT(B65,C65,D65)
A66: Other Contractual Services | B66: 00109160 | C66: 503401 | E66: =_xlfn.CONCAT(B66,C66,D66) -> 00109160503401 | F66: $ | G66: =ROUND(IFERROR(VLOOKUP(_xlfn.CONCAT($B66,$C66,$D66),$A$134:$C$9994,3,FALSE),0),0) -> 0 | H66: $ | I66: =ROUND(IFERROR(VLOOKUP(_xlfn.CONCAT($B66,$C66,$D66),$A$134:$C$9994,2,FALSE),0),0) -> 0 | J66: $ | K66: 0 | L66: $ | M66: 0 | N66: $ | O66: =M66 -> 0 | P66: $ | Q66: =O66 -> 0
A67: Computer System Training | B67: 00109160 | E67: =_xlfn.CONCAT(B67,C67,D67) -> 00109160 | G67: =ROUND(IFERROR(VLOOKUP(_xlfn.CONCAT($B67,$C67,$D67),$A$134:$C$9994,3,FALSE),0),0) -> 0 | I67: =ROUND(IFERROR(VLOOKUP(_xlfn.CONCAT($B67,$C67,$D67),$A$134:$C$9994,2,FALSE),0),0) -> 0 | K67: 2500 | M67: 2500 | O67: =M67 -> 2500 | Q67: =O67 -> 2500
A68: Other Services-Software Subscription | B68: 00109160 | C68: 503403 | E68: =_xlfn.CONCAT(B68,C68,D68) -> 00109160503403 | G68: =ROUND(IFERROR(VLOOKUP(_xlfn.CONCAT($B68,$C68,$D68),$A$134:$C$9994,3,FALSE),0),0) -> 0 | I68: =ROUND(IFERROR(VLOOKUP(_xlfn.CONCAT($B68,$C68,$D68),$A$134:$C$9994,2,FALSE),0),0) -> 0 | K68: 400 | M68: 400 | O68: =M68 -> 400 | Q68: =O68 -> 400
A69: Other Services-Bank Fees | B69: 00109160 | C69: 503415 | E69: =_xlfn.CONCAT(B69,C69,D69) -> 00109160503415 | G69: =ROUND(IFERROR(VLOOKUP(_xlfn.CONCAT($B69,$C69,$D69),$A$134:$C$9994,3,FALSE),0),0) -> 19773 | I69: =ROUND(IFERROR(VLOOKUP(_xlfn.CONCAT($B69,$C69,$D69),$A$134:$C$9994,2,FALSE),0),0) -> 19881 | K69: 0 | M69: 0 | O69: =M69 -> 0 | Q69: =O69 -> 0
A70: Civic Rec Processing | B70: 00109160 | E70: =_xlfn.CONCAT(B70,C70,D70) -> 00109160 | G70: =ROUND(IFERROR(VLOOKUP(_xlfn.CONCAT($B70,$C70,$D70),$A$134:$C$9994,3,FALSE),0),0) -> 0 | I70: =ROUND(IFERROR(VLOOKUP(_xlfn.CONCAT($B70,$C70,$D70),$A$134:$C$9994,2,FALSE),0),0) -> 0 | K70: 20000 | M70: 20000 | O70: =M70 -> 20000 | Q70: =O70 -> 20000
A71: Other Services-Temporary Labor | B71: 00109160 | C71: 503450 | E71: =_xlfn.CONCAT(B71,C71,D71) -> 00109160503450 | G71: =ROUND(IFERROR(VLOOKUP(_xlfn.CONCAT($B71,$C71,$D71),$A$134:$C$9994,3,FALSE),0),0) -> 0 | I71: =ROUND(IFERROR(VLOOKUP(_xlfn.CONCAT($B71,$C71,$D71),$A$134:$C$9994,2,FALSE),0),0) -> 0 | K71: 0 | M71: 0 | O71: =M71 -> 0 | Q71: =O71 -> 0
A72: Other Services-Youth Programs | B72: 00109160 | C72: 503457 | E72: =_xlfn.CONCAT(B72,C72,D72) -> 00109160503457 | G72: =ROUND(IFERROR(VLOOKUP(_xlfn.CONCAT($B72,$C72,$D72),$A$134:$C$9994,3,FALSE),0),0) -> 0 | I72: =ROUND(IFERROR(VLOOKUP(_xlfn.CONCAT($B72,$C72,$D72),$A$134:$C$9994,2,FALSE),0),0) -> 0 | K72: 0 | M72: 0 | O72: =M72 -> 0 | Q72: =O72 -> 0
A73: Educational Incentive | B73: 00109160 | C73: 503901 | E73: =_xlfn.CONCAT(B73,C73,D73) -> 00109160503901 | G73: =ROUND(IFERROR(VLOOKUP(_xlfn.CONCAT($B73,$C73,$D73),$A$134:$C$9994,3,FALSE),0),0) -> 0 | I73: =ROUND(IFERROR(VLOOKUP(_xlfn.CONCAT($B73,$C73,$D73),$A$134:$C$9994,2,FALSE),0),0) -> 570 | K73: 3000 | M73: 3000 | O73: =M73 -> 3000 | Q73: =O73 -> 3000
A74: Certifications | B74: 00109160 | E74: =_xlfn.CONCAT(B74,C74,D74) -> 00109160 | G74: =ROUND(IFERROR(VLOOKUP(_xlfn.CONCAT($B74,$C74,$D74),$A$134:$C$9994,3,FALSE),0),0) -> 0 | I74: =ROUND(IFERROR(VLOOKUP(_xlfn.CONCAT($B74,$C74,$D74),$A$134:$C$9994,2,FALSE),0),0) -> 0 | K74: 0 | M74: 0 | O74: =M74 -> 0 | Q74: =O74 -> 0
A75: Conferences/Seminars/Meetings | B75: 00109160 | E75: =_xlfn.CONCAT(B75,C75,D75) -> 00109160 | G75: =ROUND(IFERROR(VLOOKUP(_xlfn.CONCAT($B75,$C75,$D75),$A$134:$C$9994,3,FALSE),0),0) -> 0 | I75: =ROUND(IFERROR(VLOOKUP(_xlfn.CONCAT($B75,$C75,$D75),$A$134:$C$9994,2,FALSE),0),0) -> 0 | K75: 0 | M75: 0 | O75: =M75 -> 0 | Q75: =O75 -> 0
A76: Non-Travel Training | B76: 00109160 | C76: 504060 | E76: =_xlfn.CONCAT(B76,C76,D76) -> 00109160504060 | G76: =ROUND(IFERROR(VLOOKUP(_xlfn.CONCAT($B76,$C76,$D76),$A$134:$C$9994,3,FALSE),0),0) -> 6292 | I76: =ROUND(IFERROR(VLOOKUP(_xlfn.CONCAT($B76,$C76,$D76),$A$134:$C$9994,2,FALSE),0),0) -> 4895 | K76: 6500 | M76: 6500 | O76: =M76 -> 6500 | Q76: =O76 -> 6500
A77: Travel Training | B77: 00109160 | C77: 504070 | E77: =_xlfn.CONCAT(B77,C77,D77) -> 00109160504070 | G77: =ROUND(IFERROR(VLOOKUP(_xlfn.CONCAT($B77,$C77,$D77),$A$134:$C$9994,3,FALSE),0),0) -> 0 | I77: =ROUND(IFERROR(VLOOKUP(_xlfn.CONCAT($B77,$C77,$D77),$A$134:$C$9994,2,FALSE),0),0) -> 303 | K77: 1000 | M77: 1000 | O77: =M77 -> 1000 | Q77: =O77 -> 1000
A78: Babe Ruth Travel Coaches | B78: 00109160 | E78: =_xlfn.CONCAT(B78,C78,D78) -> 00109160 | G78: =ROUND(IFERROR(VLOOKUP(_xlfn.CONCAT($B78,$C78,$D78),$A$134:$C$9994,3,FALSE),0),0) -> 0 | I78: =ROUND(IFERROR(VLOOKUP(_xlfn.CONCAT($B78,$C78,$D78),$A$134:$C$9994,2,FALSE),0),0) -> 0 | K78: 25000 | M78: 25000 | O78: =M78 -> 25000 | Q78: =O78 -> 25000
A79: ABA Travel Coaches | B79: 00109160 | C79: 504070 | D79: LR030 | E79: =_xlfn.CONCAT(B79,C79,D79) -> 00109160504070LR030 | G79: =ROUND(IFERROR(VLOOKUP(_xlfn.CONCAT($B79,$C79,$D79),$A$134:$C$9994,3,FALSE),0),0) -> 24511 | I79: =ROUND(IFERROR(VLOOKUP(_xlfn.CONCAT($B79,$C79,$D79),$A$134:$C$9994,2,FALSE),0),0) -> 4317 | K79: 2500 | M79: 2500 | O79: =M79 -> 2500 | Q79: =O79 -> 2500
A80: AFA Travel Coaches | B80: 00109160 | C80: 504070 | D80: LR035 | E80: =_xlfn.CONCAT(B80,C80,D80) -> 00109160504070LR035 | G80: =ROUND(IFERROR(VLOOKUP(_xlfn.CONCAT($B80,$C80,$D80),$A$134:$C$9994,3,FALSE),0),0) -> 3696 | I80: =ROUND(IFERROR(VLOOKUP(_xlfn.CONCAT($B80,$C80,$D80),$A$134:$C$9994,2,FALSE),0),0) -> 0 | K80: 2500 | M80: 2500 | O80: =M80 -> 2500 | Q80: =O80 -> 2500
A81: Freight and Postage Services | B81: 00109160 | C81: 504201 | E81: =_xlfn.CONCAT(B81,C81,D81) -> 00109160504201 | G81: =ROUND(IFERROR(VLOOKUP(_xlfn.CONCAT($B81,$C81,$D81),$A$134:$C$9994,3,FALSE),0),0) -> 0 | I81: =ROUND(IFERROR(VLOOKUP(_xlfn.CONCAT($B81,$C81,$D81),$A$134:$C$9994,2,FALSE),0),0) -> 0 | K81: 0 | M81: 0 | O81: =M81 -> 0 | Q81: =O81 -> 0
A82: Rental/Lease-Off-Site Storage | B82: 00109160 | C82: 504410 | E82: =_xlfn.CONCAT(B82,C82,D82) -> 00109160504410 | G82: =ROUND(IFERROR(VLOOKUP(_xlfn.CONCAT($B82,$C82,$D82),$A$134:$C$9994,3,FALSE),0),0) -> 0 | I82: =ROUND(IFERROR(VLOOKUP(_xlfn.CONCAT($B82,$C82,$D82),$A$134:$C$9994,2,FALSE),0),0) -> 0 | K82: 0 | M82: 0 | O82: =M82 -> 0 | Q82: =O82 -> 0
A83: Rental/Lease-Equipment | B83: 00109160 | C83: 504430 | E83: =_xlfn.CONCAT(B83,C83,D83) -> 00109160504430 | G83: =ROUND(IFERROR(VLOOKUP(_xlfn.CONCAT($B83,$C83,$D83),$A$134:$C$9994,3,FALSE),0),0) -> 0 | I83: =ROUND(IFERROR(VLOOKUP(_xlfn.CONCAT($B83,$C83,$D83),$A$134:$C$9994,2,FALSE),0),0) -> 2165 | K83: 0 | M83: 0 | O83: =M83 -> 0 | Q83: =O83 -> 0
A84: Repair/Maint-Bldgs/ Facilities | B84: 00109160 | C84: 504601 | E84: =_xlfn.CONCAT(B84,C84,D84) -> 00109160504601 | G84: =ROUND(IFERROR(VLOOKUP(_xlfn.CONCAT($B84,$C84,$D84),$A$134:$C$9994,3,FALSE),0),0) -> 0 | I84: =ROUND(IFERROR(VLOOKUP(_xlfn.CONCAT($B84,$C84,$D84),$A$134:$C$9994,2,FALSE),0),0) -> 0 | K84: 0 | M84: 0 | O84: =M84 -> 0 | Q84: =O84 -> 0
A85: Repair/Maint-Ballfield | B85: 00109160 | C85: 504610 | E85: =_xlfn.CONCAT(B85,C85,D85) -> 00109160504610 | G85: =ROUND(IFERROR(VLOOKUP(_xlfn.CONCAT($B85,$C85,$D85),$A$134:$C$9994,3,FALSE),0),0) -> 9513 | I85: =ROUND(IFERROR(VLOOKUP(_xlfn.CONCAT($B85,$C85,$D85),$A$134:$C$9994,2,FALSE),0),0) -> 0 | K85: 0 | M85: 0 | O85: =M85 -> 0 | Q85: =O85 -> 0
A86: Repair/Maint-Equipment | B86: 00109160 | C86: 504620 | E86: =_xlfn.CONCAT(B86,C86,D86) -> 00109160504620 | G86: =ROUND(IFERROR(VLOOKUP(_xlfn.CONCAT($B86,$C86,$D86),$A$134:$C$9994,3,FALSE),0),0) -> 0 | I86: =ROUND(IFERROR(VLOOKUP(_xlfn.CONCAT($B86,$C86,$D86),$A$134:$C$9994,2,FALSE),0),0) -> 0 | K86: 5000 | M86: 5000 | O86: =M86 -> 5000 | Q86: =O86 -> 5000
A87: Repair/Maint-Service Contracts | B87: 00109160 | C87: 504680 | E87: =_xlfn.CONCAT(B87,C87,D87) -> 00109160504680 | G87: =ROUND(IFERROR(VLOOKUP(_xlfn.CONCAT($B87,$C87,$D87),$A$134:$C$9994,3,FALSE),0),0) -> 0 | I87: =ROUND(IFERROR(VLOOKUP(_xlfn.CONCAT($B87,$C87,$D87),$A$134:$C$9994,2,FALSE),0),0) -> 0 | K87: 0 | M87: 0 | O87: =M87 -> 0 | Q87: =O87 -> 0
A88: Printing & Binding | B88: 00109160 | C88: 504710 | E88: =_xlfn.CONCAT(B88,C88,D88) -> 00109160504710 | G88: =ROUND(IFERROR(VLOOKUP(_xlfn.CONCAT($B88,$C88,$D88),$A$134:$C$9994,3,FALSE),0),0) -> 1307 | I88: =ROUND(IFERROR(VLOOKUP(_xlfn.CONCAT($B88,$C88,$D88),$A$134:$C$9994,2,FALSE),0),0) -> 1638 | K88: 3000 | M88: 3000 | O88: =M88 -> 3000 | Q88: =O88 -> 3000
A89: Promo Activity-Community Programs | B89: 00109160 | C89: 504810 | E89: =_xlfn.CONCAT(B89,C89,D89) -> 00109160504810 | G89: =ROUND(IFERROR(VLOOKUP(_xlfn.CONCAT($B89,$C89,$D89),$A$134:$C$9994,3,FALSE),0),0) -> 2342 | I89: =ROUND(IFERROR(VLOOKUP(_xlfn.CONCAT($B89,$C89,$D89),$A$134:$C$9994,2,FALSE),0),0) -> 2144 | K89: 500 | M89: 500 | O89: =M89 -> 500 | Q89: =O89 -> 500
A90: Baseball Opening Day | B90: 00109160 | E90: =_xlfn.CONCAT(B90,C90,D90) -> 00109160 | G90: =ROUND(IFERROR(VLOOKUP(_xlfn.CONCAT($B90,$C90,$D90),$A$134:$C$9994,3,FALSE),0),0) -> 0 | I90: =ROUND(IFERROR(VLOOKUP(_xlfn.CONCAT($B90,$C90,$D90),$A$134:$C$9994,2,FALSE),0),0) -> 0 | K90: 2000 | M90: 2000 | O90: =M90 -> 2000 | Q90: =O90 -> 2000
A91: Promo Activity-Marketing | B91: 00109160 | C91: 504870 | E91: =_xlfn.CONCAT(B91,C91,D91) -> 00109160504870 | G91: =ROUND(IFERROR(VLOOKUP(_xlfn.CONCAT($B91,$C91,$D91),$A$134:$C$9994,3,FALSE),0),0) -> 36601 | I91: =ROUND(IFERROR(VLOOKUP(_xlfn.CONCAT($B91,$C91,$D91),$A$134:$C$9994,2,FALSE),0),0) -> 34961 | K91: 45000 | M91: 45000 | O91: =M91 -> 45000 | Q91: =O91 -> 45000
A92: Email Marketing | B92: 00109160 | E92: =_xlfn.CONCAT(B92,C92,D92) -> 00109160 | G92: =ROUND(IFERROR(VLOOKUP(_xlfn.CONCAT($B92,$C92,$D92),$A$134:$C$9994,3,FALSE),0),0) -> 0 | I92: =ROUND(IFERROR(VLOOKUP(_xlfn.CONCAT($B92,$C92,$D92),$A$134:$C$9994,2,FALSE),0),0) -> 0 | K92: 3000 | M92: 3000 | O92: =M92 -> 3000 | Q92: =O92 -> 3000
A93: Other Charges-Program Awards | B93: 00109160 | C93: 504910 | E93: =_xlfn.CONCAT(B93,C93,D93) -> 00109160504910 | G93: =ROUND(IFERROR(VLOOKUP(_xlfn.CONCAT($B93,$C93,$D93),$A$134:$C$9994,3,FALSE),0),0) -> 0 | I93: =ROUND(IFERROR(VLOOKUP(_xlfn.CONCAT($B93,$C93,$D93),$A$134:$C$9994,2,FALSE),0),0) -> 0 | K93: 0 | M93: 0 | O93: =M93 -> 0 | Q93: =O93 -> 0
A94: Office Supplies | B94: 00109160 | C94: 505101 | E94: =_xlfn.CONCAT(B94,C94,D94) -> 00109160505101 | G94: =ROUND(IFERROR(VLOOKUP(_xlfn.CONCAT($B94,$C94,$D94),$A$134:$C$9994,3,FALSE),0),0) -> 0 | I94: =ROUND(IFERROR(VLOOKUP(_xlfn.CONCAT($B94,$C94,$D94),$A$134:$C$9994,2,FALSE),0),0) -> -104 | K94: 0 | M94: 0 | O94: =M94 -> 0 | Q94: =O94 -> 0
A95: Cost of Goods Sold-Fanshop | B95: 00109160 | C95: 505200 | E95: =_xlfn.CONCAT(B95,C95,D95) -> 00109160505200 | G95: =ROUND(IFERROR(VLOOKUP(_xlfn.CONCAT($B95,$C95,$D95),$A$134:$C$9994,3,FALSE),0),0) -> 2884 | I95: =ROUND(IFERROR(VLOOKUP(_xlfn.CONCAT($B95,$C95,$D95),$A$134:$C$9994,2,FALSE),0),0) -> 2801 | K95: 0 | M95: 0 | O95: =M95 -> 0 | Q95: =O95 -> 0
A96: OPERATING EXPENDITURES (continued) | B96: 00109160 | E96: =_xlfn.CONCAT(B96,C96,D96) -> 00109160 | G96: =ROUND(IFERROR(VLOOKUP(_xlfn.CONCAT($B96,$C96,$D96),$A$134:$C$9994,3,FALSE),0),0) -> 0 | I96: =ROUND(IFERROR(VLOOKUP(_xlfn.CONCAT($B96,$C96,$D96),$A$134:$C$9994,2,FALSE),0),0) -> 0
A97: Operating Supplies | B97: 00109160 | C97: 505201 | E97: =_xlfn.CONCAT(B97,C97,D97) -> 00109160505201 | F97: $ | G97: =ROUND(IFERROR(VLOOKUP(_xlfn.CONCAT($B97,$C97,$D97),$A$134:$C$9994,3,FALSE),0),0) -> 8868 | H97: $ | I97: =ROUND(IFERROR(VLOOKUP(_xlfn.CONCAT($B97,$C97,$D97),$A$134:$C$9994,2,FALSE),0),0) -> 8809 | J97: $ | K97: 14000 | L97: $ | M97: 14000 | N97: $ | O97: =M97 -> 14000 | P97: $ | Q97: =O97 -> 14000
A98: Program Supplies | B98: 00109160 | C98: 505250 | E98: =_xlfn.CONCAT(B98,C98,D98) -> 00109160505250 | G98: =ROUND(IFERROR(VLOOKUP(_xlfn.CONCAT($B98,$C98,$D98),$A$134:$C$9994,3,FALSE),0),0) -> 0 | I98: =ROUND(IFERROR(VLOOKUP(_xlfn.CONCAT($B98,$C98,$D98),$A$134:$C$9994,2,FALSE),0),0) -> 544 | K98: 0 | M98: 0 | O98: =M98 -> 0 | Q98: =O98 -> 0
A99: ABA Travel Program | B99: 00109160 | C99: 505250 | D99: LR030 | E99: =_xlfn.CONCAT(B99,C99,D99) -> 00109160505250LR030 | G99: =ROUND(IFERROR(VLOOKUP(_xlfn.CONCAT($B99,$C99,$D99),$A$134:$C$9994,3,FALSE),0),0) -> 52316 | I99: =ROUND(IFERROR(VLOOKUP(_xlfn.CONCAT($B99,$C99,$D99),$A$134:$C$9994,2,FALSE),0),0) -> 67032 | K99: 125000 | M99: 125000 | O99: =M99 -> 125000 | Q99: =O99 -> 125000
A100: AFA Travel Program | B100: 00109160 | C100: 505250 | D100: LR035 | E100: =_xlfn.CONCAT(B100,C100,D100) -> 00109160505250LR035 | G100: =ROUND(IFERROR(VLOOKUP(_xlfn.CONCAT($B100,$C100,$D100),$A$134:$C$9994,3,FALSE),0),0) -> 47504 | I100: =ROUND(IFERROR(VLOOKUP(_xlfn.CONCAT($B100,$C100,$D100),$A$134:$C$9994,2,FALSE),0),0) -> 43064 | K100: 52000 | M100: 52000 | O100: =M100 -> 52000 | Q100: =O100 -> 52000
A101: Program Costs | B101: 00109160 | C101: 505255 | E101: =_xlfn.CONCAT(B101,C101,D101) -> 00109160505255 | G101: =ROUND(IFERROR(VLOOKUP(_xlfn.CONCAT($B101,$C101,$D101),$A$134:$C$9994,3,FALSE),0),0) -> 0 | I101: =ROUND(IFERROR(VLOOKUP(_xlfn.CONCAT($B101,$C101,$D101),$A$134:$C$9994,2,FALSE),0),0) -> 0
A102: World Series Hosting Fee | B102: 00109160 | E102: =_xlfn.CONCAT(B102,C102,D102) -> 00109160 | G102: =ROUND(IFERROR(VLOOKUP(_xlfn.CONCAT($B102,$C102,$D102),$A$134:$C$9994,3,FALSE),0),0) -> 0 | I102: =ROUND(IFERROR(VLOOKUP(_xlfn.CONCAT($B102,$C102,$D102),$A$134:$C$9994,2,FALSE),0),0) -> 0 | K102: 80000 | M102: 80000 | O102: =M102 -> 80000 | Q102: =O102 -> 80000
...

Sheet 908 Brantley
A1: City of Altamonte Springs, Florida
A2: ='[1]Admin Summary'!A2:K2 -> Fiscal Year 2026 / 2027 Annual Budget
A4: Leisure and Maintenance Services Department
A5: Lake Brantley Sports Complex
A6: General Fund (00109080)
M8: =' 911 Admin'!M8 -> 2027
G9: =' 911 Admin'!G9 -> 2024 | I9: =' 911 Admin'!I9 -> 2025 | K9: =' 911 Admin'!K9 -> 2026 | M9: Department | O9: Manager | Q9: Commission
B10: Org | C10: Obj | D10: Proj | G10: Actual | I10: Actual | K10: Budget | M10: Requested | O10: Recommended | Q10: Adopted | R10: Notes
A11: PERSONNEL SERVICES
A12: Limited Term Employee Wages | B12: 00109080 | C12: 501300 | E12: =_xlfn.CONCAT(B12,C12,D12) -> 00109080501300 | G12: =ROUND(IFERROR(VLOOKUP(_xlfn.CONCAT($B12,$C12,$D12),$A$45:$C$9994,3,FALSE),0),0) -> 0 | I12: =ROUND(IFERROR(VLOOKUP(_xlfn.CONCAT($B12,$C12,$D12),$A$45:$C$9994,2,FALSE),0),0) -> 0 | K12: 0 | M12: 0 | O12: =M12 -> 0 | Q12: =O12 -> 0
A13: Limited Term-Recreation | B13: 00109080 | C13: 501305 | E13: =_xlfn.CONCAT(B13,C13,D13) -> 00109080501305 | F13: $ | G13: =ROUND(IFERROR(VLOOKUP(_xlfn.CONCAT($B13,$C13,$D13),$A$45:$C$9994,3,FALSE),0),0) -> 53055 | H13: $ | I13: =ROUND(IFERROR(VLOOKUP(_xlfn.CONCAT($B13,$C13,$D13),$A$45:$C$9994,2,FALSE),0),0) -> 49606 | J13: $ | K13: 22500 | L13: $ | M13: 22500 | N13: $ | O13: =M13 -> 22500 | P13: $ | Q13: =O13 -> 22500
A14: FICA Taxes | B14: 00109080 | C14: 502100 | E14: =_xlfn.CONCAT(B14,C14,D14) -> 00109080502100 | G14: =ROUND(IFERROR(VLOOKUP(_xlfn.CONCAT($B14,$C14,$D14),$A$45:$C$9994,3,FALSE),0),0) -> 4059 | I14: =ROUND(IFERROR(VLOOKUP(_xlfn.CONCAT($B14,$C14,$D14),$A$45:$C$9994,2,FALSE),0),0) -> 3795 | K14: 1721 | M14: ='[1]Payroll Summary by Department'!N58 -> 1721 | O14: =M14 -> 1721 | Q14: =O14 -> 1721
A15: Total Personnel Services | E15: =_xlfn.CONCAT(B15,C15,D15) | F15: $ | G15: =SUM(G12:G14) -> 57114 | H15: $ | I15: =SUM(I12:I14) -> 53401 | J15: $ | K15: =SUM(K12:K14) -> 24221 | L15: $ | M15: =SUM(M12:M14) -> 24221 | N15: $ | O15: =SUM(O12:O14) -> 24221 | P15: $ | Q15: =SUM(Q12:Q14) -> 24221
A16: OPERATING EXPENDITURES | E16: =_xlfn.CONCAT(B16,C16,D16)
A17: Utilities-Energy/Power | B17: 00109080 | C17: 504310 | E17: =_xlfn.CONCAT(B17,C17,D17) -> 00109080504310 | F17: $ | G17: =ROUND(IFERROR(VLOOKUP(_xlfn.CONCAT($B17,$C17,$D17),$A$45:$C$9994,3,FALSE),0),0) -> 6800 | H17: $ | I17: =ROUND(IFERROR(VLOOKUP(_xlfn.CONCAT($B17,$C17,$D17),$A$45:$C$9994,2,FALSE),0),0) -> 6800 | J17: $ | K17: 6800 | L17: $ | M17: 6800 | N17: $ | O17: =M17 -> 6800 | P17: $ | Q17: =O17 -> 6800
A18: Rental/Lease-Facilities | B18: 00109080 | C18: 504450 | E18: =_xlfn.CONCAT(B18,C18,D18) -> 00109080504450 | G18: =ROUND(IFERROR(VLOOKUP(_xlfn.CONCAT($B18,$C18,$D18),$A$45:$C$9994,3,FALSE),0),0) -> 0 | I18: =ROUND(IFERROR(VLOOKUP(_xlfn.CONCAT($B18,$C18,$D18),$A$45:$C$9994,2,FALSE),0),0) -> 466
A19: Ballfield LBHS/Softball | B19: 00109080 | E19: =_xlfn.CONCAT(B19,C19,D19) -> 00109080 | G19: =ROUND(IFERROR(VLOOKUP(_xlfn.CONCAT($B19,$C19,$D19),$A$45:$C$9994,3,FALSE),0),0) -> 0 | I19: =ROUND(IFERROR(VLOOKUP(_xlfn.CONCAT($B19,$C19,$D19),$A$45:$C$9994,2,FALSE),0),0) -> 0 | K19: 5000 | M19: 5000 | O19: =M19 -> 5000 | Q19: =O19 -> 5000
A20: Repair/Maint-Bldgs/Facilities | B20: 00109080 | C20: 504601 | E20: =_xlfn.CONCAT(B20,C20,D20) -> 00109080504601 | G20: =ROUND(IFERROR(VLOOKUP(_xlfn.CONCAT($B20,$C20,$D20),$A$45:$C$9994,3,FALSE),0),0) -> 20206 | I20: =ROUND(IFERROR(VLOOKUP(_xlfn.CONCAT($B20,$C20,$D20),$A$45:$C$9994,2,FALSE),0),0) -> 19340 | K20: 0 | M20: 0 | O20: =M20 -> 0 | Q20: =O20 -> 0
A21: Field House Gym | B21: 00109080 | E21: =_xlfn.CONCAT(B21,C21,D21) -> 00109080 | G21: =ROUND(IFERROR(VLOOKUP(_xlfn.CONCAT($B21,$C21,$D21),$A$45:$C$9994,3,FALSE),0),0) -> 0 | I21: =ROUND(IFERROR(VLOOKUP(_xlfn.CONCAT($B21,$C21,$D21),$A$45:$C$9994,2,FALSE),0),0) -> 0 | K21: 0 | Q21: =O21 -> 0
A22: Resurface Gym Floors | B22: 00109080 | E22: =_xlfn.CONCAT(B22,C22,D22) -> 00109080 | G22: =ROUND(IFERROR(VLOOKUP(_xlfn.CONCAT($B22,$C22,$D22),$A$45:$C$9994,3,FALSE),0),0) -> 0 | I22: =ROUND(IFERROR(VLOOKUP(_xlfn.CONCAT($B22,$C22,$D22),$A$45:$C$9994,2,FALSE),0),0) -> 0 | K22: 15000 | M22: 15000 | O22: =M22 -> 15000 | Q22: =O22 -> 15000
A23: Gym Cleaning/Field House | B23: 00109080 | E23: =_xlfn.CONCAT(B23,C23,D23) -> 00109080 | G23: =ROUND(IFERROR(VLOOKUP(_xlfn.CONCAT($B23,$C23,$D23),$A$45:$C$9994,3,FALSE),0),0) -> 0 | I23: =ROUND(IFERROR(VLOOKUP(_xlfn.CONCAT($B23,$C23,$D23),$A$45:$C$9994,2,FALSE),0),0) -> 0 | K23: 5000 | M23: 5000 | O23: =M23 -> 5000 | Q23: =O23 -> 5000
A24: Replace Signage | B24: 00109080 | E24: =_xlfn.CONCAT(B24,C24,D24) -> 00109080 | G24: =ROUND(IFERROR(VLOOKUP(_xlfn.CONCAT($B24,$C24,$D24),$A$45:$C$9994,3,FALSE),0),0) -> 0 | I24: =ROUND(IFERROR(VLOOKUP(_xlfn.CONCAT($B24,$C24,$D24),$A$45:$C$9994,2,FALSE),0),0) -> 0 | K24: 1500 | M24: 1500 | O24: =M24 -> 1500 | Q24: =O24 -> 1500
A25: Repair/Maint-Ballfield | B25: 00109080 | C25: 504610 | E25: =_xlfn.CONCAT(B25,C25,D25) -> 00109080504610 | G25: =ROUND(IFERROR(VLOOKUP(_xlfn.CONCAT($B25,$C25,$D25),$A$45:$C$9994,3,FALSE),0),0) -> 8279 | I25: =ROUND(IFERROR(VLOOKUP(_xlfn.CONCAT($B25,$C25,$D25),$A$45:$C$9994,2,FALSE),0),0) -> 0 | K25: 0 | M25: 0 | O25: =M25 -> 0 | Q25: =O25 -> 0
A26: Repair/Maint-Equipment | B26: 00109080 | C26: 504620 | E26: =_xlfn.CONCAT(B26,C26,D26) -> 00109080504620 | G26: =ROUND(IFERROR(VLOOKUP(_xlfn.CONCAT($B26,$C26,$D26),$A$45:$C$9994,3,FALSE),0),0) -> 1818 | I26: =ROUND(IFERROR(VLOOKUP(_xlfn.CONCAT($B26,$C26,$D26),$A$45:$C$9994,2,FALSE),0),0) -> 11080 | K26: 0 | M26: 0 | O26: =M26 -> 0 | Q26: =O26 -> 0
A27: Basketball Goal (Rebudget) | B27: 00109080 | E27: =_xlfn.CONCAT(B27,C27,D27) -> 00109080 | G27: =ROUND(IFERROR(VLOOKUP(_xlfn.CONCAT($B27,$C27,$D27),$A$45:$C$9994,3,FALSE),0),0) -> 0 | I27: =ROUND(IFERROR(VLOOKUP(_xlfn.CONCAT($B27,$C27,$D27),$A$45:$C$9994,2,FALSE),0),0) -> 0 | K27: 0 | M27: 0 | O27: =M27 -> 0 | Q27: =O27 -> 0
A28: Basketball Goal Maintenance | B28: 00109080 | E28: =_xlfn.CONCAT(B28,C28,D28) -> 00109080 | G28: =ROUND(IFERROR(VLOOKUP(_xlfn.CONCAT($B28,$C28,$D28),$A$45:$C$9994,3,FALSE),0),0) -> 0 | I28: =ROUND(IFERROR(VLOOKUP(_xlfn.CONCAT($B28,$C28,$D28),$A$45:$C$9994,2,FALSE),0),0) -> 0 | K28: 12500 | M28: 12500 | O28: =M28 -> 12500 | Q28: =O28 -> 12500
A29: Repair/Main-Technology | B29: 00109080 | C29: 504683 | E29: =_xlfn.CONCAT(B29,C29,D29) -> 00109080504683 | G29: =ROUND(IFERROR(VLOOKUP(_xlfn.CONCAT($B29,$C29,$D29),$A$45:$C$9994,3,FALSE),0),0) -> 982 | I29: =ROUND(IFERROR(VLOOKUP(_xlfn.CONCAT($B29,$C29,$D29),$A$45:$C$9994,2,FALSE),0),0) -> 0 | K29: 2000 | M29: 2000 | O29: =M29 -> 2000 | Q29: =O29 -> 2000
A30: Repair/Maint-Other | B30: 00109080 | C30: 504699 | E30: =_xlfn.CONCAT(B30,C30,D30) -> 00109080504699 | G30: =ROUND(IFERROR(VLOOKUP(_xlfn.CONCAT($B30,$C30,$D30),$A$45:$C$9994,3,FALSE),0),0) -> 56 | I30: =ROUND(IFERROR(VLOOKUP(_xlfn.CONCAT($B30,$C30,$D30),$A$45:$C$9994,2,FALSE),0),0) -> 1296 | K30: 1000 | M30: 1000 | O30: =M30 -> 1000 | Q30: =O30 -> 1000
A31: Operating Supplies | B31: 00109080 | C31: 505201 | E31: =_xlfn.CONCAT(B31,C31,D31) -> 00109080505201 | G31: =ROUND(IFERROR(VLOOKUP(_xlfn.CONCAT($B31,$C31,$D31),$A$45:$C$9994,3,FALSE),0),0) -> 160 | I31: =ROUND(IFERROR(VLOOKUP(_xlfn.CONCAT($B31,$C31,$D31),$A$45:$C$9994,2,FALSE),0),0) -> 0 | K31: 0 | M31: 0 | O31: =M31 -> 0 | Q31: =O31 -> 0
A32: Rental Uniforms | B32: 00109080 | C32: 505505 | E32: =_xlfn.CONCAT(B32,C32,D32) -> 00109080505505 | G32: =ROUND(IFERROR(VLOOKUP(_xlfn.CONCAT($B32,$C32,$D32),$A$45:$C$9994,3,FALSE),0),0) -> 0 | I32: =ROUND(IFERROR(VLOOKUP(_xlfn.CONCAT($B32,$C32,$D32),$A$45:$C$9994,2,FALSE),0),0) -> 0 | K32: 0 | M32: 0 | O32: =M32 -> 0 | Q32: =O32 -> 0
A33: Park Equipment < $5,000 | B33: 00109080 | C33: 505750 | E33: =_xlfn.CONCAT(B33,C33,D33) -> 00109080505750 | G33: =ROUND(IFERROR(VLOOKUP(_xlfn.CONCAT($B33,$C33,$D33),$A$45:$C$9994,3,FALSE),0),0) -> 0 | I33: =ROUND(IFERROR(VLOOKUP(_xlfn.CONCAT($B33,$C33,$D33),$A$45:$C$9994,2,FALSE),0),0) -> 0 | K33: 2500 | M33: 2500 | O33: =M33 -> 2500 | Q33: =O33 -> 2500
A34: Technology Items < $5,000 | B34: 00109080 | C34: 505801 | E34: =_xlfn.CONCAT(B34,C34,D34) -> 00109080505801 | G34: =ROUND(IFERROR(VLOOKUP(_xlfn.CONCAT($B34,$C34,$D34),$A$45:$C$9994,3,FALSE),0),0)-1 -> 1538 | I34: =ROUND(IFERROR(VLOOKUP(_xlfn.CONCAT($B34,$C34,$D34),$A$45:$C$9994,2,FALSE),0),0) -> 0 | K34: 0 | M34: 0 | O34: =M34 -> 0 | Q34: =O34 -> 0
A36: Total Operating Expenditures | F36: $ | G36: =SUM(G17:G35) -> 39839 | H36: $ | I36: =SUM(I17:I35) -> 38982 | J36: $ | K36: =SUM(K17:K35) -> 51300 | L36: $ | M36: =SUM(M17:M35) -> 51300 | N36: $ | O36: =SUM(O17:O35) -> 51300 | P36: $ | Q36: =SUM(Q17:Q35) -> 51300
A37: TOTAL BUDGET | F37: $ | G37: =+G15+G36 -> 96953 | H37: $ | I37: =+I15+I36 -> 92383 | J37: $ | K37: =+K15+K36 -> 75521 | L37: $ | M37: =+M15+M36 -> 75521 | N37: $ | O37: =+O15+O36 -> 75521 | P37: $ | Q37: =+Q15+Q36 -> 75521
A40: Per GL | G40: 96953 | I40: 92383
A41: Diff | G41: =G37-G40 -> 0 | I41: =I37-I40 -> 0
B44: 2025 Actual | C44: 2024 Actual | G44: Missing Accounts Check?
A45: 00109080501201 | B45: 0 | C45: 0 | G45: =VLOOKUP(A45,E:E,1,FALSE) -> #N/A
A46: 00109080501300 | B46: 0 | C46: 0 | G46: =VLOOKUP(A46,E:E,1,FALSE) -> 00109080501300
A47: 00109080501305 | B47: 49606.48 | C47: 53055.03 | G47: =VLOOKUP(A47,E:E,1,FALSE) -> 00109080501305
A48: 00109080501400 | B48: 0 | C48: 0 | G48: =VLOOKUP(A48,E:E,1,FALSE) -> #N/A
A49: 00109080502100 | B49: 3795.11 | C49: 4058.94 | G49: =VLOOKUP(A49,E:E,1,FALSE) -> 00109080502100
A50: 00109080504120 | B50: 0 | C50: 0 | G50: =VLOOKUP(A50,E:E,1,FALSE) -> #N/A
A51: 00109080504310 | B51: 6800 | C51: 6800 | G51: =VLOOKUP(A51,E:E,1,FALSE) -> 00109080504310
A52: 00109080504450 | B52: 466 | C52: 0 | G52: =VLOOKUP(A52,E:E,1,FALSE) -> 00109080504450
A53: 00109080504601 | B53: 19340 | C53: 20206 | G53: =VLOOKUP(A53,E:E,1,FALSE) -> 00109080504601
A54: 00109080504610 | B54: 0 | C54: 8279.04 | G54: =VLOOKUP(A54,E:E,1,FALSE) -> 00109080504610
A55: 00109080504620 | B55: 11079.5 | C55: 1817.5 | G55: =VLOOKUP(A55,E:E,1,FALSE) -> 00109080504620
A56: 00109080504683 | B56: 0 | C56: 982.31 | G56: =VLOOKUP(A56,E:E,1,FALSE) -> 00109080504683
... A67: 00109080999999 | B67: 0 | C67: 0 | G67: =VLOOKUP(A67,E:E,1,FALSE) -> #N/A

Sheet 909 Lotus
A1: City of Altamonte Springs, Florida
A2: ='[1]Admin Summary'!A2:K2 -> Fiscal Year 2026 / 2027 Annual Budget
A4: Leisure and Maintenance Services Department
A5: Lake Lotus Park
A6: General Fund (00109090)
M8: =' 911 Admin'!M8 -> 2027
G9: =' 911 Admin'!G9 -> 2024 | I9: =' 911 Admin'!I9 -> 2025 | K9: =' 911 Admin'!K9 -> 2026 | M9: Department | O9: Manager | Q9: Commission
B10: Org | C10: Obj | D10: Proj | G10: Actual | I10: Actual | K10: Budget | M10: Requested | O10: Recommended | Q10: Adopted | R10: Notes
A11: PERSONNEL SERVICES
A12: Regular Salaries & Wages Base: 3 Positions | B12: 00109090 | C12: 501201 | E12: =_xlfn.CONCAT(B12,C12,D12) -> 00109090501201 | F12: $ | G12: =ROUND(IFERROR(VLOOKUP(_xlfn.CONCAT($B12,$C12,$D12),$A$75:$C$9994,3,FALSE),0),0) -> 116539 | H12: $ | I12: =ROUND(IFERROR(VLOOKUP(_xlfn.CONCAT($B12,$C12,$D12),$A$75:$C$9994,2,FALSE),0),0) -> 126239 | J12: $ | K12: 138033 | L12: $ | M12: ='[1]Payroll Summary by Department'!C59 -> 138033 | N12: $ | O12: =M12 -> 138033 | P12: $ | Q12: =O12 -> 138033
A13: Sign Incentive Award | B13: 00109090 | C13: 501290 | E13: =_xlfn.CONCAT(B13,C13,D13) -> 00109090501290 | G13: =ROUND(IFERROR(VLOOKUP(_xlfn.CONCAT($B13,$C13,$D13),$A$75:$C$9994,3,FALSE),0),0) -> 0 | I13: =ROUND(IFERROR(VLOOKUP(_xlfn.CONCAT($B13,$C13,$D13),$A$75:$C$9994,2,FALSE),0),0) -> 0 | K13: 0 | M13: 0 | O13: =M13 -> 0 | Q13: =O13 -> 0
A14: Overtime | B14: 00109090 | C14: 501400 | E14: =_xlfn.CONCAT(B14,C14,D14) -> 00109090501400 | G14: =ROUND(IFERROR(VLOOKUP(_xlfn.CONCAT($B14,$C14,$D14),$A$75:$C$9994,3,FALSE),0),0) -> 2579 | I14: =ROUND(IFERROR(VLOOKUP(_xlfn.CONCAT($B14,$C14,$D14),$A$75:$C$9994,2,FALSE),0),0) -> 6319 | K14: 3000 | M14: 3000 | O14: =M14 -> 3000 | Q14: =O14 -> 3000
A15: On Call | B15: 00109090 | C15: 501401 | E15: =_xlfn.CONCAT(B15,C15,D15) -> 00109090501401 | G15: =ROUND(IFERROR(VLOOKUP(_xlfn.CONCAT($B15,$C15,$D15),$A$75:$C$9994,3,FALSE),0),0) -> 0 | I15: =ROUND(IFERROR(VLOOKUP(_xlfn.CONCAT($B15,$C15,$D15),$A$75:$C$9994,2,FALSE),0),0) -> 0 | K15: 750 | M15: 750 | O15: =M15 -> 750 | Q15: =O15 -> 750
A16: Add Pays | B16: 00109090 | C16: 501600 | E16: =_xlfn.CONCAT(B16,C16,D16) -> 00109090501600 | G16: =ROUND(IFERROR(VLOOKUP(_xlfn.CONCAT($B16,$C16,$D16),$A$75:$C$9994,3,FALSE),0),0) -> 4234 | I16: =ROUND(IFERROR(VLOOKUP(_xlfn.CONCAT($B16,$C16,$D16),$A$75:$C$9994,2,FALSE),0),0) -> 3071 | K16: 7800 | M16: ='[1]Payroll Summary by Department'!I59 -> 7800 | O16: =M16 -> 7800 | Q16: =O16 -> 7800
A17: Cell Phone Allowance | B17: 00109090 | C17: 501702 | E17: =_xlfn.CONCAT(B17,C17,D17) -> 00109090501702 | G17: =ROUND(IFERROR(VLOOKUP(_xlfn.CONCAT($B17,$C17,$D17),$A$75:$C$9994,3,FALSE),0),0) -> 348 | I17: =ROUND(IFERROR(VLOOKUP(_xlfn.CONCAT($B17,$C17,$D17),$A$75:$C$9994,2,FALSE),0),0) -> 602 | K17: 600 | M17: ='[1]Payroll Summary by Department'!L59 -> 600 | O17: =M17 -> 600 | Q17: =O17 -> 600
A18: Uniform Allowance | B18: 00109090 | C18: 501800 | E18: =_xlfn.CONCAT(B18,C18,D18) -> 00109090501800 | G18: =ROUND(IFERROR(VLOOKUP(_xlfn.CONCAT($B18,$C18,$D18),$A$75:$C$9994,3,FALSE),0),0) -> 0 | I18: =ROUND(IFERROR(VLOOKUP(_xlfn.CONCAT($B18,$C18,$D18),$A$75:$C$9994,2,FALSE),0),0) -> 0 | K18: 0 | M18: 0 | O18: =M18 -> 0 | Q18: =O18 -> 0
A19: FICA Taxes | B19: 00109090 | C19: 502100 | E19: =_xlfn.CONCAT(B19,C19,D19) -> 00109090502100 | G19: =ROUND(IFERROR(VLOOKUP(_xlfn.CONCAT($B19,$C19,$D19),$A$75:$C$9994,3,FALSE),0),0) -> 9284 | I19: =ROUND(IFERROR(VLOOKUP(_xlfn.CONCAT($B19,$C19,$D19),$A$75:$C$9994,2,FALSE),0),0) -> 10311 | K19: 10892 | M19: ='[1]Payroll Summary by Department'!N59 -> 10892 | O19: =M19 -> 10892 | Q19: =O19 -> 10892
A20: Retirement Contributions | B20: 00109090 | C20: 502200 | E20: =_xlfn.CONCAT(B20,C20,D20) -> 00109090502200 | G20: =ROUND(IFERROR(VLOOKUP(_xlfn.CONCAT($B20,$C20,$D20),$A$75:$C$9994,3,FALSE),0),0) -> 12011 | I20: =ROUND(IFERROR(VLOOKUP(_xlfn.CONCAT($B20,$C20,$D20),$A$75:$C$9994,2,FALSE),0),0) -> 12548 | K20: 17525 | M20: ='[1]Payroll Summary by Department'!O59+'[1]Payroll Summary by Department'!P59 -> 17525 | O20: =M20 -> 17525 | Q20: =O20 -> 17525
A21: Health Insurance | B21: 00109090 | C21: 502300 | E21: =_xlfn.CONCAT(B21,C21,D21) -> 00109090502300 | G21: =ROUND(IFERROR(VLOOKUP(_xlfn.CONCAT($B21,$C21,$D21),$A$75:$C$9994,3,FALSE),0),0) -> 24981 | I21: =ROUND(IFERROR(VLOOKUP(_xlfn.CONCAT($B21,$C21,$D21),$A$75:$C$9994,2,FALSE),0),0) -> 24458 | K21: 34554 | M21: ='[1]Payroll Summary by Department'!Q59 -> 34554 | O21: =M21 -> 34554 | Q21: =O21 -> 34554
A22: Life Insurance | B22: 00109090 | C22: 502400 | E22: =_xlfn.CONCAT(B22,C22,D22) -> 00109090502400 | G22: =ROUND(IFERROR(VLOOKUP(_xlfn.CONCAT($B22,$C22,$D22),$A$75:$C$9994,3,FALSE),0),0) -> 236 | I22: =ROUND(IFERROR(VLOOKUP(_xlfn.CONCAT($B22,$C22,$D22),$A$75:$C$9994,2,FALSE),0),0) -> 250 | K22: 261 | M22: ='[1]Payroll Summary by Department'!R59 -> 261 | O22: =M22 -> 261 | Q22: =O22 -> 261
A23: Total Personnel Services | E23: =_xlfn.CONCAT(B23,C23,D23) | F23: $ | G23: =SUM(G12:G22) -> 170212 | H23: $ | I23: =SUM(I12:I22) -> 183798 | J23: $ | K23: =SUM(K12:K22) -> 213415 | L23: $ | M23: =SUM(M12:M22) -> 213415 | N23: $ | O23: =SUM(O12:O22) -> 213415 | P23: $ | Q23: =SUM(Q12:Q22) -> 213415
A24: POSITION ROSTER | E24: =_xlfn.CONCAT(B24,C24,D24)
A25: Full-Time Employees | E25: =_xlfn.CONCAT(B25,C25,D25)
A26: Interpretive Park Ranger Supervisor | C26: 3A | E26: =_xlfn.CONCAT(B26,C26,D26) -> 3A | G26: 1 | I26: 1 | K26: 1 | M26: 1 | O26: =M26 -> 1 | Q26: =O26 -> 1
A27: Interpretive Park Ranger | C27: 4C | E27: =_xlfn.CONCAT(B27,C27,D27) -> 4C | G27: 2 | I27: 2 | K27: 2 | M27: 2 | O27: 2 | Q27: =O27 -> 2
A28: Total Positions | E28: =_xlfn.CONCAT(B28,C28,D28) | G28: =SUM(G26:G27) -> 3 | I28: =SUM(I26:I27) -> 3 | K28: =SUM(K26:K27) -> 3 | M28: =SUM(M26:M27) -> 3 | O28: =SUM(O26:O27) -> 3 | Q28: =SUM(Q26:Q27) -> 3
A29: OPERATING EXPENDITURES | E29: =_xlfn.CONCAT(B29,C29,D29)
A30: Other Services-Temporary Labor | B30: 00109090 | C30: 503450 | E30: =_xlfn.CONCAT(B30,C30,D30) -> 00109090503450 | F30: $ | G30: =ROUND(IFERROR(VLOOKUP(_xlfn.CONCAT($B30,$C30,$D30),$A$75:$C$9994,3,FALSE),0),0) -> 0 | H30: $ | I30: =ROUND(IFERROR(VLOOKUP(_xlfn.CONCAT($B30,$C30,$D30),$A$75:$C$9994,2,FALSE),0),0) -> 0 | J30: $ | K30: 0 | L30: $ | M30: 0 | N30: $ | O30: =M30 -> 0 | P30: $ | Q30: =O30 -> 0
A31: Other Services-Trash Disposal | B31: 00109090 | C31: 503460 | E31: =_xlfn.CONCAT(B31,C31,D31) -> 00109090503460 | F31: $ | G31: =ROUND(IFERROR(VLOOKUP(_xlfn.CONCAT($B31,$C31,$D31),$A$75:$C$9994,3,FALSE),0),0) -> 0 | H31: $ | I31: =ROUND(IFERROR(VLOOKUP(_xlfn.CONCAT($B31,$C31,$D31),$A$75:$C$9994,2,FALSE),0),0) -> 0 | J31: $ | K31: 0 | L31: $ | M31: 0 | N31: $ | O31: =M31 -> 0 | P31: $ | Q31: =O31 -> 0
A32: Other Services-Sludge Hauling | B32: 00109090 | C32: 503461 | E32: =_xlfn.CONCAT(B32,C32,D32) -> 00109090503461 | F32: $ | G32: =ROUND(IFERROR(VLOOKUP(_xlfn.CONCAT($B32,$C32,$D32),$A$75:$C$9994,3,FALSE),0),0) -> 0 | H32: $ | I32: =ROUND(IFERROR(VLOOKUP(_xlfn.CONCAT($B32,$C32,$D32),$A$75:$C$9994,2,FALSE),0),0) -> 0 | J32: $ | K32: 0 | L32: $ | M32: 0 | N32: $ | O32: =M32 -> 0 | P32: $ | Q32: =O32 -> 0
A33: Other Contractual Service | B33: 00109090 | C33: 503499 | E33: =_xlfn.CONCAT(B33,C33,D33) -> 00109090503499 | F33: $ | G33: =ROUND(IFERROR(VLOOKUP(_xlfn.CONCAT($B33,$C33,$D33),$A$75:$C$9994,3,FALSE),0),0) -> 0 | H33: $ | I33: =ROUND(IFERROR(VLOOKUP(_xlfn.CONCAT($B33,$C33,$D33),$A$75:$C$9994,2,FALSE),0),0) -> 0 | J33: $ | K33: 0 | L33: $ | M33: 0 | N33: $ | O33: =M33 -> 0 | P33: $ | Q33: =O33 -> 0
A34: Educational Incentive | B34: 00109090 | C34: 503901 | E34: =_xlfn.CONCAT(B34,C34,D34) -> 00109090503901 | F34: $ | G34: =ROUND(IFERROR(VLOOKUP(_xlfn.CONCAT($B34,$C34,$D34),$A$75:$C$9994,3,FALSE),0),0) -> 0 | H34: $ | I34: =ROUND(IFERROR(VLOOKUP(_xlfn.CONCAT($B34,$C34,$D34),$A$75:$C$9994,2,FALSE),0),0) -> 0 | J34: $ | K34: 0 | L34: $ | M34: 0 | N34: $ | O34: =M34 -> 0 | P34: $ | Q34: =O34 -> 0
A35: Certifications | B35: 00109090 | E35: =_xlfn.CONCAT(B35,C35,D35) -> 00109090 | F35: $ | G35: =ROUND(IFERROR(VLOOKUP(_xlfn.CONCAT($B35,$C35,$D35),$A$75:$C$9994,3,FALSE),0),0) -> 0 | H35: $ | I35: =ROUND(IFERROR(VLOOKUP(_xlfn.CONCAT($B35,$C35,$D35),$A$75:$C$9994,2,FALSE),0),0) -> 0 | J35: $ | K35: 0 | L35: $ | M35: 0 | N35: $ | O35: =M35 -> 0 | P35: $ | Q35: =O35 -> 0
A36: Non-Travel Training | B36: 00109090 | C36: 504060 | E36: =_xlfn.CONCAT(B36,C36,D36) -> 00109090504060 | G36: =ROUND(IFERROR(VLOOKUP(_xlfn.CONCAT($B36,$C36,$D36),$A$75:$C$9994,3,FALSE),0),0) -> 0 | I36: =ROUND(IFERROR(VLOOKUP(_xlfn.CONCAT($B36,$C36,$D36),$A$75:$C$9994,2,FALSE),0),0) -> 0 | K36: 750 | M36: 750 | O36: =M36 -> 750 | Q36: =O36 -> 750
A37: Travel-Training | B37: 00109090 | C37: 504070 | E37: =_xlfn.CONCAT(B37,C37,D37) -> 00109090504070 | G37: =ROUND(IFERROR(VLOOKUP(_xlfn.CONCAT($B37,$C37,$D37),$A$75:$C$9994,3,FALSE),0),0) -> 0 | I37: =ROUND(IFERROR(VLOOKUP(_xlfn.CONCAT($B37,$C37,$D37),$A$75:$C$9994,2,FALSE),0),0) -> 0 | K37: 0 | M37: 0 | O37: =M37 -> 0 | Q37: =O37 -> 0
A38: Rental/Lease-Facilities | B38: 00109090 | C38: 504450 | E38: =_xlfn.CONCAT(B38,C38,D38) -> 00109090504450 | G38: =ROUND(IFERROR(VLOOKUP(_xlfn.CONCAT($B38,$C38,$D38),$A$75:$C$9994,3,FALSE),0),0) -> 1434 | I38: =ROUND(IFERROR(VLOOKUP(_xlfn.CONCAT($B38,$C38,$D38),$A$75:$C$9994,2,FALSE),0),0) -> 1243 | K38: 0 | M38: 0 | O38: =M38 -> 0 | Q38: =O38 -> 0
A39: Storage Unit | B39: 00109090 | E39: =_xlfn.CONCAT(B39,C39,D39) -> 00109090 | G39: =ROUND(IFERROR(VLOOKUP(_xlfn.CONCAT($B39,$C39,$D39),$A$75:$C$9994,3,FALSE),0),0) -> 0 | I39: =ROUND(IFERROR(VLOOKUP(_xlfn.CONCAT($B39,$C39,$D39),$A$75:$C$9994,2,FALSE),0),0) -> 0 | K39: 1750 | M39: 1750 | O39: =M39 -> 1750 | Q39: =O39 -> 1750
A40: Repair/Maint-Bldgs/Facilities | B40: 00109090 | C40: 504601 | E40: =_xlfn.CONCAT(B40,C40,D40) -> 00109090504601 | G40: =ROUND(IFERROR(VLOOKUP(_xlfn.CONCAT($B40,$C40,$D40),$A$75:$C$9994,3,FALSE),0),0) -> 2060 | I40: =ROUND(IFERROR(VLOOKUP(_xlfn.CONCAT($B40,$C40,$D40),$A$75:$C$9994,2,FALSE),0),0) -> 7247 | K40: 8000 | M40: 8000 | O40: =M40 -> 8000 | Q40: =O40 -> 8000
A41: Replace Signage | B41: 00109090 | E41: =_xlfn.CONCAT(B41,C41,D41) -> 00109090 | G41: =ROUND(IFERROR(VLOOKUP(_xlfn.CONCAT($B41,$C41,$D41),$A$75:$C$9994,3,FALSE),0),0) -> 0 | I41: =ROUND(IFERROR(VLOOKUP(_xlfn.CONCAT($B41,$C41,$D41),$A$75:$C$9994,2,FALSE),0),0) -> 0 | K41: 2000 | M41: 2000 | O41: =M41 -> 2000 | Q41: =O41 -> 2000
A42: Repair/Maint-Fencing/Security | B42: 00109090 | C42: 504602 | E42: =_xlfn.CONCAT(B42,C42,D42) -> 00109090504602 | G42: =ROUND(IFERROR(VLOOKUP(_xlfn.CONCAT($B42,$C42,$D42),$A$75:$C$9994,3,FALSE),0),0) -> 7465 | I42: =ROUND(IFERROR(VLOOKUP(_xlfn.CONCAT($B42,$C42,$D42),$A$75:$C$9994,2,FALSE),0),0) -> 11931 | K42: 0 | M42: 0 | O42: =M42 -> 0 | Q42: =O42 -> 0
A43: Fence | B43: 00109090 | E43: =_xlfn.CONCAT(B43,C43,D43) -> 00109090 | G43: =ROUND(IFERROR(VLOOKUP(_xlfn.CONCAT($B43,$C43,$D43),$A$75:$C$9994,3,FALSE),0),0) -> 0 | I43: =ROUND(IFERROR(VLOOKUP(_xlfn.CONCAT($B43,$C43,$D43),$A$75:$C$9994,2,FALSE),0),0) -> 0 | K43: 10000 | M43: 10000 | O43: =M43 -> 10000 | Q43: =O43 -> 10000
A44: Repair/Maint-Landscape | B44: 00109090 | C44: 504615 | E44: =_xlfn.CONCAT(B44,C44,D44) -> 00109090504615 | G44: =ROUND(IFERROR(VLOOKUP(_xlfn.CONCAT($B44,$C44,$D44),$A$75:$C$9994,3,FALSE),0),0) -> 0 | I44: =ROUND(IFERROR(VLOOKUP(_xlfn.CONCAT($B44,$C44,$D44),$A$75:$C$9994,2,FALSE),0),0) -> 0 | K44: 0 | M44: 0 | O44: =M44 -> 0 | Q44: =O44 -> 0
A45: Repair/Maint-Equipment | B45: 00109090 | C45: 504620 | E45: =_xlfn.CONCAT(B45,C45,D45) -> 00109090504620 | G45: =ROUND(IFERROR(VLOOKUP(_xlfn.CONCAT($B45,$C45,$D45),$A$75:$C$9994,3,FALSE),0),0) -> 209 | I45: =ROUND(IFERROR(VLOOKUP(_xlfn.CONCAT($B45,$C45,$D45),$A$75:$C$9994,2,FALSE),0),0) -> 0 | K45: 1500 | M45: 1500 | O45: =M45 -> 1500 | Q45: =O45 -> 1500
A46: Playground | B46: 00109090 | E46: =_xlfn.CONCAT(B46,C46,D46) -> 00109090 | G46: =ROUND(IFERROR(VLOOKUP(_xlfn.CONCAT($B46,$C46,$D46),$A$75:$C$9994,3,FALSE),0),0) -> 0 | I46: =ROUND(IFERROR(VLOOKUP(_xlfn.CONCAT($B46,$C46,$D46),$A$75:$C$9994,2,FALSE),0),0) -> 0 | K46: 5000 | M46: 5000 | O46: =M46 -> 5000 | Q46: =O46 -> 5000
A47: Lumber | B47: 00109090 | E47: =_xlfn.CONCAT(B47,C47,D47) -> 00109090 | G47: =ROUND(IFERROR(VLOOKUP(_xlfn.CONCAT($B47,$C47,$D47),$A$75:$C$9994,3,FALSE),0),0) -> 0 | I47: =ROUND(IFERROR(VLOOKUP(_xlfn.CONCAT($B47,$C47,$D47),$A$75:$C$9994,2,FALSE),0),0) -> 0 | K47: 5000 | M47: 5000 | O47: =M47 -> 5000 | Q47: =O47 -> 5000
A48: Repair/Maint-Hardscape | B48: 00109090 | E48: =_xlfn.CONCAT(B48,C48,D48) -> 00109090 | G48: =ROUND(IFERROR(VLOOKUP(_xlfn.CONCAT($B48,$C48,$D48),$A$75:$C$9994,3,FALSE),0),0) -> 0 | I48: =ROUND(IFERROR(VLOOKUP(_xlfn.CONCAT($B48,$C48,$D48),$A$75:$C$9994,2,FALSE),0),0) -> 0
A49: Concrete/Stone/Brick/Paver | B49: 00109090 | C49: 504675 | E49: =_xlfn.CONCAT(B49,C49,D49) -> 00109090504675 | G49: =ROUND(IFERROR(VLOOKUP(_xlfn.CONCAT($B49,$C49,$D49),$A$75:$C$9994,3,FALSE),0),0) -> 0 | I49: =ROUND(IFERROR(VLOOKUP(_xlfn.CONCAT($B49,$C49,$D49),$A$75:$C$9994,2,FALSE),0),0) -> 0 | K49: 3000 | M49: 3000 | O49: =M49 -> 3000 | Q49: =O49 -> 3000
A50: Printing & Binding | B50: 00109090 | C50: 504710 | E50: =_xlfn.CONCAT(B50,C50,D50) -> 00109090504710 | G50: =ROUND(IFERROR(VLOOKUP(_xlfn.CONCAT($B50,$C50,$D50),$A$75:$C$9994,3,FALSE),0),0) -> 429 | I50: =ROUND(IFERROR(VLOOKUP(_xlfn.CONCAT($B50,$C50,$D50),$A$75:$C$9994,2,FALSE),0),0) -> 298 | K50: 1000 | M50: 1000 | O50: =M50 -> 1000 | Q50: =O50 -> 1000
A51: Promo Activity-Community Programs | B51: 00109090 | C51: 504810 | E51: =_xlfn.CONCAT(B51,C51,D51) -> 00109090504810 | G51: =ROUND(IFERROR(VLOOKUP(_xlfn.CONCAT($B51,$C51,$D51),$A$75:$C$9994,3,FALSE),0),0) -> 0 | I51: =ROUND(IFERROR(VLOOKUP(_xlfn.CONCAT($B51,$C51,$D51),$A$75:$C$9994,2,FALSE),0),0) -> 0 | K51: 1500 | M51: 1500 | O51: =M51 -> 1500 | Q51: =O51 -> 1500
A52: Office Supplies | B52: 00109090 | C52: 505101 | E52: =_xlfn.CONCAT(B52,C52,D52) -> 00109090505101 | G52: =ROUND(IFERROR(VLOOKUP(_xlfn.CONCAT($B52,$C52,$D52),$A$75:$C$9994,3,FALSE),0),0) -> 0 | I52: =ROUND(IFERROR(VLOOKUP(_xlfn.CONCAT($B52,$C52,$D52),$A$75:$C$9994,2,FALSE),0),0) -> 0 | K52: 0 | M52: 0 | O52: =M52 -> 0 | Q52: =O52 -> 0
A53: Operating Supplies | B53: 00109090 | C53: 505201 | E53: =_xlfn.CONCAT(B53,C53,D53) -> 00109090505201 | G53: =ROUND(IFERROR(VLOOKUP(_xlfn.CONCAT($B53,$C53,$D53),$A$75:$C$9994,3,FALSE),0),0) -> 12624 | I53: =ROUND(IFERROR(VLOOKUP(_xlfn.CONCAT($B53,$C53,$D53),$A$75:$C$9994,2,FALSE),0),0) -> 12488 | K53: 14000 | M53: 14000 | O53: =M53 -> 14000 | Q53: =O53 -> 14000
A54: Custodial Supplies | B54: 00109090 | C54: 505210 | E54: =_xlfn.CONCAT(B54,C54,D54) -> 00109090505210 | G54: =ROUND(IFERROR(VLOOKUP(_xlfn.CONCAT($B54,$C54,$D54),$A$75:$C$9994,3,FALSE),0),0) -> 0 | I54: =ROUND(IFERROR(VLOOKUP(_xlfn.CONCAT($B54,$C54,$D54),$A$75:$C$9994,2,FALSE),0),0) -> 63 | K54: 0 | M54: 0 | O54: =M54 -> 0 | Q54: =O54 -> 0
A55: Safety/First Aid Supplies | B55: 00109090 | C55: 505260 | E55: =_xlfn.CONCAT(B55,C55,D55) -> 00109090505260 | G55: =ROUND(IFERROR(VLOOKUP(_xlfn.CONCAT($B55,$C55,$D55),$A$75:$C$9994,3,FALSE),0),0) -> 0 | I55: =ROUND(IFERROR(VLOOKUP(_xlfn.CONCAT($B55,$C55,$D55),$A$75:$C$9994,2,FALSE),0),0) -> 0 | K55: 0 | M55: 0 | O55: =M55 -> 0 | Q55: =O55 -> 0
A56: Landscaping Supplies | B56: 00109090 | C56: 505285 | E56: =_xlfn.CONCAT(B56,C56,D56) -> 00109090505285 | G56: =ROUND(IFERROR(VLOOKUP(_xlfn.CONCAT($B56,$C56,$D56),$A$75:$C$9994,3,FALSE),0),0) -> 0 | I56: =ROUND(IFERROR(VLOOKUP(_xlfn.CONCAT($B56,$C56,$D56),$A$75:$C$9994,2,FALSE),0),0) -> 0 | K56: 0 | M56: 0 | O56: =M56 -> 0 | Q56: =O56 -> 0
A57: Warehouse Issued Uniforms | B57: 00109090 | E57: =_xlfn.CONCAT(B57,C57,D57) -> 00109090 | G57: =ROUND(IFERROR(VLOOKUP(_xlfn.CONCAT($B57,$C57,$D57),$A$75:$C$9994,3,FALSE),0),0) -> 0 | I57: =ROUND(IFERROR(VLOOKUP(_xlfn.CONCAT($B57,$C57,$D57),$A$75:$C$9994,2,FALSE),0),0) -> 0 | K57: 0 | M57: 0 | O57: =M57 -> 0 | Q57: =O57 -> 0
A58: Rental Uniforms | B58: 00109090 | C58: 505505 | E58: =_xlfn.CONCAT(B58,C58,D58) -> 00109090505505 | G58: =ROUND(IFERROR(VLOOKUP(_xlfn.CONCAT($B58,$C58,$D58),$A$75:$C$9994,3,FALSE),0),0) -> 1199 | I58: =ROUND(IFERROR(VLOOKUP(_xlfn.CONCAT($B58,$C58,$D58),$A$75:$C$9994,2,FALSE),0),0) -> 772 | K58: 1200 | M58: 1200 | O58: =M58 -> 1200 | Q58: =O58 -> 1200
A59: Boots/Shoes | B59: 00109090 | C59: 505532 | E59: =_xlfn.CONCAT(B59,C59,D59) -> 00109090505532 | G59: =ROUND(IFERROR(VLOOKUP(_xlfn.CONCAT($B59,$C59,$D59),$A$75:$C$9994,3,FALSE),0),0)+1 -> 154 | I59: =ROUND(IFERROR(VLOOKUP(_xlfn.CONCAT($B59,$C59,$D59),$A$75:$C$9994,2,FALSE),0),0)+2 -> 338 | K59: 825 | M59: 825 | O59: =M59 -> 825 | Q59: =O59 -> 825
A60: Safety Uniforms | B60: 00109090 | C60: 505540 | E60: =_xlfn.CONCAT(B60,C60,D60) -> 00109090505540 | G60: =ROUND(IFERROR(VLOOKUP(_xlfn.CONCAT($B60,$C60,$D60),$A$75:$C$9994,3,FALSE),0),0) -> 0 | I60: =ROUND(IFERROR(VLOOKUP(_xlfn.CONCAT($B60,$C60,$D60),$A$75:$C$9994,2,FALSE),0),0) -> 0 | K60: 500 | M60: 500 | O60: =M60 -> 500 | Q60: =O60 -> 500
A61: Purchased Uniforms | B61: 00109090 | C61: 505550 | E61: =_xlfn.CONCAT(B61,C61,D61) -> 00109090505550 | G61: =ROUND(IFERROR(VLOOKUP(_xlfn.CONCAT($B61,$C61,$D61),$A$75:$C$9994,3,FALSE),0),0) -> 0 | I61: =ROUND(IFERROR(VLOOKUP(_xlfn.CONCAT($B61,$C61,$D61),$A$75:$C$9994,2,FALSE),0),0) -> 0 | K61: 3000 | M61: 3000 | O61: =M61 -> 3000 | Q61: =O61 -> 3000
A62: Small Tools/Equip < $5,000 | B62: 00109090 | C62: 505701 | E62: =_xlfn.CONCAT(B62,C62,D62) -> 00109090505701 | G62: =ROUND(IFERROR(VLOOKUP(_xlfn.CONCAT($B62,$C62,$D62),$A$75:$C$9994,3,FALSE),0),0) -> 0 | I62: =ROUND(IFERROR(VLOOKUP(_xlfn.CONCAT($B62,$C62,$D62),$A$75:$C$9994,2,FALSE),0),0) -> 0 | K62: 800 | M62: 800 | O62: =M62 -> 800 | Q62: =O62 -> 800
A63: Office Equipment < $5,000 | B63: 00109090 | C63: 505715 | E63: =_xlfn.CONCAT(B63,C63,D63) -> 00109090505715 | G63: =ROUND(IFERROR(VLOOKUP(_xlfn.CONCAT($B63,$C63,$D63),$A$75:$C$9994,3,FALSE),0),0) -> 0 | I63: =ROUND(IFERROR(VLOOKUP(_xlfn.CONCAT($B63,$C63,$D63),$A$75:$C$9994,2,FALSE),0),0) -> 0 | K63: 0 | M63: 0 | O63: =M63 -> 0 | Q63: =O63 -> 0
A64: Park Equipment < $5,000 | B64: 00109090 | C64: 505750 | E64: =_xlfn.CONCAT(B64,C64,D64) -> 00109090505750 | G64: =ROUND(IFERROR(VLOOKUP(_xlfn.CONCAT($B64,$C64,$D64),$A$75:$C$9994,3,FALSE),0),0) -> 0 | I64: =ROUND(IFERROR(VLOOKUP(_xlfn.CONCAT($B64,$C64,$D64),$A$75:$C$9994,2,FALSE),0),0) -> 1228 | K64: 4950 | M64: 4950 | O64: =M64 -> 4950 | Q64: =O64 -> 4950
A65: Technology Items < $5,000 | B65: 00109090 | C65: 505801 | E65: =_xlfn.CONCAT(B65,C65,D65) -> 00109090505801 | G65: =ROUND(IFERROR(VLOOKUP(_xlfn.CONCAT($B65,$C65,$D65),$A$75:$C$9994,3,FALSE),0),0) -> 0 | I65: =ROUND(IFERROR(VLOOKUP(_xlfn.CONCAT($B65,$C65,$D65),$A$75:$C$9994,2,FALSE),0),0) -> 0 | K65: 0 | M65: 0 | O65: =M65 -> 0 | Q65: =O65 -> 0
A67: Total Operating Expenditures | F67: $ | G67: =SUM(G30:G66) -> 25574 | H67: $ | I67: =SUM(I30:I66) -> 35608 | J67: $ | K67: =SUM(K30:K66) -> 64775 | L67: $ | M67: =SUM(M30:M66) -> 64775 | N67: $ | O67: =SUM(O30:O66) -> 64775 | P67: $ | Q67: =SUM(Q30:Q66) -> 64775
A68: TOTAL BUDGET | F68: $ | G68: =+G67+G23 -> 195786 | H68: $ | I68: =+I67+I23 -> 219406 | J68: $ | K68: =+K67+K23 -> 278190 | L68: $ | M68: =+M67+M23 -> 278190 | N68: $ | O68: =+O67+O23 -> 278190 | P68: $ | Q68: =+Q67+Q23 -> 278190
A70: Per GL | G70: 195786 | I70: 219406
A71: Diff | G71: =G68-G70 -> 0 | I71: =I68-I70 -> 0
B74: 2025 Actual | C74: 2024 Actual | G74: Missing Accounts Check?
A75: 00109090501201 | B75: 126239.14 | C75: 116538.67 | G75: =VLOOKUP(A75,E:E,1,FALSE) -> 00109090501201
A76: 00109090501290 | B76: 0 | C76: 0 | G76: =VLOOKUP(A76,E:E,1,FALSE) -> 00109090501290
A77: 00109090501300 | B77: 0 | C77: 0 | G77: =VLOOKUP(A77,E:E,1,FALSE) -> #N/A
A78: 00109090501400 | B78: 6319.46 | C78: 2578.64 | G78: =VLOOKUP(A78,E:E,1,FALSE) -> 00109090501400
A79: 00109090501401 | B79: 0 | C79: 0 | G79: =VLOOKUP(A79,E:E,1,FALSE) -> 00109090501401
A80: 00109090501600 | B80: 3070.5 | C80: 4234.01 | G80: =VLOOKUP(A80,E:E,1,FALSE) -> 00109090501600
A81: 00109090501702 | B81: 602.26 | C81: 348.34 | G81: =VLOOKUP(A81,E:E,1,FALSE) -> 00109090501702
A82: 00109090501800 | B82: 0 | C82: 0 | G82: =VLOOKUP(A82,E:E,1,FALSE) -> 00109090501800
A83: 00109090502100 | B83: 10310.86 | C83: 9284.34 | G83: =VLOOKUP(A83,E:E,1,FALSE) -> 00109090502100
A84: 00109090502100CIALS | B84: 0 | C84: 0 | G84: =VLOOKUP(A84,E:E,1,FALSE) -> #N/A
A85: 00109090502200 | B85: 12548.32 | C85: 12010.96 | G85: =VLOOKUP(A85,E:E,1,FALSE) -> 00109090502200
A86: 00109090502300 | B86: 24458.3 | C86: 24981.22 | G86: =VLOOKUP(A86,E:E,1,FALSE) -> 00109090502300
... A124: 00109090999999 | B124: 0 | C124: 0 | G124: =VLOOKUP(A124,E:E,1,FALSE) -> #N/A

Sheet 920 Park Rangers
A1: City of Altamonte Springs, Florida
A2: ='[1]Admin Summary'!A2:K2 -> Fiscal Year 2026 / 2027 Annual Budget
A4: Leisure and Maintenance Services Department
A5: Park Rangers
A6: General Fund (00109200)
M8: =' 911 Admin'!M8 -> 2027
G9: =' 911 Admin'!G9 -> 2024 | I9: =' 911 Admin'!I9 -> 2025 | K9: =' 911 Admin'!K9 -> 2026 | M9: Department | O9: Manager | Q9: Commission
B10: Org | C10: Obj | D10: Proj | G10: Actual | I10: Actual | K10: Budget | M10: Requested | O10: Recommended | Q10: Adopted | R10: Notes
A11: PERSONNEL SERVICES
A12: Regular Salaries & Wages Base: 14 Positions | B12: 00109200 | C12: 501201 | E12: =_xlfn.CONCAT(B12,C12,D12) -> 00109200501201 | F12: $ | G12: =ROUND(IFERROR(VLOOKUP(_xlfn.CONCAT($B12,$C12,$D12),$A$93:$C$9994,3,FALSE),0),0) -> 517030 | H12: $ | I12: =ROUND(IFERROR(VLOOKUP(_xlfn.CONCAT($B12,$C12,$D12),$A$93:$C$9994,2,FALSE),0),0) -> 537521 | J12: $ | K12: 571289 | L12: $ | M12: ='[1]Payroll Summary by Department'!C65 -> 571289 | N12: $ | O12: =M12 -> 571289 | P12: $ | Q12: =O12 -> 571289
A13: Sign Incentive Award | B13: 00109200 | C13: 501290 | E13: =_xlfn.CONCAT(B13,C13,D13) -> 00109200501290 | G13: =ROUND(IFERROR(VLOOKUP(_xlfn.CONCAT($B13,$C13,$D13),$A$93:$C$9994,3,FALSE),0),0) -> 72 | I13: =ROUND(IFERROR(VLOOKUP(_xlfn.CONCAT($B13,$C13,$D13),$A$93:$C$9994,2,FALSE),0),0) -> 0 | K13: 300 | M13: 300 | O13: =M13 -> 300 | Q13: =O13 -> 300
A14: Limited Term Employee Wages | B14: 00109200 | C14: 501300 | E14: =_xlfn.CONCAT(B14,C14,D14) -> 00109200501300 | G14: =ROUND(IFERROR(VLOOKUP(_xlfn.CONCAT($B14,$C14,$D14),$A$93:$C$9994,3,FALSE),0),0) -> 87053 | I14: =ROUND(IFERROR(VLOOKUP(_xlfn.CONCAT($B14,$C14,$D14),$A$93:$C$9994,2,FALSE),0),0) -> 87506 | K14: 69000 | M14: 69000 | O14: =M14 -> 69000 | Q14: =O14 -> 69000
A15: Overtime | B15: 00109200 | C15: 501400 | E15: =_xlfn.CONCAT(B15,C15,D15) -> 00109200501400 | G15: =ROUND(IFERROR(VLOOKUP(_xlfn.CONCAT($B15,$C15,$D15),$A$93:$C$9994,3,FALSE),0),0) -> 45259 | I15: =ROUND(IFERROR(VLOOKUP(_xlfn.CONCAT($B15,$C15,$D15),$A$93:$C$9994,2,FALSE),0),0) -> 51431 | K15: 30000 | M15: 30000 | O15: =M15 -> 30000 | Q15: =O15 -> 30000
A16: On Call | B16: 00109200 | C16: 501401 | E16: =_xlfn.CONCAT(B16,C16,D16) -> 00109200501401 | G16: =ROUND(IFERROR(VLOOKUP(_xlfn.CONCAT($B16,$C16,$D16),$A$93:$C$9994,3,FALSE),0),0) -> 0 | I16: =ROUND(IFERROR(VLOOKUP(_xlfn.CONCAT($B16,$C16,$D16),$A$93:$C$9994,2,FALSE),0),0) -> 0 | K16: 50 | M16: 50 | O16: =M16 -> 50 | Q16: =O16 -> 50
A17: Add Pays | B17: 00109200 | C17: 501600 | E17: =_xlfn.CONCAT(B17,C17,D17) -> 00109200501600 | G17: =ROUND(IFERROR(VLOOKUP(_xlfn.CONCAT($B17,$C17,$D17),$A$93:$C$9994,3,FALSE),0),0) -> 13451 | I17: =ROUND(IFERROR(VLOOKUP(_xlfn.CONCAT($B17,$C17,$D17),$A$93:$C$9994,2,FALSE),0),0) -> 8615 | K17: 0 | M17: ='[1]Payroll Summary by Department'!I65 -> 0 | O17: =M17 -> 0 | Q17: =O17 -> 0
A18: Auto Allowance | B18: 00109200 | C18: 501701 | E18: =_xlfn.CONCAT(B18,C18,D18) -> 00109200501701 | G18: =ROUND(IFERROR(VLOOKUP(_xlfn.CONCAT($B18,$C18,$D18),$A$93:$C$9994,3,FALSE),0),0) -> 0 | I18: =ROUND(IFERROR(VLOOKUP(_xlfn.CONCAT($B18,$C18,$D18),$A$93:$C$9994,2,FALSE),0),0) -> 0 | K18: 0 | M18: ='[1]Payroll Summary by Department'!K65 -> 0 | O18: =M18 -> 0 | Q18: =O18 -> 0
A19: Cell Phone Allowance | B19: 00109200 | C19: 501702 | E19: =_xlfn.CONCAT(B19,C19,D19) -> 00109200501702 | G19: =ROUND(IFERROR(VLOOKUP(_xlfn.CONCAT($B19,$C19,$D19),$A$93:$C$9994,3,FALSE),0),0) -> 1690 | I19: =ROUND(IFERROR(VLOOKUP(_xlfn.CONCAT($B19,$C19,$D19),$A$93:$C$9994,2,FALSE),0),0) -> 1325 | K19: 1800 | M19: ='[1]Payroll Summary by Department'!L65 -> 1800 | O19: =M19 -> 1800 | Q19: =O19 -> 1800
A20: Uniform Allowance | B20: 00109200 | C20: 501800 | E20: =_xlfn.CONCAT(B20,C20,D20) -> 00109200501800 | G20: =ROUND(IFERROR(VLOOKUP(_xlfn.CONCAT($B20,$C20,$D20),$A$93:$C$9994,3,FALSE),0),0) -> 0 | I20: =ROUND(IFERROR(VLOOKUP(_xlfn.CONCAT($B20,$C20,$D20),$A$93:$C$9994,2,FALSE),0),0) -> 0 | K20: 50 | M20: 50 | O20: =M20 -> 50 | Q20: =O20 -> 50
A21: FICA Taxes | B21: 00109200 | C21: 502100 | E21: =_xlfn.CONCAT(B21,C21,D21) -> 00109200502100 | G21: =ROUND(IFERROR(VLOOKUP(_xlfn.CONCAT($B21,$C21,$D21),$A$93:$C$9994,3,FALSE),0),0) -> 50467 | I21: =ROUND(IFERROR(VLOOKUP(_xlfn.CONCAT($B21,$C21,$D21),$A$93:$C$9994,2,FALSE),0),0) -> 52117 | K21: 51367 | M21: ='[1]Payroll Summary by Department'!N65-80 -> 51367 | O21: =M21 -> 51367 | Q21: =O21 -> 51367
A22: Retirement Contributions | B22: 00109200 | C22: 502200 | E22: =_xlfn.CONCAT(B22,C22,D22) -> 00109200502200 | G22: =ROUND(IFERROR(VLOOKUP(_xlfn.CONCAT($B22,$C22,$D22),$A$93:$C$9994,3,FALSE),0),0) -> 55617 | I22: =ROUND(IFERROR(VLOOKUP(_xlfn.CONCAT($B22,$C22,$D22),$A$93:$C$9994,2,FALSE),0),0) -> 54507 | K22: 75169 | M22: ='[1]Payroll Summary by Department'!O65+'[1]Payroll Summary by Department'!P65 -> 75169 | O22: =M22 -> 75169 | Q22: =O22 -> 75169
A23: Health Insurance | B23: 00109200 | C23: 502300 | E23: =_xlfn.CONCAT(B23,C23,D23) -> 00109200502300 | G23: =ROUND(IFERROR(VLOOKUP(_xlfn.CONCAT($B23,$C23,$D23),$A$93:$C$9994,3,FALSE),0),0) -> 110059 | I23: =ROUND(IFERROR(VLOOKUP(_xlfn.CONCAT($B23,$C23,$D23),$A$93:$C$9994,2,FALSE),0),0) -> 107809 | K23: 148232 | M23: ='[1]Payroll Summary by Department'!Q65 -> 148232 | O23: =M23 -> 148232 | Q23: =O23 -> 148232
A24: Life Insurance | B24: 00109200 | C24: 502400 | E24: =_xlfn.CONCAT(B24,C24,D24) -> 00109200502400 | G24: =ROUND(IFERROR(VLOOKUP(_xlfn.CONCAT($B24,$C24,$D24),$A$93:$C$9994,3,FALSE),0),0) -> 1021 | I24: =ROUND(IFERROR(VLOOKUP(_xlfn.CONCAT($B24,$C24,$D24),$A$93:$C$9994,2,FALSE),0),0) -> 1089 | K24: 1081 | M24: ='[1]Payroll Summary by Department'!R65 -> 1081 | O24: =M24 -> 1081 | Q24: =O24 -> 1081
A25: Total Personnel Services | E25: =_xlfn.CONCAT(B25,C25,D25) | F25: $ | G25: =SUM(G12:G24) -> 881719 | H25: $ | I25: =SUM(I12:I24) -> 901920 | J25: $ | K25: =SUM(K12:K24) -> 948338 | L25: $ | M25: =SUM(M12:M24) -> 948338 | N25: $ | O25: =SUM(O12:O24) -> 948338 | P25: $ | Q25: =SUM(Q12:Q24) -> 948338
A26: POSITION ROSTER | E26: =_xlfn.CONCAT(B26,C26,D26)
A27: Full Time Employees | E27: =_xlfn.CONCAT(B27,C27,D27)
A28: Park Manager | C28: 3C | E28: =_xlfn.CONCAT(B28,C28,D28) -> 3C | G28: 1 | I28: 1 | K28: 1 | M28: 1 | O28: =M28 -> 1 | Q28: =O28 -> 1
A29: Park Ranger Supervisor | C29: 3A | E29: =_xlfn.CONCAT(B29,C29,D29) -> 3A | G29: 2 | I29: 2 | K29: 2 | M29: 2 | O29: =M29 -> 2 | Q29: =O29 -> 2
A30: Event Park Ranger | C30: 4C | E30: =_xlfn.CONCAT(B30,C30,D30) -> 4C | G30: 1 | I30: 1 | K30: 1 | M30: 1 | O30: =M30 -> 1 | Q30: =O30 -> 1
A31: Park Ranger | C31: 4C | E31: =_xlfn.CONCAT(B31,C31,D31) -> 4C | G31: 10 | I31: 10 | K31: 10 | M31: 10 | O31: =M31 -> 10 | Q31: =O31 -> 10
A32: Total Full Time Employees | E32: =_xlfn.CONCAT(B32,C32,D32) | G32: =SUM(G28:G31) -> 14 | I32: =SUM(I28:I31) -> 14 | K32: =SUM(K28:K31) -> 14 | M32: =SUM(M28:M31) -> 14 | O32: =SUM(O28:O31) -> 14 | Q32: =SUM(Q28:Q31) -> 14
A33: Part Time Employees | E33: =_xlfn.CONCAT(B33,C33,D33)
A34: Park Ranger | C34: 4B | E34: =_xlfn.CONCAT(B34,C34,D34) -> 4B | G34: 0 | I34: 0 | K34: 0 | M34: 0 | O34: 0 | Q34: =O34 -> 0
A35: Total Part Time Employees | E35: =_xlfn.CONCAT(B35,C35,D35) | G35: =SUM(G34:G34) -> 0 | I35: =SUM(I34:I34) -> 0 | K35: =SUM(K34:K34) -> 0 | M35: =SUM(M34:M34) -> 0 | O35: =SUM(O34:O34) -> 0 | Q35: =SUM(Q34:Q34) -> 0
A36: Total Positions | E36: =_xlfn.CONCAT(B36,C36,D36) | G36: =+G35+G32 -> 14 | I36: =+I35+I32 -> 14 | K36: =+K35+K32 -> 14 | M36: =+M35+M32 -> 14 | O36: =+O35+O32 -> 14 | Q36: =+Q35+Q32 -> 14
A37: OPERATING EXPENDITURES | E37: =_xlfn.CONCAT(B37,C37,D37)
A38: Professional Services-Electrical | B38: 00109200 | C38: 503182 | E38: =_xlfn.CONCAT(B38,C38,D38) -> 00109200503182 | F38: $ | G38: =ROUND(IFERROR(VLOOKUP(_xlfn.CONCAT($B38,$C38,$D38),$A$93:$C$9994,3,FALSE),0),0) -> 7960 | H38: $ | I38: =ROUND(IFERROR(VLOOKUP(_xlfn.CONCAT($B38,$C38,$D38),$A$93:$C$9994,2,FALSE),0),0) -> 10220 | J38: $ | K38: 0 | L38: $ | M38: 0 | N38: $ | O38: =M38 -> 0 | P38: $ | Q38: =O38 -> 0
A39: Electrical Services | B39: 00109200 | E39: =_xlfn.CONCAT(B39,C39,D39) -> 00109200 | G39: =ROUND(IFERROR(VLOOKUP(_xlfn.CONCAT($B39,$C39,$D39),$A$93:$C$9994,3,FALSE),0),0) -> 0 | I39: =ROUND(IFERROR(VLOOKUP(_xlfn.CONCAT($B39,$C39,$D39),$A$93:$C$9994,2,FALSE),0),0) -> 0 | K39: 15000 | M39: 15000 | O39: =M39 -> 15000 | Q39: =O39 -> 15000
A40: Park Lighting | B40: 00109200 | E40: =_xlfn.CONCAT(B40,C40,D40) -> 00109200 | G40: =ROUND(IFERROR(VLOOKUP(_xlfn.CONCAT($B40,$C40,$D40),$A$93:$C$9994,3,FALSE),0),0) -> 0 | I40: =ROUND(IFERROR(VLOOKUP(_xlfn.CONCAT($B40,$C40,$D40),$A$93:$C$9994,2,FALSE),0),0) -> 0 | K40: 10000 | M40: 10000 | O40: =M40 -> 10000 | Q40: =O40 -> 10000
A41: Professional Services-Security | B41: 00109200 | C41: 503185 | E41: =_xlfn.CONCAT(B41,C41,D41) -> 00109200503185 | G41: =ROUND(IFERROR(VLOOKUP(_xlfn.CONCAT($B41,$C41,$D41),$A$93:$C$9994,3,FALSE),0),0) -> 0 | I41: =ROUND(IFERROR(VLOOKUP(_xlfn.CONCAT($B41,$C41,$D41),$A$93:$C$9994,2,FALSE),0),0) -> 0 | K41: 0 | M41: 0 | O41: =M41 -> 0 | Q41: =O41 -> 0
A42: Other Contractual Services | B42: 00109200 | C42: 503401 | E42: =_xlfn.CONCAT(B42,C42,D42) -> 00109200503401 | G42: =ROUND(IFERROR(VLOOKUP(_xlfn.CONCAT($B42,$C42,$D42),$A$93:$C$9994,3,FALSE),0),0) -> 0 | I42: =ROUND(IFERROR(VLOOKUP(_xlfn.CONCAT($B42,$C42,$D42),$A$93:$C$9994,2,FALSE),0),0) -> 0 | K42: 0 | M42: 0 | O42: =M42 -> 0 | Q42: =O42 -> 0
A43: Pressure Washing | B43: 00109200 | E43: =_xlfn.CONCAT(B43,C43,D43) -> 00109200 | G43: =ROUND(IFERROR(VLOOKUP(_xlfn.CONCAT($B43,$C43,$D43),$A$93:$C$9994,3,FALSE),0),0) -> 0 | I43: =ROUND(IFERROR(VLOOKUP(_xlfn.CONCAT($B43,$C43,$D43),$A$93:$C$9994,2,FALSE),0),0) -> 0 | K43: 5000 | M43: 5000 | O43: =M43 -> 5000 | Q43: =O43 -> 5000
A44: Other Services-Temporary Labor | B44: 00109200 | C44: 503450 | E44: =_xlfn.CONCAT(B44,C44,D44) -> 00109200503450 | G44: =ROUND(IFERROR(VLOOKUP(_xlfn.CONCAT($B44,$C44,$D44),$A$93:$C$9994,3,FALSE),0),0) -> 2168 | I44: =ROUND(IFERROR(VLOOKUP(_xlfn.CONCAT($B44,$C44,$D44),$A$93:$C$9994,2,FALSE),0),0) -> 2897 | K44: 3000 | M44: 3000 | O44: =M44 -> 3000 | Q44: =O44 -> 3000
A45: Other Services-Trash Disposal | B45: 00109200 | C45: 503460 | E45: =_xlfn.CONCAT(B45,C45,D45) -> 00109200503460 | G45: =ROUND(IFERROR(VLOOKUP(_xlfn.CONCAT($B45,$C45,$D45),$A$93:$C$9994,3,FALSE),0),0) -> 410 | I45: =ROUND(IFERROR(VLOOKUP(_xlfn.CONCAT($B45,$C45,$D45),$A$93:$C$9994,2,FALSE),0),0) -> 0 | K45: 1200 | M45: 1200 | O45: =M45 -> 1200 | Q45: =O45 -> 1200
A46: Other Services-Sludge Hauling | B46: 00109200 | C46: 503461 | E46: =_xlfn.CONCAT(B46,C46,D46) -> 00109200503461 | G46: =ROUND(IFERROR(VLOOKUP(_xlfn.CONCAT($B46,$C46,$D46),$A$93:$C$9994,3,FALSE),0),0) -> 150 | I46: =ROUND(IFERROR(VLOOKUP(_xlfn.CONCAT($B46,$C46,$D46),$A$93:$C$9994,2,FALSE),0),0) -> 300 | K46: 750 | M46: 750 | O46: =M46 -> 750 | Q46: =O46 -> 750
A47: Other Contractual Service | B47: 00109200 | C47: 503499 | E47: =_xlfn.CONCAT(B47,C47,D47) -> 00109200503499 | G47: =ROUND(IFERROR(VLOOKUP(_xlfn.CONCAT($B47,$C47,$D47),$A$93:$C$9994,3,FALSE),0),0) -> 0 | I47: =ROUND(IFERROR(VLOOKUP(_xlfn.CONCAT($B47,$C47,$D47),$A$93:$C$9994,2,FALSE),0),0) -> 0 | K47: 0 | M47: 0 | O47: =M47 -> 0 | Q47: =O47 -> 0
A48: Technical Training | B48: 00109200 | E48: =_xlfn.CONCAT(B48,C48,D48) -> 00109200 | G48: =ROUND(IFERROR(VLOOKUP(_xlfn.CONCAT($B48,$C48,$D48),$A$93:$C$9994,3,FALSE),0),0) -> 0 | I48: =ROUND(IFERROR(VLOOKUP(_xlfn.CONCAT($B48,$C48,$D48),$A$93:$C$9994,2,FALSE),0),0) -> 0 | K48: 0 | M48: 0 | O48: =M48 -> 0 | Q48: =O48 -> 0
A49: Certifications | B49: 00109200 | E49: =_xlfn.CONCAT(B49,C49,D49) -> 00109200 | G49: =ROUND(IFERROR(VLOOKUP(_xlfn.CONCAT($B49,$C49,$D49),$A$93:$C$9994,3,FALSE),0),0) -> 0 | I49: =ROUND(IFERROR(VLOOKUP(_xlfn.CONCAT($B49,$C49,$D49),$A$93:$C$9994,2,FALSE),0),0) -> 0 | K49: 0 | M49: 0 | O49: =M49 -> 0 | Q49: =O49 -> 0
A50: Non-Travel Training | B50: 00109200 | C50: 504060 | E50: =_xlfn.CONCAT(B50,C50,D50) -> 00109200504060 | G50: =ROUND(IFERROR(VLOOKUP(_xlfn.CONCAT($B50,$C50,$D50),$A$93:$C$9994,3,FALSE),0),0) -> 454 | I50: =ROUND(IFERROR(VLOOKUP(_xlfn.CONCAT($B50,$C50,$D50),$A$93:$C$9994,2,FALSE),0),0) -> 1360 | K50: 750 | M50: 750 | O50: =M50 -> 750 | Q50: =O50 -> 750
A51: Travel-Training | B51: 00109200 | C51: 504070 | E51: =_xlfn.CONCAT(B51,C51,D51) -> 00109200504070 | G51: =ROUND(IFERROR(VLOOKUP(_xlfn.CONCAT($B51,$C51,$D51),$A$93:$C$9994,3,FALSE),0),0) -> 0 | I51: =ROUND(IFERROR(VLOOKUP(_xlfn.CONCAT($B51,$C51,$D51),$A$93:$C$9994,2,FALSE),0),0) -> 0 | K51: 0 | M51: 0 | O51: =M51 -> 0 | Q51: =O51 -> 0
A52: Rental/Lease-Equipment | B52: 00109200 | C52: 504430 | E52: =_xlfn.CONCAT(B52,C52,D52) -> 00109200504430 | G52: =ROUND(IFERROR(VLOOKUP(_xlfn.CONCAT($B52,$C52,$D52),$A$93:$C$9994,3,FALSE),0),0) -> 0 | I52: =ROUND(IFERROR(VLOOKUP(_xlfn.CONCAT($B52,$C52,$D52),$A$93:$C$9994,2,FALSE),0),0) -> 0 | K52: 3500 | M52: 3500 | O52: =M52 -> 3500 | Q52: =O52 -> 3500
A53: Rental/Lease-Facilities | B53: 00109200 | C53: 504450 | E53: =_xlfn.CONCAT(B53,C53,D53) -> 00109200504450 | G53: =ROUND(IFERROR(VLOOKUP(_xlfn.CONCAT($B53,$C53,$D53),$A$93:$C$9994,3,FALSE),0),0) -> -773 | I53: =ROUND(IFERROR(VLOOKUP(_xlfn.CONCAT($B53,$C53,$D53),$A$93:$C$9994,2,FALSE),0),0) -> 0 | K53: 0 | M53: 0 | O53: =M53 -> 0 | Q53: =O53 -> 0
A54: Office Lease-Rangers | B54: 00109200 | E54: =_xlfn.CONCAT(B54,C54,D54) -> 00109200 | G54: =ROUND(IFERROR(VLOOKUP(_xlfn.CONCAT($B54,$C54,$D54),$A$93:$C$9994,3,FALSE),0),0) -> 0 | I54: =ROUND(IFERROR(VLOOKUP(_xlfn.CONCAT($B54,$C54,$D54),$A$93:$C$9994,2,FALSE),0),0) -> 0 | K54: 30000 | M54: 30000 | O54: =M54 -> 30000 | Q54: =O54 -> 30000
A55: Repair/Maint-Bldgs/ Facilities | B55: 00109200 | C55: 504601 | E55: =_xlfn.CONCAT(B55,C55,D55) -> 00109200504601 | G55: =ROUND(IFERROR(VLOOKUP(_xlfn.CONCAT($B55,$C55,$D55),$A$93:$C$9994,3,FALSE),0),0) -> 8979 | I55: =ROUND(IFERROR(VLOOKUP(_xlfn.CONCAT($B55,$C55,$D55),$A$93:$C$9994,2,FALSE),0),0) -> 11527 | K55: 27500 | M55: 27500 | O55: =M55 -> 27500 | Q55: =O55 -> 27500
A56: Repair/Maint-Equipment | B56: 00109200 | C56: 504620 | E56: =_xlfn.CONCAT(B56,C56,D56) -> 00109200504620 | G56: =ROUND(IFERROR(VLOOKUP(_xlfn.CONCAT($B56,$C56,$D56),$A$93:$C$9994,3,FALSE),0),0) -> 3117 | I56: =ROUND(IFERROR(VLOOKUP(_xlfn.CONCAT($B56,$C56,$D56),$A$93:$C$9994,2,FALSE),0),0) -> 8837 | K56: 6000 | M56: 6000 | O56: =M56 -> 6000 | Q56: =O56 -> 6000
A57: Aluminum Railings | B57: 00109200 | E57: =_xlfn.CONCAT(B57,C57,D57) -> 00109200 | G57: =ROUND(IFERROR(VLOOKUP(_xlfn.CONCAT($B57,$C57,$D57),$A$93:$C$9994,3,FALSE),0),0) -> 0 | I57: =ROUND(IFERROR(VLOOKUP(_xlfn.CONCAT($B57,$C57,$D57),$A$93:$C$9994,2,FALSE),0),0) -> 0 | K57: 3800 | M57: 3800 | O57: =M57 -> 3800 | Q57: =O57 -> 3800
A58: Lumber Boards | B58: 00109200 | E58: =_xlfn.CONCAT(B58,C58,D58) -> 00109200 | G58: =ROUND(IFERROR(VLOOKUP(_xlfn.CONCAT($B58,$C58,$D58),$A$93:$C$9994,3,FALSE),0),0) -> 0 | I58: =ROUND(IFERROR(VLOOKUP(_xlfn.CONCAT($B58,$C58,$D58),$A$93:$C$9994,2,FALSE),0),0) -> 0 | K58: 5000 | M58: 5000 | O58: =M58 -> 5000 | Q58: =O58 -> 5000
A59: Repair/Maint-Hardscape | B59: 00109200 | C59: 504675 | E59: =_xlfn.CONCAT(B59,C59,D59) -> 00109200504675 | G59: =ROUND(IFERROR(VLOOKUP(_xlfn.CONCAT($B59,$C59,$D59),$A$93:$C$9994,3,FALSE),0),0) -> 0 | I59: =ROUND(IFERROR(VLOOKUP(_xlfn.CONCAT($B59,$C59,$D59),$A$93:$C$9994,2,FALSE),0),0) -> 1250 | K59: 8000 | M59: 8000 | O59: =M59 -> 8000 | Q59: =O59 -> 8000
A60: Repair/Maint-Technology | B60: 00109200 | C60: 504683 | E60: =_xlfn.CONCAT(B60,C60,D60) -> 00109200504683 | G60: =ROUND(IFERROR(VLOOKUP(_xlfn.CONCAT($B60,$C60,$D60),$A$93:$C$9994,3,FALSE),0),0) -> 36680 | I60: =ROUND(IFERROR(VLOOKUP(_xlfn.CONCAT($B60,$C60,$D60),$A$93:$C$9994,2,FALSE),0),0) -> 17897 | K60: 0 | M60: 0 | O60: =M60 -> 0 | Q60: =O60 -> 0
A61: AV System | B61: 00109200 | E61: =_xlfn.CONCAT(B61,C61,D61) -> 00109200 | G61: =ROUND(IFERROR(VLOOKUP(_xlfn.CONCAT($B61,$C61,$D61),$A$93:$C$9994,3,FALSE),0),0) -> 0 | I61: =ROUND(IFERROR(VLOOKUP(_xlfn.CONCAT($B61,$C61,$D61),$A$93:$C$9994,2,FALSE),0),0) -> 0 | K61: 25000 | M61: 25000 | O61: =M61 -> 25000 | Q61: =O61 -> 25000
A62: Fountain | B62: 00109200 | E62: =_xlfn.CONCAT(B62,C62,D62) -> 00109200 | G62: =ROUND(IFERROR(VLOOKUP(_xlfn.CONCAT($B62,$C62,$D62),$A$93:$C$9994,3,FALSE),0),0) -> 0 | I62: =ROUND(IFERROR(VLOOKUP(_xlfn.CONCAT($B62,$C62,$D62),$A$93:$C$9994,2,FALSE),0),0) -> 0 | K62: 22000 | M62: 22000 | O62: =M62 -> 22000 | Q62: =O62 -> 22000
A63: Repair/Maint-Other | B63: 00109200 | C63: 504699 | E63: =_xlfn.CONCAT(B63,C63,D63) -> 00109200504699 | G63: =ROUND(IFERROR(VLOOKUP(_xlfn.CONCAT($B63,$C63,$D63),$A$93:$C$9994,3,FALSE),0),0) -> 2041 | I63: =ROUND(IFERROR(VLOOKUP(_xlfn.CONCAT($B63,$C63,$D63),$A$93:$C$9994,2,FALSE),0),0) -> 0 | K63: 0 | M63: 0 | O63: =M63 -> 0 | Q63: =O63 -> 0
A64: Promo Activity-Flags/Banners | B64: 00109200 | C64: 504871 | E64: =_xlfn.CONCAT(B64,C64,D64) -> 00109200504871 | G64: =ROUND(IFERROR(VLOOKUP(_xlfn.CONCAT($B64,$C64,$D64),$A$93:$C$9994,3,FALSE),0),0) -> 0 | I64: =ROUND(IFERROR(VLOOKUP(_xlfn.CONCAT($B64,$C64,$D64),$A$93:$C$9994,2,FALSE),0),0) -> 0 | K64: 1000 | M64: 1000 | O64: =M64 -> 1000 | Q64: =O64 -> 1000
A65: Office Supplies | B65: 00109200 | C65: 505101 | E65: =_xlfn.CONCAT(B65,C65,D65) -> 00109200505101 | G65: =ROUND(IFERROR(VLOOKUP(_xlfn.CONCAT($B65,$C65,$D65),$A$93:$C$9994,3,FALSE),0),0) -> 0 | I65: =ROUND(IFERROR(VLOOKUP(_xlfn.CONCAT($B65,$C65,$D65),$A$93:$C$9994,2,FALSE),0),0) -> 0 | K65: 0 | M65: 0 | O65: =M65 -> 0 | Q65: =O65 -> 0
A66: Operating Supplies | B66: 00109200 | C66: 505201 | E66: =_xlfn.CONCAT(B66,C66,D66) -> 00109200505201 | G66: =ROUND(IFERROR(VLOOKUP(_xlfn.CONCAT($B66,$C66,$D66),$A$93:$C$9994,3,FALSE),0),0) -> 16578 | I66: =ROUND(IFERROR(VLOOKUP(_xlfn.CONCAT($B66,$C66,$D66),$A$93:$C$9994,2,FALSE),0),0) -> 15473 | K66: 17000 | M66: 17000 | O66: =M66 -> 17000 | Q66: =O66 -> 17000
A67: Custodial Supplies | B67: 00109200 | E67: =_xlfn.CONCAT(B67,C67,D67) -> 00109200 | G67: =ROUND(IFERROR(VLOOKUP(_xlfn.CONCAT($B67,$C67,$D67),$A$93:$C$9994,3,FALSE),0),0) -> 0 | I67: =ROUND(IFERROR(VLOOKUP(_xlfn.CONCAT($B67,$C67,$D67),$A$93:$C$9994,2,FALSE),0),0) -> 0 | K67: 0 | M67: 0 | O67: =M67 -> 0 | Q67: =O67 -> 0
A68: Books, Pubs, Sub, Mem | B68: 00109200 | C68: 505401 | E68: =_xlfn.CONCAT(B68,C68,D68) -> 00109200505401 | G68: =ROUND(IFERROR(VLOOKUP(_xlfn.CONCAT($B68,$C68,$D68),$A$93:$C$9994,3,FALSE),0),0) -> 0 | I68: =ROUND(IFERROR(VLOOKUP(_xlfn.CONCAT($B68,$C68,$D68),$A$93:$C$9994,2,FALSE),0),0) -> 0 | K68: 200 | M68: 200 | O68: =M68 -> 200 | Q68: =O68 -> 200
A69: Warehouse Issued Uniforms | B69: 00109200 | E69: =_xlfn.CONCAT(B69,C69,D69) -> 00109200 | G69: =ROUND(IFERROR(VLOOKUP(_xlfn.CONCAT($B69,$C69,$D69),$A$93:$C$9994,3,FALSE),0),0) -> 0 | I69: =ROUND(IFERROR(VLOOKUP(_xlfn.CONCAT($B69,$C69,$D69),$A$93:$C$9994,2,FALSE),0),0) -> 0 | K69: 0 | M69: 0 | O69: =M69 -> 0 | Q69: =O69 -> 0
A70: Rental Uniforms | B70: 00109200 | C70: 505505 | E70: =_xlfn.CONCAT(B70,C70,D70) -> 00109200505505 | G70: =ROUND(IFERROR(VLOOKUP(_xlfn.CONCAT($B70,$C70,$D70),$A$93:$C$9994,3,FALSE),0),0) -> 6672 | I70: =ROUND(IFERROR(VLOOKUP(_xlfn.CONCAT($B70,$C70,$D70),$A$93:$C$9994,2,FALSE),0),0) -> 7116 | K70: 6000 | M70: 6000 | O70: =M70 -> 6000 | Q70: =O70 -> 6000
A71: Boots/Shoes | B71: 00109200 | C71: 505532 | E71: =_xlfn.CONCAT(B71,C71,D71) -> 00109200505532 | G71: =ROUND(IFERROR(VLOOKUP(_xlfn.CONCAT($B71,$C71,$D71),$A$93:$C$9994,3,FALSE),0),0) -> 2431 | I71: =ROUND(IFERROR(VLOOKUP(_xlfn.CONCAT($B71,$C71,$D71),$A$93:$C$9994,2,FALSE),0),0) -> 2046 | K71: 4125 | M71: 4125 | O71: =M71 -> 4125 | Q71: =O71 -> 4125
A72: Safety Uniforms | B72: 00109200 | C72: 505540 | E72: =_xlfn.CONCAT(B72,C72,D72) -> 00109200505540 | G72: =ROUND(IFERROR(VLOOKUP(_xlfn.CONCAT($B72,$C72,$D72),$A$93:$C$9994,3,FALSE),0),0) -> 838 | I72: =ROUND(IFERROR(VLOOKUP(_xlfn.CONCAT($B72,$C72,$D72),$A$93:$C$9994,2,FALSE),0),0) -> 0 | K72: 500 | M72: 500 | O72: =M72 -> 500 | Q72: =O72 -> 500
A73: Purchased Uniforms | B73: 00109200 | C73: 505550 | E73: =_xlfn.CONCAT(B73,C73,D73) -> 00109200505550 | G73: =ROUND(IFERROR(VLOOKUP(_xlfn.CONCAT($B73,$C73,$D73),$A$93:$C$9994,3,FALSE),0),0) -> 2818 | I73: =ROUND(IFERROR(VLOOKUP(_xlfn.CONCAT($B73,$C73,$D73),$A$93:$C$9994,2,FALSE),0),0) -> 2169 | K73: 15000 | M73: 15000 | O73: =M73 -> 15000 | Q73: =O73 -> 15000
A74: Gas/Oil/Lube | B74: 00109200 | C74: 505601 | E74: =_xlfn.CONCAT(B74,C74,D74) -> 00109200505601 | G74: =ROUND(IFERROR(VLOOKUP(_xlfn.CONCAT($B74,$C74,$D74),$A$93:$C$9994,3,FALSE),0),0) -> 304 | I74: =ROUND(IFERROR(VLOOKUP(_xlfn.CONCAT($B74,$C74,$D74),$A$93:$C$9994,2,FALSE),0),0) -> 609 | K74: 1000 | M74: 1000 | O74: =M74 -> 1000 | Q74: =O74 -> 1000
A75: Small Tools/Equip < $5,000 | B75: 00109200 | C75: 505701 | E75: =_xlfn.CONCAT(B75,C75,D75) -> 00109200505701 | G75: =ROUND(IFERROR(VLOOKUP(_xlfn.CONCAT($B75,$C75,$D75),$A$93:$C$9994,3,FALSE),0),0) -> 2018 | I75: =ROUND(IFERROR(VLOOKUP(_xlfn.CONCAT($B75,$C75,$D75),$A$93:$C$9994,2,FALSE),0),0) -> 0 | K75: 0 | M75: 0 | O75: =M75 -> 0 | Q75: =O75 -> 0
A76: Office Furniture < $5,000 | B76: 00109200 | C76: 505710 | E76: =_xlfn.CONCAT(B76,C76,D76) -> 00109200505710 | G76: =ROUND(IFERROR(VLOOKUP(_xlfn.CONCAT($B76,$C76,$D76),$A$93:$C$9994,3,FALSE),0),0) -> 0 | I76: =ROUND(IFERROR(VLOOKUP(_xlfn.CONCAT($B76,$C76,$D76),$A$93:$C$9994,2,FALSE),0),0) -> 0 | K76: 0 | M76: 0 | O76: =M76 -> 0 | Q76: =O76 -> 0
A77: Park Equipment < $5,000 | B77: 00109200 | C77: 505750 | E77: =_xlfn.CONCAT(B77,C77,D77) -> 00109200505750 | G77: =ROUND(IFERROR(VLOOKUP(_xlfn.CONCAT($B77,$C77,$D77),$A$93:$C$9994,3,FALSE),0),0) -> 1734 | I77: =ROUND(IFERROR(VLOOKUP(_xlfn.CONCAT($B77,$C77,$D77),$A$93:$C$9994,2,FALSE),0),0) -> 0 | K77: 0 | M77: 0 | O77: =M77 -> 0 | Q77: =O77 -> 0
A78: Technology Items < 5,000 | B78: 00109200 | C78: 505801 | E78: =_xlfn.CONCAT(B78,C78,D78) -> 00109200505801 | G78: =ROUND(IFERROR(VLOOKUP(_xlfn.CONCAT($B78,$C78,$D78),$A$93:$C$9994,3,FALSE),0),0) -> 0 | I78: =ROUND(IFERROR(VLOOKUP(_xlfn.CONCAT($B78,$C78,$D78),$A$93:$C$9994,2,FALSE),0),0) -> 351 | K78: 0 | M78: 0 | O78: =M78 -> 0 | Q78: =O78 -> 0
A80: Total Operating Expenditures | F80: $ | G80: =SUM(G38:G79) -> 94579 | H80: $ | I80: =SUM(I38:I79) -> 82052 | J80: $ | K80: =SUM(K38:K79) -> 211325 | L80: $ | M80: =SUM(M38:M79) -> 211325 | N80: $ | O80: =SUM(O38:O79) -> 211325 | P80: $ | Q80: =SUM(Q38:Q79) -> 211325
A81: TOTAL BUDGET | F81: $ | G81: =+G25+G80 -> 976298 | H81: $ | I81: =+I25+I80 -> 983972 | J81: $ | K81: =+K25+K80 -> 1159663 | L81: $ | M81: =+M25+M80 -> 1159663 | N81: $ | O81: =+O25+O80 -> 1159663 | P81: $ | Q81: =+Q25+Q80 -> 1159663
A83: Capital Outlay Lease | G83: =ROUND(S83,0) -> 0 | I83: =ROUND(T83,0) -> 0
A84: Lease Principal-Office Lease | B84: 00109200 | C84: 571000 | G84: =ROUND(IFERROR(VLOOKUP(_xlfn.CONCAT($B84,$C84,$D84),$A$93:$C$9994,3,FALSE),0),0) -> 23922 | I84: =ROUND(IFERROR(VLOOKUP(_xlfn.CONCAT($B84,$C84,$D84),$A$93:$C$9994,2,FALSE),0),0) -> 25356
A85: Lease Interest-Office Lease | B85: 00109200 | C85: 571200 | G85: =ROUND(IFERROR(VLOOKUP(_xlfn.CONCAT($B85,$C85,$D85),$A$93:$C$9994,3,FALSE),0),0) -> 1761 | I85: =ROUND(IFERROR(VLOOKUP(_xlfn.CONCAT($B85,$C85,$D85),$A$93:$C$9994,2,FALSE),0),0) -> 1097
A86: Total Operating Expenditures | F86: $ | G86: =G80+G83+G84+G85 -> 120262 | H86: $ | I86: =I80+I83+I84+I85 -> 108505
A88: Per GL | G88: 1001982 | I88: 1010427
A89: Diff | G89: =G81-G88 -> -25684 | I89: =I81-I88 -> -26455
B92: 2025 Actual | C92: 2024 Actual | G92: Missing Accounts Check?
A93: 00109200168910 | B93: 0 | C93: 0 | G93: =VLOOKUP(A93,E:E,1,FALSE) -> #N/A
A94: 00109200168951 | B94: 0 | C94: 0 | G94: =VLOOKUP(A94,E:E,1,FALSE) -> #N/A
A95: 00109200225900 | B95: 0 | C95: 0 | G95: =VLOOKUP(A95,E:E,1,FALSE) -> #N/A
A96: 00109200225990 | B96: 0 | C96: 0 | G96: =VLOOKUP(A96,E:E,1,FALSE) -> #N/A
A97: 00109200383100 | B97: 0 | C97: 0 | G97: =VLOOKUP(A97,E:E,1,FALSE) -> #N/A
A98: 00109200501201 | B98: 537521.22 | C98: 517029.52 | G98: =VLOOKUP(A98,E:E,1,FALSE) -> 00109200501201
A99: 00109200501290 | B99: 0 | C99: 72 | G99: =VLOOKUP(A99,E:E,1,FALSE) -> 00109200501290
A100: 00109200501300 | B100: 87506.49 | C100: 87053.12 | G100: =VLOOKUP(A100,E:E,1,FALSE) -> 00109200501300
A101: 00109200501400 | B101: 51431.27 | C101: 45258.63 | G101: =VLOOKUP(A101,E:E,1,FALSE) -> 00109200501400
A102: 00109200501401 | B102: 0 | C102: 0 | G102: =VLOOKUP(A102,E:E,1,FALSE) -> 00109200501401
A103: 00109200501600 | B103: 8615.47 | C103: 13451.43 | G103: =VLOOKUP(A103,E:E,1,FALSE) -> 00109200501600
A104: 00109200501701 | B104: 0 | C104: 0 | G104: =VLOOKUP(A104,E:E,1,FALSE) -> 00109200501701
... A149: 00109200999999 | B149: 0 | C149: 0 | G149: =VLOOKUP(A149,E:E,1,FALSE) -> #N/A

Sheet 315 Rec Impact
A1: City of Altamonte Springs, Florida
A2: ='[1]Admin Summary'!A2:K2 -> Fiscal Year 2026 / 2027 Annual Budget
R3: Allowable use: used solely for the purpose of acquisition, expansion and development of the capital assets determined to be needed to serve new development
A4: Leisure and Maintenance Services Department
A5: Recreational Facilities Impact Fee Fund (315)
B8: Acct | C8: Proj | E8: =' 914 Westmonte'!G9 -> 2024 | G8: =' 914 Westmonte'!I9 -> 2025 | I8: =' 914 Westmonte'!K9 -> 2026 | M8: =' 914 Westmonte'!M8 -> 2027 | O8: =E8 -> 2024 | P8: =G8 -> 2025 | R8: Actual | S8: projected
B9: No | C9: No | E9: Actual | G9: Actual | I9: Budget | K9: Projected | M9: Budget | O9: Actual | P9: Actual | R9: 45770 | S9: bal of year | T9: total
A10: REVENUES
A11: Impact Fees Residential | B11: 324610 | D11: $ | E11: =ROUND(O11,0) -> 1349 | F11: $ | G11: =ROUND(P11,0) -> 1686 | H11: $ | I11: 0 | J11: $ | K11: =ROUND(T11,0) -> 1349 | L11: $ | M11: 0 | O11: 1348.76 | P11: 1685.95 | R11: 1348.76 | S11: 0 | T11: =+R11+S11 -> 1348.76
A12: Impact Fees Commercial | B12: 324620 | E12: =ROUND(O12,0) -> 143 | G12: =ROUND(P12,0) -> 1110 | I12: 0 | K12: 179 | M12: 0 | O12: 142.93 | P12: 1109.64 | R12: 0 | T12: =+R12+S12 -> 0
A13: Interest Income | B13: 361100 | E13: =ROUND(O13,0) -> 30776 | G13: =ROUND(P13,0) -> 18135 | I13: 0 | K13: 2825 | M13: 0 | O13: 30776.33 | P13: 18134.88
A14: Total Revenues | D14: $ | E14: =SUM(E11:E13) -> 32268 | F14: $ | G14: =SUM(G11:G13) -> 20931 | H14: $ | I14: =SUM(I11:I13) -> 0 | J14: $ | K14: =SUM(K11:K13) -> 4353 | L14: $ | M14: =SUM(M11:M13) -> 0 | O14: =SUM(O11:O13) -> 32268.02 | P14: =SUM(P11:P13) -> 20930.47 | R14: 0 | S14: =(R14/6)*6 -> 0 | T14: =+R14+S14 -> 0 | U14: interest income
R15: 0 | S15: =(R15/6)*6 -> 0 | T15: =+R15+S15 -> 0 | U15: unrealized gains (losses)
A16: EXPENDITURES | R16: 0 | S16: =(R16/6)*6 -> 0 | T16: =+R16+S16 -> 0 | U16: realized gains (losses)
A17: Eastmonte Synthetic Turf (Rebudget) | B17: 563320 | C17: 23040 | D17: $ | E17: =ROUND(O17,0) -> 0 | F17: $ | G17: =ROUND(P17,0) -> 0 | H17: $ | I17: =150000-25107 -> 124893 | J17: $ | K17: =150000-25107 -> 124893 | L17: $ | M17: =150000-25107 -> 124893 | O17: 0 | P17: 0 | R17: =SUM(R14:R16) -> 0 | S17: =SUM(S14:S16) -> 0 | T17: =SUM(T14:T16) -> 0
A19: Total Expenditures | D19: $ | E19: =SUM(E17:E18) -> 0 | F19: $ | G19: =SUM(G17:G18) -> 0 | H19: $ | I19: =SUM(I17:I18) -> 124893 | J19: $ | K19: =SUM(K17:K18) -> 124893 | L19: $ | M19: =SUM(M17:M18) -> 124893 | O19: =SUM(O17:O18) -> 0 | P19: =SUM(P17:P18) -> 0
A21: REVENUES OVER (UNDER) EXPENDITURES | D21: $ | E21: =+E14-E19 -> 32268 | F21: $ | G21: =+G14-G19 -> 20931 | H21: $ | I21: =+I14-I19 -> -124893 | J21: $ | K21: =+K14-K19 -> -120540 | L21: $ | M21: =+M14-M19 -> -124893 | O21: =+O14-O19 -> 32268.02 | P21: =+P14-P19 -> 20930.47
A23: FUND BALANCE
A24: Beginning of Year | E24: =ROUND(O24,0) -> 418991 | G24: =+E26 -> 451259 | I24: =+G26 -> 472190 | K24: =+I24 -> 472190 | M24: =+K26 -> 351650 | O24: 418991 | P24: =+N26 -> 0
A26: End of Year | D26: $ | E26: =SUM(E21:E25) -> 451259 | F26: $ | G26: =SUM(G21:G25) -> 472190 | H26: $ | I26: =SUM(I21:I25) -> 347297 | J26: $ | K26: =SUM(K21:K25) -> 351650 | L26: $ | M26: =SUM(M21:M25) -> 226757 | N26: =SUM(N21:N25) -> 0 | O26: =SUM(O21:O25) -> 451259.02 | P26: =SUM(P21:P25) -> 20930.47
M28: 0
A29: Per GL | E29: 0 | G29: 0
A30: Diff | E30: =E19-E29 -> 0 | G30: =G19-G29 -> 0

Sheet 903 PLM&O
A1: City of Altamonte Springs, Florida
A2: ='[1]Admin Summary'!A2:K2 -> Fiscal Year 2026 / 2027 Annual Budget
A4: Leisure and Maintenance Services Department
A5: Park Landscape Management and Operations
A6: General Fund (00109030)
M8: ='920 Park Rangers'!M8 -> 2027
G9: ='920 Park Rangers'!G9 -> 2024 | I9: ='920 Park Rangers'!I9 -> 2025 | K9: ='920 Park Rangers'!K9 -> 2026 | M9: Department | O9: Manager | Q9: Commission
B10: Org | C10: Obj | D10: Proj | G10: Actual | I10: Actual | K10: Budget | M10: Requested | O10: Recommended | Q10: Adopted | R10: Notes
A11: PERSONNEL SERVICES
A12: Regular Salaries & Wages Base: 28 Positions | B12: 00109030 | C12: 501201 | E12: =_xlfn.CONCAT(B12,C12,D12) -> 00109030501201 | F12: $ | G12: =ROUND(IFERROR(VLOOKUP(_xlfn.CONCAT($B12,$C12,$D12),$A$117:$C$9996,3,FALSE),0),0) -> 1204143 | H12: $ | I12: =ROUND(IFERROR(VLOOKUP(_xlfn.CONCAT($B12,$C12,$D12),$A$117:$C$9996,2,FALSE),0),0) -> 1184425 | J12: $ | K12: 1293097.8 | L12: $ | M12: ='[1]Payroll Summary by Department'!C53-M13 -> 1293097.8 | N12: $ | O12: ='[1]Payroll Summary by Department'!C53-M13 -> 1293097.8 | P12: $ | Q12: =O12 -> 1293097.8
A13: Part-Time Salaries & Wages Base: 1 Position | B13: 00109030 | C13: 501210 | E13: =_xlfn.CONCAT(B13,C13,D13) -> 00109030501210 | G13: =ROUND(IFERROR(VLOOKUP(_xlfn.CONCAT($B13,$C13,$D13),$A$117:$C$9996,3,FALSE),0),0) -> 16336 | I13: =ROUND(IFERROR(VLOOKUP(_xlfn.CONCAT($B13,$C13,$D13),$A$117:$C$9996,2,FALSE),0),0) -> 16006 | K13: 17479.186 | M13: =SUMIFS('[1]Input Master'!O21:O565,'[1]Input Master'!E21:E565,"00109030",'[1]Input Master'!L21:L565,"P1") -> 17479.186 | O13: =M13 -> 17479.186 | Q13: =O13 -> 17479.186
A14: Sign Incentive Award | B14: 00109030 | C14: 501290 | E14: =_xlfn.CONCAT(B14,C14,D14) -> 00109030501290 | G14: =ROUND(IFERROR(VLOOKUP(_xlfn.CONCAT($B14,$C14,$D14),$A$117:$C$9996,3,FALSE),0),0) -> 0 | I14: =ROUND(IFERROR(VLOOKUP(_xlfn.CONCAT($B14,$C14,$D14),$A$117:$C$9996,2,FALSE),0),0) -> 0 | J14: =+F14+H14 -> 0 | K14: 500 | M14: 500 | O14: =M14 -> 500 | Q14: =O14 -> 500
A15: Limited Term Employee Wages | B15: 00109030 | C15: 501300 | E15: =_xlfn.CONCAT(B15,C15,D15) -> 00109030501300 | G15: =ROUND(IFERROR(VLOOKUP(_xlfn.CONCAT($B15,$C15,$D15),$A$117:$C$9996,3,FALSE),0),0) -> 30743 | I15: =ROUND(IFERROR(VLOOKUP(_xlfn.CONCAT($B15,$C15,$D15),$A$117:$C$9996,2,FALSE),0),0) -> 15040 | K15: 30000 | M15: 30000 | O15: =M15 -> 30000 | Q15: =O15 -> 30000
A16: Overtime | B16: 00109030 | C16: 501400 | E16: =_xlfn.CONCAT(B16,C16,D16) -> 00109030501400 | G16: =ROUND(IFERROR(VLOOKUP(_xlfn.CONCAT($B16,$C16,$D16),$A$117:$C$9996,3,FALSE),0),0) -> 31970 | I16: =ROUND(IFERROR(VLOOKUP(_xlfn.CONCAT($B16,$C16,$D16),$A$117:$C$9996,2,FALSE),0),0) -> 65641 | K16: 30000 | M16: 30000 | O16: =M16 -> 30000 | Q16: =O16 -> 30000
A17: On Call | B17: 00109030 | C17: 501401 | E17: =_xlfn.CONCAT(B17,C17,D17) -> 00109030501401 | G17: =ROUND(IFERROR(VLOOKUP(_xlfn.CONCAT($B17,$C17,$D17),$A$117:$C$9996,3,FALSE),0),0) -> 225 | I17: =ROUND(IFERROR(VLOOKUP(_xlfn.CONCAT($B17,$C17,$D17),$A$117:$C$9996,2,FALSE),0),0) -> 0 | K17: 500 | M17: 500 | O17: =M17 -> 500 | Q17: =O17 -> 500
A18: Add Pays | B18: 00109030 | C18: 501600 | E18: =_xlfn.CONCAT(B18,C18,D18) -> 00109030501600 | G18: =ROUND(IFERROR(VLOOKUP(_xlfn.CONCAT($B18,$C18,$D18),$A$117:$C$9996,3,FALSE),0),0) -> 763 | I18: =ROUND(IFERROR(VLOOKUP(_xlfn.CONCAT($B18,$C18,$D18),$A$117:$C$9996,2,FALSE),0),0) -> 6848 | K18: 7800 | M18: ='[1]Payroll Summary by Department'!I53 -> 7800 | O18: =M18 -> 7800 | Q18: =O18 -> 7800
A19: Cell Phone Allowance | B19: 00109030 | C19: 501702 | E19: =_xlfn.CONCAT(B19,C19,D19) -> 00109030501702 | G19: =ROUND(IFERROR(VLOOKUP(_xlfn.CONCAT($B19,$C19,$D19),$A$117:$C$9996,3,FALSE),0),0) -> 4535 | I19: =ROUND(IFERROR(VLOOKUP(_xlfn.CONCAT($B19,$C19,$D19),$A$117:$C$9996,2,FALSE),0),0) -> 4427 | K19: 4800 | M19: ='[1]Payroll Summary by Department'!L53 -> 4800 | O19: =M19 -> 4800 | Q19: =O19 -> 4800
A20: Uniform Allowance | B20: 00109030 | C20: 501800 | E20: =_xlfn.CONCAT(B20,C20,D20) -> 00109030501800 | G20: =ROUND(IFERROR(VLOOKUP(_xlfn.CONCAT($B20,$C20,$D20),$A$117:$C$9996,3,FALSE),0),0) -> 0 | I20: =ROUND(IFERROR(VLOOKUP(_xlfn.CONCAT($B20,$C20,$D20),$A$117:$C$9996,2,FALSE),0),0) -> 0 | K20: 100 | M20: 100 | O20: =M20 -> 100 | Q20: =O20 -> 100
A21: FICA Taxes | B21: 00109030 | C21: 502100 | E21: =_xlfn.CONCAT(B21,C21,D21) -> 00109030502100 | G21: =ROUND(IFERROR(VLOOKUP(_xlfn.CONCAT($B21,$C21,$D21),$A$117:$C$9996,3,FALSE),0),0) -> 96651 | I21: =ROUND(IFERROR(VLOOKUP(_xlfn.CONCAT($B21,$C21,$D21),$A$117:$C$9996,2,FALSE),0),0) -> 96899 | K21: 105597 | M21: ='[1]Payroll Summary by Department'!N53 -> 105597 | O21: ='[1]Payroll Summary by Department'!N53 -> 105597 | Q21: =O21 -> 105597
A22: Retirement Contributions | B22: 00109030 | C22: 502200 | E22: =_xlfn.CONCAT(B22,C22,D22) -> 00109030502200 | G22: =ROUND(IFERROR(VLOOKUP(_xlfn.CONCAT($B22,$C22,$D22),$A$117:$C$9996,3,FALSE),0),0) -> 138278 | I22: =ROUND(IFERROR(VLOOKUP(_xlfn.CONCAT($B22,$C22,$D22),$A$117:$C$9996,2,FALSE),0),0) -> 137311 | K22: 182324 | M22: ='[1]Payroll Summary by Department'!O53+'[1]Payroll Summary by Department'!P53 -> 182324 | O22: ='[1]Payroll Summary by Department'!O53+'[1]Payroll Summary by Department'!P53 -> 182324 | Q22: =O22 -> 182324
A23: Health Insurance | B23: 00109030 | C23: 502300 | E23: =_xlfn.CONCAT(B23,C23,D23) -> 00109030502300 | G23: =ROUND(IFERROR(VLOOKUP(_xlfn.CONCAT($B23,$C23,$D23),$A$117:$C$9996,3,FALSE),0),0) -> 249525 | I23: =ROUND(IFERROR(VLOOKUP(_xlfn.CONCAT($B23,$C23,$D23),$A$117:$C$9996,2,FALSE),0),0) -> 234048 | K23: 319500 | M23: ='[1]Payroll Summary by Department'!Q53 -> 319500 | O23: ='[1]Payroll Summary by Department'!Q53 -> 319500 | Q23: =O23 -> 319500
A24: Life Insurance | B24: 00109030 | C24: 502400 | E24: =_xlfn.CONCAT(B24,C24,D24) -> 00109030502400 | G24: =ROUND(IFERROR(VLOOKUP(_xlfn.CONCAT($B24,$C24,$D24),$A$117:$C$9996,3,FALSE),0),0) -> 2394 | I24: =ROUND(IFERROR(VLOOKUP(_xlfn.CONCAT($B24,$C24,$D24),$A$117:$C$9996,2,FALSE),0),0) -> 2409 | K24: 2476 | M24: ='[1]Payroll Summary by Department'!R53 -> 2476 | O24: ='[1]Payroll Summary by Department'!R53 -> 2476 | Q24: =O24 -> 2476
A25: Total Personnel Services | E25: =_xlfn.CONCAT(B25,C25,D25) | F25: $ | G25: =SUM(G12:G24) -> 1775563 | H25: $ | I25: =SUM(I12:I24) -> 1763054 | J25: $ | K25: =SUM(K12:K24) -> 1994174 | L25: $ | M25: =SUM(M12:M24) -> 1994174 | N25: $ | O25: =SUM(O12:O24) -> 1994174 | P25: $ | Q25: =SUM(Q12:Q24) -> 1994174
A26: POSITION ROSTER | E26: =_xlfn.CONCAT(B26,C26,D26)
A27: Full-Time Employees | E27: =_xlfn.CONCAT(B27,C27,D27)
A28: PLMO Operations Manager | C28: 3C | E28: =_xlfn.CONCAT(B28,C28,D28) -> 3C | G28: 1 | I28: 1 | K28: 1 | M28: 1 | O28: =M28 -> 1 | Q28: =O28 -> 1
A29: Park/Grounds Supervisor | C29: 3B | E29: =_xlfn.CONCAT(B29,C29,D29) -> 3B | G29: 1 | I29: 1 | K29: 1 | M29: 1 | O29: =M29 -> 1 | Q29: =O29 -> 1
A30: Turf Specialist | C30: 3B | E30: =_xlfn.CONCAT(B30,C30,D30) -> 3B | G30: 1 | I30: 1 | K30: 1 | M30: 1 | O30: =M30 -> 1 | Q30: =O30 -> 1
A31: Landscape Maint. Supervisor | C31: 3B | E31: =_xlfn.CONCAT(B31,C31,D31) -> 3B | G31: 1 | I31: 1 | K31: 1 | M31: 1 | O31: =M31 -> 1 | Q31: =O31 -> 1
A32: Chemical Application Tech | C32: 3A | E32: =_xlfn.CONCAT(B32,C32,D32) -> 3A | G32: 1 | I32: 1 | K32: 1 | M32: 1 | O32: =M32 -> 1 | Q32: =O32 -> 1
A33: Horticulture Leader | C33: 3A | E33: =_xlfn.CONCAT(B33,C33,D33) -> 3A | G33: 1 | I33: 1 | K33: 2 | M33: 2 | O33: =M33 -> 2 | Q33: =O33 -> 2
A34: Irrigation Supervisor | C34: 3A | E34: =_xlfn.CONCAT(B34,C34,D34) -> 3A | G34: 1 | I34: 1 | K34: 1 | M34: 1 | O34: =M34 -> 1 | Q34: =O34 -> 1
A35: Senior Arborist | C35: 3A/3B | E35: =_xlfn.CONCAT(B35,C35,D35) -> 3A/3B | G35: 1 | I35: 1 | K35: 1 | M35: 1 | O35: 1 | Q35: =O35 -> 1
A36: Crew Leader | C36: 4C | E36: =_xlfn.CONCAT(B36,C36,D36) -> 4C | G36: 4 | I36: 4 | K36: 6 | M36: 6 | O36: =M36 -> 6 | Q36: =O36 -> 6
A37: Heavy Equipment Operator | C37: 6B | E37: =_xlfn.CONCAT(B37,C37,D37) -> 6B | G37: 1 | I37: 1 | K37: 1 | M37: 1 | O37: 1 | Q37: =O37 -> 1
A38: Irrigation Technician | C38: 4C | E38: =_xlfn.CONCAT(B38,C38,D38) -> 4C | G38: 1 | I38: 1 | K38: 1 | M38: 1 | O38: 1 | Q38: =O38 -> 1
A39: Arborist Technician | C39: 4C | E39: =_xlfn.CONCAT(B39,C39,D39) -> 4C | G39: 2 | I39: 2 | K39: 1 | M39: 1 | O39: 1 | Q39: =O39 -> 1
A40: Groundskeeper/Landscapers | C40: 4B | E40: =_xlfn.CONCAT(B40,C40,D40) -> 4B | G40: 14 | I40: 13 | K40: 10 | M40: 10 | O40: 10 | Q40: =O40 -> 10
A41: Landscape Supervisor | C41: 3A | E41: =_xlfn.CONCAT(B41,C41,D41) -> 3A | G41: 1 | I41: 1 | K41: 0 | M41: 0 | O41: =M41 -> 0 | Q41: =O41 -> 0
A42: Arborist | C42: 3A | E42: =_xlfn.CONCAT(B42,C42,D42) -> 3A | G42: 0 | I42: 0 | K42: 0 | M42: 0 | O42: =M42 -> 0 | Q42: =O42 -> 0
A43: PLMO Specialist | C43: 4C | E43: =_xlfn.CONCAT(B43,C43,D43) -> 4C | G43: 0 | I43: 0 | K43: 0 | M43: 0 | O43: =M43 -> 0 | Q43: =O43 -> 0
A44: Tree Maint/Heavy Equip Operator | C44: 4C | E44: =_xlfn.CONCAT(B44,C44,D44) -> 4C | G44: 0 | I44: 0 | K44: 0 | M44: 0 | O44: =M44 -> 0 | Q44: =O44 -> 0
A45: Tree Maint Worker | C45: 4C | E45: =_xlfn.CONCAT(B45,C45,D45) -> 4C | G45: 0 | I45: 0 | K45: 0 | M45: 0 | O45: =M45 -> 0 | Q45: =O45 -> 0
E46: =_xlfn.CONCAT(B46,C46,D46)
A47: Total Full-Time Employees | E47: =_xlfn.CONCAT(B47,C47,D47) | G47: =SUM(G28:G46) -> 31 | I47: =SUM(I28:I46) -> 30 | K47: =SUM(K28:K46) -> 28 | M47: =SUM(M28:M46) -> 28 | O47: =SUM(O28:O46) -> 28 | Q47: =SUM(Q28:Q46) -> 28
A48: Part-Time Employees | E48: =_xlfn.CONCAT(B48,C48,D48)
A49: Special Worker | C49: 4APT | E49: =_xlfn.CONCAT(B49,C49,D49) -> 4APT | G49: =ROUND(S49,0) -> 0 | I49: 1 | K49: 1 | M49: 1 | O49: =M49 -> 1 | Q49: =O49 -> 1
A50: Total Part-Time Employees | E50: =_xlfn.CONCAT(B50,C50,D50) | G50: =G49 -> 0 | I50: =I49 -> 1 | K50: =K49 -> 1 | M50: =M49 -> 1 | O50: =O49 -> 1 | Q50: =Q49 -> 1
A51: Total Positions | E51: =_xlfn.CONCAT(B51,C51,D51) | G51: =+G47+G50 -> 31 | I51: =+I47+I50 -> 31 | K51: =+K47+K50 -> 29 | M51: =+M47+M50 -> 29 | O51: =+O47+O50 -> 29 | Q51: =+Q47+Q50 -> 29
A52: OPERATING EXPENDITURES | E52: =_xlfn.CONCAT(B52,C52,D52)
A53: Other Services-Landscaping | B53: 00109030 | C53: 503420 | E53: =_xlfn.CONCAT(B53,C53,D53) -> 00109030503420 | F53: $ | G53: =ROUND(IFERROR(VLOOKUP(_xlfn.CONCAT($B53,$C53,$D53),$A$117:$C$9996,3,FALSE),0),0) -> 393841 | H53: $ | I53: =ROUND(IFERROR(VLOOKUP(_xlfn.CONCAT($B53,$C53,$D53),$A$117:$C$9996,2,FALSE),0),0) -> 466983 | J53: $ | K53: 560000 | L53: $ | M53: 560000 | N53: $ | O53: =M53 -> 560000 | P53: $ | Q53: =O53 -> 560000
A54: Landscaping - West Alt Fuel Tank | B54: 00109030 | C54: 503420 | D54: 22025 | E54: =_xlfn.CONCAT(B54,C54,D54) -> 0010903050342022025 | G54: =ROUND(IFERROR(VLOOKUP(_xlfn.CONCAT($B54,$C54,$D54),$A$117:$C$9996,3,FALSE),0),0) -> 1320 | I54: =ROUND(IFERROR(VLOOKUP(_xlfn.CONCAT($B54,$C54,$D54),$A$117:$C$9996,2,FALSE),0),0) -> 0 | K54: 0 | M54: 0 | O54: =M54 -> 0 | Q54: =O54 -> 0
A55: Sod | B55: 00109030 | E55: =_xlfn.CONCAT(B55,C55,D55) -> 00109030 | G55: =ROUND(IFERROR(VLOOKUP(_xlfn.CONCAT($B55,$C55,$D55),$A$117:$C$9996,3,FALSE),0),0) -> 0 | I55: =ROUND(IFERROR(VLOOKUP(_xlfn.CONCAT($B55,$C55,$D55),$A$117:$C$9996,2,FALSE),0),0) -> 0 | K55: 15000 | M55: 15000 | O55: =M55 -> 15000 | Q55: =O55 -> 15000
A56: Tree Removal and Trimming | B56: 00109030 | E56: =_xlfn.CONCAT(B56,C56,D56) -> 00109030 | G56: =ROUND(IFERROR(VLOOKUP(_xlfn.CONCAT($B56,$C56,$D56),$A$117:$C$9996,3,FALSE),0),0) -> 0 | I56: =ROUND(IFERROR(VLOOKUP(_xlfn.CONCAT($B56,$C56,$D56),$A$117:$C$9996,2,FALSE),0),0) -> 0 | K56: 60000 | M56: 60000 | O56: =M56 -> 60000 | Q56: =O56 -> 60000
A57: Other Services-Temporary Labor | B57: 00109030 | C57: 503450 | E57: =_xlfn.CONCAT(B57,C57,D57) -> 00109030503450 | G57: =ROUND(IFERROR(VLOOKUP(_xlfn.CONCAT($B57,$C57,$D57),$A$117:$C$9996,3,FALSE),0),0) -> 1033 | I57: =ROUND(IFERROR(VLOOKUP(_xlfn.CONCAT($B57,$C57,$D57),$A$117:$C$9996,2,FALSE),0),0) -> 2620 | K57: 3000 | M57: 3000 | O57: =M57 -> 3000 | Q57: =O57 -> 3000
A58: Other Services-Trash Disposal | B58: 00109030 | C58: 503460 | E58: =_xlfn.CONCAT(B58,C58,D58) -> 00109030503460 | G58: =ROUND(IFERROR(VLOOKUP(_xlfn.CONCAT($B58,$C58,$D58),$A$117:$C$9996,3,FALSE),0),0) -> 8000 | I58: =ROUND(IFERROR(VLOOKUP(_xlfn.CONCAT($B58,$C58,$D58),$A$117:$C$9996,2,FALSE),0),0) -> 8984 | K58: 15000 | M58: 15000 | O58: =M58 -> 15000 | Q58: =O58 -> 15000
A59: Other Contractual Services | B59: 00109030 | C59: 503499 | E59: =_xlfn.CONCAT(B59,C59,D59) -> 00109030503499 | G59: =ROUND(IFERROR(VLOOKUP(_xlfn.CONCAT($B59,$C59,$D59),$A$117:$C$9996,3,FALSE),0),0) -> 0 | I59: =ROUND(IFERROR(VLOOKUP(_xlfn.CONCAT($B59,$C59,$D59),$A$117:$C$9996,2,FALSE),0),0) -> 0 | K59: 0 | M59: 0 | O59: =M59 -> 0 | Q59: =O59 -> 0
A60: Educational Incentive | B60: 00109030 | C60: 503901 | E60: =_xlfn.CONCAT(B60,C60,D60) -> 00109030503901 | G60: =ROUND(IFERROR(VLOOKUP(_xlfn.CONCAT($B60,$C60,$D60),$A$117:$C$9996,3,FALSE),0),0) -> 0 | I60: =ROUND(IFERROR(VLOOKUP(_xlfn.CONCAT($B60,$C60,$D60),$A$117:$C$9996,2,FALSE),0),0) -> 0 | K60: 0 | M60: 0 | O60: =M60 -> 0 | Q60: =O60 -> 0
A61: Professional Training | B61: 00109030 | E61: =_xlfn.CONCAT(B61,C61,D61) -> 00109030 | G61: =ROUND(IFERROR(VLOOKUP(_xlfn.CONCAT($B61,$C61,$D61),$A$117:$C$9996,3,FALSE),0),0) -> 0 | I61: =ROUND(IFERROR(VLOOKUP(_xlfn.CONCAT($B61,$C61,$D61),$A$117:$C$9996,2,FALSE),0),0) -> 0 | K61: 0 | M61: 0 | O61: =M61 -> 0 | Q61: =O61 -> 0
A62: Conferences/Seminars/Meetings | B62: 00109030 | E62: =_xlfn.CONCAT(B62,C62,D62) -> 00109030 | G62: =ROUND(IFERROR(VLOOKUP(_xlfn.CONCAT($B62,$C62,$D62),$A$117:$C$9996,3,FALSE),0),0) -> 0 | I62: =ROUND(IFERROR(VLOOKUP(_xlfn.CONCAT($B62,$C62,$D62),$A$117:$C$9996,2,FALSE),0),0) -> 0 | K62: 0 | M62: 0 | O62: =M62 -> 0 | Q62: =O62 -> 0
A63: Non-Travel Training | B63: 00109030 | C63: 504060 | E63: =_xlfn.CONCAT(B63,C63,D63) -> 00109030504060 | G63: =ROUND(IFERROR(VLOOKUP(_xlfn.CONCAT($B63,$C63,$D63),$A$117:$C$9996,3,FALSE),0),0) -> 683 | I63: =ROUND(IFERROR(VLOOKUP(_xlfn.CONCAT($B63,$C63,$D63),$A$117:$C$9996,2,FALSE),0),0) -> 1900 | K63: 2400 | M63: 2400 | O63: =M63 -> 2400 | Q63: =O63 -> 2400
A64: Travel Training | B64: 00109030 | C64: 504070 | E64: =_xlfn.CONCAT(B64,C64,D64) -> 00109030504070 | G64: =ROUND(IFERROR(VLOOKUP(_xlfn.CONCAT($B64,$C64,$D64),$A$117:$C$9996,3,FALSE),0),0) -> 2595 | I64: =ROUND(IFERROR(VLOOKUP(_xlfn.CONCAT($B64,$C64,$D64),$A$117:$C$9996,2,FALSE),0),0) -> 0 | K64: 6000 | M64: 6000 | O64: =M64 -> 6000 | Q64: =O64 -> 6000
A65: Rental/Lease-Equipment | B65: 00109030 | C65: 504430 | E65: =_xlfn.CONCAT(B65,C65,D65) -> 00109030504430 | G65: =ROUND(IFERROR(VLOOKUP(_xlfn.CONCAT($B65,$C65,$D65),$A$117:$C$9996,3,FALSE),0),0) -> 0 | I65: =ROUND(IFERROR(VLOOKUP(_xlfn.CONCAT($B65,$C65,$D65),$A$117:$C$9996,2,FALSE),0),0) -> 2883 | K65: 1200 | M65: 1200 | O65: =M65 -> 1200 | Q65: =O65 -> 1200
A66: Repair/Maint-Bldgs/ Facilities | B66: 00109030 | C66: 504601 | E66: =_xlfn.CONCAT(B66,C66,D66) -> 00109030504601 | G66: =ROUND(IFERROR(VLOOKUP(_xlfn.CONCAT($B66,$C66,$D66),$A$117:$C$9996,3,FALSE),0),0) -> 0 | I66: =ROUND(IFERROR(VLOOKUP(_xlfn.CONCAT($B66,$C66,$D66),$A$117:$C$9996,2,FALSE),0),0) -> 0 | K66: 0 | M66: 0 | O66: =M66 -> 0 | Q66: =O66 -> 0
A67: Repair/Maint-Fencing/Security | B67: 00109030 | C67: 504602 | E67: =_xlfn.CONCAT(B67,C67,D67) -> 00109030504602 | G67: =ROUND(IFERROR(VLOOKUP(_xlfn.CONCAT($B67,$C67,$D67),$A$117:$C$9996,3,FALSE),0),0) -> 0 | I67: =ROUND(IFERROR(VLOOKUP(_xlfn.CONCAT($B67,$C67,$D67),$A$117:$C$9996,2,FALSE),0),0) -> 0 | K67: 0 | M67: 0 | O67: =M67 -> 0 | Q67: =O67 -> 0
A68: Repair/Maint-Ballfield | B68: 00109030 | C68: 504610 | E68: =_xlfn.CONCAT(B68,C68,D68) -> 00109030504610 | G68: =ROUND(IFERROR(VLOOKUP(_xlfn.CONCAT($B68,$C68,$D68),$A$117:$C$9996,3,FALSE),0),0) -> 82809 | I68: =ROUND(IFERROR(VLOOKUP(_xlfn.CONCAT($B68,$C68,$D68),$A$117:$C$9996,2,FALSE),0),0) -> 97604 | K68: 1000 | M68: 1000 | O68: =M68 -> 1000 | Q68: =O68 -> 1000
A69: General Maintenance (All Parks) | B69: 00109030 | E69: =_xlfn.CONCAT(B69,C69,D69) -> 00109030 | G69: =ROUND(IFERROR(VLOOKUP(_xlfn.CONCAT($B69,$C69,$D69),$A$117:$C$9996,3,FALSE),0),0) -> 0 | I69: =ROUND(IFERROR(VLOOKUP(_xlfn.CONCAT($B69,$C69,$D69),$A$117:$C$9996,2,FALSE),0),0) -> 0 | K69: 25000 | M69: 25000 | O69: =M69 -> 25000 | Q69: =O69 -> 25000
A70: Replace Windscreens (EM, WM, MP) | B70: 00109030 | E70: =_xlfn.CONCAT(B70,C70,D70) -> 00109030 | G70: =ROUND(IFERROR(VLOOKUP(_xlfn.CONCAT($B70,$C70,$D70),$A$117:$C$9996,3,FALSE),0),0) -> 0 | I70: =ROUND(IFERROR(VLOOKUP(_xlfn.CONCAT($B70,$C70,$D70),$A$117:$C$9996,2,FALSE),0),0) -> 0 | K70: 10000 | M70: 10000 | O70: =M70 -> 10000 | Q70: =O70 -> 10000
A71: Crimson Stone | B71: 00109030 | E71: =_xlfn.CONCAT(B71,C71,D71) -> 00109030 | G71: =ROUND(IFERROR(VLOOKUP(_xlfn.CONCAT($B71,$C71,$D71),$A$117:$C$9996,3,FALSE),0),0) -> 0 | I71: =ROUND(IFERROR(VLOOKUP(_xlfn.CONCAT($B71,$C71,$D71),$A$117:$C$9996,2,FALSE),0),0) -> 0 | K71: 15000 | M71: 15000 | O71: =M71 -> 15000 | Q71: =O71 -> 15000
A72: Clay | B72: 00109030 | E72: =_xlfn.CONCAT(B72,C72,D72) -> 00109030 | G72: =ROUND(IFERROR(VLOOKUP(_xlfn.CONCAT($B72,$C72,$D72),$A$117:$C$9996,3,FALSE),0),0) -> 0 | I72: =ROUND(IFERROR(VLOOKUP(_xlfn.CONCAT($B72,$C72,$D72),$A$117:$C$9996,2,FALSE),0),0) -> 0 | K72: 7000 | M72: 7000 | O72: =M72 -> 7000 | Q72: =O72 -> 7000
A73: Field Paint | B73: 00109030 | E73: =_xlfn.CONCAT(B73,C73,D73) -> 00109030 | G73: =ROUND(IFERROR(VLOOKUP(_xlfn.CONCAT($B73,$C73,$D73),$A$117:$C$9996,3,FALSE),0),0) -> 0 | I73: =ROUND(IFERROR(VLOOKUP(_xlfn.CONCAT($B73,$C73,$D73),$A$117:$C$9996,2,FALSE),0),0) -> 0 | K73: 2000 | M73: 2000 | O73: =M73 -> 2000 | Q73: =O73 -> 2000
A74: Sod | B74: 00109030 | E74: =_xlfn.CONCAT(B74,C74,D74) -> 00109030 | G74: =ROUND(IFERROR(VLOOKUP(_xlfn.CONCAT($B74,$C74,$D74),$A$117:$C$9996,3,FALSE),0),0) -> 0 | I74: =ROUND(IFERROR(VLOOKUP(_xlfn.CONCAT($B74,$C74,$D74),$A$117:$C$9996,2,FALSE),0),0) -> 0 | K74: 20000 | M74: 20000 | O74: =M74 -> 20000 | Q74: =O74 -> 20000
A75: Sand | B75: 00109030 | E75: =_xlfn.CONCAT(B75,C75,D75) -> 00109030 | G75: =ROUND(IFERROR(VLOOKUP(_xlfn.CONCAT($B75,$C75,$D75),$A$117:$C$9996,3,FALSE),0),0) -> 0 | I75: =ROUND(IFERROR(VLOOKUP(_xlfn.CONCAT($B75,$C75,$D75),$A$117:$C$9996,2,FALSE),0),0) -> 0 | K75: 6000 | M75: 6000 | O75: =M75 -> 6000 | Q75: =O75 -> 6000
A76: Repair/Maint-Landscape | B76: 00109030 | C76: 504615 | E76: =_xlfn.CONCAT(B76,C76,D76) -> 00109030504615 | G76: =ROUND(IFERROR(VLOOKUP(_xlfn.CONCAT($B76,$C76,$D76),$A$117:$C$9996,3,FALSE),0),0) -> 145559 | I76: =ROUND(IFERROR(VLOOKUP(_xlfn.CONCAT($B76,$C76,$D76),$A$117:$C$9996,2,FALSE),0),0) -> 193949 | K76: 0 | M76: 0 | O76: =M76 -> 0 | Q76: =O76 -> 0
A77: Landscaping - West Alt Fuel Tank | B77: 00109030 | C77: 504615 | D77: 22025 | E77: =_xlfn.CONCAT(B77,C77,D77) -> 0010903050461522025 | G77: =ROUND(IFERROR(VLOOKUP(_xlfn.CONCAT($B77,$C77,$D77),$A$117:$C$9996,3,FALSE),0),0) -> 4652 | I77: =ROUND(IFERROR(VLOOKUP(_xlfn.CONCAT($B77,$C77,$D77),$A$117:$C$9996,2,FALSE),0),0) -> 0 | K77: 0 | M77: 0 | O77: =M77 -> 0 | Q77: =O77 -> 0
A78: General Landscaping | B78: 00109030 | E78: =_xlfn.CONCAT(B78,C78,D78) -> 00109030 | G78: =ROUND(IFERROR(VLOOKUP(_xlfn.CONCAT($B78,$C78,$D78),$A$117:$C$9996,3,FALSE),0),0) -> 0 | I78: =ROUND(IFERROR(VLOOKUP(_xlfn.CONCAT($B78,$C78,$D78),$A$117:$C$9996,2,FALSE),0),0) -> 0 | K78: 50000 | M78: 50000 | O78: =M78 -> 50000 | Q78: =O78 -> 50000
A79: Homeowner Asst/Trees E/M | B79: 00109030 | E79: =_xlfn.CONCAT(B79,C79,D79) -> 00109030 | G79: =ROUND(IFERROR(VLOOKUP(_xlfn.CONCAT($B79,$C79,$D79),$A$117:$C$9996,3,FALSE),0),0) -> 0 | I79: =ROUND(IFERROR(VLOOKUP(_xlfn.CONCAT($B79,$C79,$D79),$A$117:$C$9996,2,FALSE),0),0) -> 0 | K79: 5000 | M79: 5000 | O79: =M79 -> 5000 | Q79: =O79 -> 5000
A80: Irrigation Parts/Repair/City-wide | B80: 00109030 | E80: =_xlfn.CONCAT(B80,C80,D80) -> 00109030 | G80: =ROUND(IFERROR(VLOOKUP(_xlfn.CONCAT($B80,$C80,$D80),$A$117:$C$9996,3,FALSE),0),0) -> 0 | I80: =ROUND(IFERROR(VLOOKUP(_xlfn.CONCAT($B80,$C80,$D80),$A$117:$C$9996,2,FALSE),0),0) -> 0 | K80: 20000 | M80: 20000 | O80: =M80 -> 20000 | Q80: =O80 -> 20000
A81: Repl Plants/Right of Way | B81: 00109030 | E81: =_xlfn.CONCAT(B81,C81,D81) -> 00109030 | G81: =ROUND(IFERROR(VLOOKUP(_xlfn.CONCAT($B81,$C81,$D81),$A$117:$C$9996,3,FALSE),0),0) -> 0 | I81: =ROUND(IFERROR(VLOOKUP(_xlfn.CONCAT($B81,$C81,$D81),$A$117:$C$9996,2,FALSE),0),0) -> 0 | K81: 12500 | M81: 12500 | O81: =M81 -> 12500 | Q81: =O81 -> 12500
A82: Repl Sod/Common Areas/Parks | B82: 00109030 | E82: =_xlfn.CONCAT(B82,C82,D82) -> 00109030 | G82: =ROUND(IFERROR(VLOOKUP(_xlfn.CONCAT($B82,$C82,$D82),$A$117:$C$9996,3,FALSE),0),0) -> 0 | I82: =ROUND(IFERROR(VLOOKUP(_xlfn.CONCAT($B82,$C82,$D82),$A$117:$C$9996,2,FALSE),0),0) -> 0 | K82: 20000 | M82: 20000 | O82: =M82 -> 20000 | Q82: =O82 -> 20000
A83: Repl Safety Surfaces Wood Mulch Fiber | B83: 00109030 | E83: =_xlfn.CONCAT(B83,C83,D83) -> 00109030 | G83: =ROUND(IFERROR(VLOOKUP(_xlfn.CONCAT($B83,$C83,$D83),$A$117:$C$9996,3,FALSE),0),0) -> 0 | I83: =ROUND(IFERROR(VLOOKUP(_xlfn.CONCAT($B83,$C83,$D83),$A$117:$C$9996,2,FALSE),0),0) -> 0 | K83: 34000 | M83: 34000 | O83: =M83 -> 34000 | Q83: =O83 -> 34000
A84: Mulch (All Parks) | B84: 00109030 | E84: =_xlfn.CONCAT(B84,C84,D84) -> 00109030 | G84: =ROUND(IFERROR(VLOOKUP(_xlfn.CONCAT($B84,$C84,$D84),$A$117:$C$9996,3,FALSE),0),0) -> 0 | I84: =ROUND(IFERROR(VLOOKUP(_xlfn.CONCAT($B84,$C84,$D84),$A$117:$C$9996,2,FALSE),0),0) -> 0 | K84: 48000 | M84: 48000 | O84: =M84 -> 48000 | Q84: =O84 -> 48000
A85: Repair/Maint-Equipment | B85: 00109030 | C85: 504620 | E85: =_xlfn.CONCAT(B85,C85,D85) -> 00109030504620 | G85: =ROUND(IFERROR(VLOOKUP(_xlfn.CONCAT($B85,$C85,$D85),$A$117:$C$9996,3,FALSE),0),0) -> 4240 | I85: =ROUND(IFERROR(VLOOKUP(_xlfn.CONCAT($B85,$C85,$D85),$A$117:$C$9996,2,FALSE),0),0) -> 12919 | K85: 6500 | M85: 6500 | O85: =M85 -> 6500 | Q85: =O85 -> 6500
A86: Repair/Maint-Hardscape | B86: 00109030 | C86: 504675 | E86: =_xlfn.CONCAT(B86,C86,D86) -> 00109030504675 | G86: =ROUND(IFERROR(VLOOKUP(_xlfn.CONCAT($B86,$C86,$D86),$A$117:$C$9996,3,FALSE),0),0) -> 0 | I86: =ROUND(IFERROR(VLOOKUP(_xlfn.CONCAT($B86,$C86,$D86),$A$117:$C$9996,2,FALSE),0),0) -> 0 | K86: 0 | M86: 0 | O86: =M86 -> 0 | Q86: =O86 -> 0
A87: Printing and Binding | B87: 00109030 | C87: 504710 | E87: =_xlfn.CONCAT(B87,C87,D87) -> 00109030504710 | G87: =ROUND(IFERROR(VLOOKUP(_xlfn.CONCAT($B87,$C87,$D87),$A$117:$C$9996,3,FALSE),0),0) -> 127 | I87: =ROUND(IFERROR(VLOOKUP(_xlfn.CONCAT($B87,$C87,$D87),$A$117:$C$9996,2,FALSE),0),0) -> 147 | K87: 1400 | M87: 1400 | O87: =M87 -> 1400 | Q87: =O87 -> 1400
A88: Office Supplies | B88: 00109030 | C88: 505101 | E88: =_xlfn.CONCAT(B88,C88,D88) -> 00109030505101 | G88: =ROUND(IFERROR(VLOOKUP(_xlfn.CONCAT($B88,$C88,$D88),$A$117:$C$9996,3,FALSE),0),0) -> 0 | I88: =ROUND(IFERROR(VLOOKUP(_xlfn.CONCAT($B88,$C88,$D88),$A$117:$C$9996,2,FALSE),0),0) -> 0 | K88: 0 | M88: 0 | O88: =M88 -> 0 | Q88: =O88 -> 0
A89: Operating Supplies | B89: 00109030 | C89: 505201 | E89: =_xlfn.CONCAT(B89,C89,D89) -> 00109030505201 | G89: =ROUND(IFERROR(VLOOKUP(_xlfn.CONCAT($B89,$C89,$D89),$A$117:$C$9996,3,FALSE),0),0) -> 5950 | I89: =ROUND(IFERROR(VLOOKUP(_xlfn.CONCAT($B89,$C89,$D89),$A$117:$C$9996,2,FALSE),0),0) -> 3972 | K89: 5000 | M89: 5000 | O89: =M89 -> 5000 | Q89: =O89 -> 5000
A90: OPERATING EXPENDITURES (continued) | B90: 00109030 | E90: =_xlfn.CONCAT(B90,C90,D90) -> 00109030 | G90: =ROUND(IFERROR(VLOOKUP(_xlfn.CONCAT($B90,$C90,$D90),$A$117:$C$9996,3,FALSE),0),0) -> 0 | I90: =ROUND(IFERROR(VLOOKUP(_xlfn.CONCAT($B90,$C90,$D90),$A$117:$C$9996,2,FALSE),0),0) -> 0
A91: Chemicals | B91: 00109030 | C91: 505220 | E91: =_xlfn.CONCAT(B91,C91,D91) -> 00109030505220 | G91: =ROUND(IFERROR(VLOOKUP(_xlfn.CONCAT($B91,$C91,$D91),$A$117:$C$9996,3,FALSE),0),0) -> 69332 | I91: =ROUND(IFERROR(VLOOKUP(_xlfn.CONCAT($B91,$C91,$D91),$A$117:$C$9996,2,FALSE),0),0) -> 53089 | K91: 0 | M91: 0 | O91: =M91 -> 0 | Q91: =O91 -> 0
A92: Fertilizer | B92: 00109030 | E92: =_xlfn.CONCAT(B92,C92,D92) -> 00109030 | G92: =ROUND(IFERROR(VLOOKUP(_xlfn.CONCAT($B92,$C92,$D92),$A$117:$C$9996,3,FALSE),0),0) -> 0 | I92: =ROUND(IFERROR(VLOOKUP(_xlfn.CONCAT($B92,$C92,$D92),$A$117:$C$9996,2,FALSE),0),0) -> 0 | K92: 33600 | M92: 33600 | O92: =M92 -> 33600 | Q92: =O92 -> 33600
A93: Insecticides/Pesticides (All Parks) | B93: 00109030 | E93: =_xlfn.CONCAT(B93,C93,D93) -> 00109030 | G93: =ROUND(IFERROR(VLOOKUP(_xlfn.CONCAT($B93,$C93,$D93),$A$117:$C$9996,3,FALSE),0),0) -> 0 | I93: =ROUND(IFERROR(VLOOKUP(_xlfn.CONCAT($B93,$C93,$D93),$A$117:$C$9996,2,FALSE),0),0) -> 0 | K93: 33600 | M93: 33600 | O93: =M93 -> 33600 | Q93: =O93 -> 33600
A94: Landscaping Supplies | B94: 00109030 | C94: 505285 | E94: =_xlfn.CONCAT(B94,C94,D94) -> 00109030505285 | G94: =ROUND(IFERROR(VLOOKUP(_xlfn.CONCAT($B94,$C94,$D94),$A$117:$C$9996,3,FALSE),0),0) -> 12338 | I94: =ROUND(IFERROR(VLOOKUP(_xlfn.CONCAT($B94,$C94,$D94),$A$117:$C$9996,2,FALSE),0),0) -> 6484 | K94: 10000 | M94: 10000 | O94: =M94 -> 10000 | Q94: =O94 -> 10000
A95: Books/Pubs/Subscrs/Membs | B95: 00109030 | C95: 505401 | E95: =_xlfn.CONCAT(B95,C95,D95) -> 00109030505401 | G95: =ROUND(IFERROR(VLOOKUP(_xlfn.CONCAT($B95,$C95,$D95),$A$117:$C$9996,3,FALSE),0),0) -> 580 | I95: =ROUND(IFERROR(VLOOKUP(_xlfn.CONCAT($B95,$C95,$D95),$A$117:$C$9996,2,FALSE),0),0) -> 314 | K95: 800 | M95: 800 | O95: =M95 -> 800 | Q95: =O95 -> 800
A96: Warehouse Issued Uniforms | B96: 00109030 | E96: =_xlfn.CONCAT(B96,C96,D96) -> 00109030 | G96: =ROUND(IFERROR(VLOOKUP(_xlfn.CONCAT($B96,$C96,$D96),$A$117:$C$9996,3,FALSE),0),0) -> 0 | I96: =ROUND(IFERROR(VLOOKUP(_xlfn.CONCAT($B96,$C96,$D96),$A$117:$C$9996,2,FALSE),0),0) -> 0 | K96: 0 | M96: 0 | O96: =M96 -> 0 | Q96: =O96 -> 0
A97: Rental Uniforms | B97: 00109030 | C97: 505505 | E97: =_xlfn.CONCAT(B97,C97,D97) -> 00109030505505 | G97: =ROUND(IFERROR(VLOOKUP(_xlfn.CONCAT($B97,$C97,$D97),$A$117:$C$9996,3,FALSE),0),0) -> 18102 | I97: =ROUND(IFERROR(VLOOKUP(_xlfn.CONCAT($B97,$C97,$D97),$A$117:$C$9996,2,FALSE),0),0) -> 16457 | K97: 18500 | M97: 18500 | O97: =M97 -> 18500 | Q97: =O97 -> 18500
A98: Boots/Shoes | B98: 00109030 | C98: 505532 | E98: =_xlfn.CONCAT(B98,C98,D98) -> 00109030505532 | G98: =ROUND(IFERROR(VLOOKUP(_xlfn.CONCAT($B98,$C98,$D98),$A$117:$C$9996,3,FALSE),0),0) -> 5813 | I98: =ROUND(IFERROR(VLOOKUP(_xlfn.CONCAT($B98,$C98,$D98),$A$117:$C$9996,2,FALSE),0),0) -> 7207 | K98: 8390 | M98: 8390 | O98: =M98 -> 8390 | Q98: =O98 -> 8390
A99: Safety Uniforms | B99: 00109030 | C99: 505540 | E99: =_xlfn.CONCAT(B99,C99,D99) -> 00109030505540 | G99: =ROUND(IFERROR(VLOOKUP(_xlfn.CONCAT($B99,$C99,$D99),$A$117:$C$9996,3,FALSE),0),0) -> 7830 | I99: =ROUND(IFERROR(VLOOKUP(_xlfn.CONCAT($B99,$C99,$D99),$A$117:$C$9996,2,FALSE),0),0) -> 3200 | K99: 7375 | M99: 7375 | O99: =M99 -> 7375 | Q99: =O99 -> 7375
A100: Purchased Uniforms | B100: 00109030 | C100: 505550 | E100: =_xlfn.CONCAT(B100,C100,D100) -> 00109030505550 | G100: =ROUND(IFERROR(VLOOKUP(_xlfn.CONCAT($B100,$C100,$D100),$A$117:$C$9996,3,FALSE),0),0) -> 3769 | I100: =ROUND(IFERROR(VLOOKUP(_xlfn.CONCAT($B100,$C100,$D100),$A$117:$C$9996,2,FALSE),0),0) -> 768 | K100: 9100 | M100: 9100 | O100: =M100 -> 9100 | Q100: =O100 -> 9100
A101: Propane/Diesel | B101: 00109030 | C101: 505602 | E101: =_xlfn.CONCAT(B101,C101,D101) -> 00109030505602 | G101: =ROUND(IFERROR(VLOOKUP(_xlfn.CONCAT($B101,$C101,$D101),$A$117:$C$9996,3,FALSE),0),0) -> 0 | I101: =ROUND(IFERROR(VLOOKUP(_xlfn.CONCAT($B101,$C101,$D101),$A$117:$C$9996,2,FALSE),0),0) -> 0 | K101: 0 | M101: 0 | O101: =M101 -> 0 | Q101: =O101 -> 0
A102: Small Tools/Equip < $5,000 | B102: 00109030 | C102: 505701 | E102: =_xlfn.CONCAT(B102,C102,D102) -> 00109030505701 | G102: =ROUND(IFERROR(VLOOKUP(_xlfn.CONCAT($B102,$C102,$D102),$A$117:$C$9996,3,FALSE),0),0)-1 -> 11241 | I102: =ROUND(IFERROR(VLOOKUP(_xlfn.CONCAT($B102,$C102,$D102),$A$117:$C$9996,2,FALSE),0),0) -> 9411 | K102: 12000 | M102: 12000 | O102: =M102 -> 12000 | Q102: =O102 -> 12000
...

Sheet 904 Fleet
A1: City of Altamonte Springs, Florida
A2: ='[1]Admin Summary'!A2:K2 -> Fiscal Year 2026 / 2027 Annual Budget
A4: Leisure and Maintenance Services Department
A5: Fleet Maintenance
A6: General Fund (00109040)
M8: ='903 PLM&O'!M8 -> 2027
G9: ='903 PLM&O'!G9 -> 2024 | I9: ='903 PLM&O'!I9 -> 2025 | K9: ='903 PLM&O'!K9 -> 2026 | M9: Department | O9: Manager | Q9: Commission
B10: Org | C10: Obj | D10: Proj | G10: Actual | I10: Actual | K10: Budget | M10: Requested | O10: Recommended | Q10: Adopted | R10: Notes
A11: PERSONNEL SERVICES
A12: Regular Salaries & Wages Base: 11 Positions | B12: 00109040 | C12: 501201 | E12: =_xlfn.CONCAT(B12,C12,D12) -> 00109040501201 | F12: $ | G12: =ROUND(IFERROR(VLOOKUP(_xlfn.CONCAT($B12,$C12,$D12),$A$80:$C$9996,3,FALSE),0),0) -> 557449 | H12: $ | I12: =ROUND(IFERROR(VLOOKUP(_xlfn.CONCAT($B12,$C12,$D12),$A$80:$C$9996,2,FALSE),0),0) -> 564785 | J12: $ | K12: 603193 | L12: $ | M12: ='[1]Payroll Summary by Department'!C54 -> 603193 | N12: $ | O12: ='[1]Payroll Summary by Department'!C54 -> 603193 | P12: $ | Q12: =O12 -> 603193
A13: Overtime | B13: 00109040 | C13: 501400 | E13: =_xlfn.CONCAT(B13,C13,D13) -> 00109040501400 | G13: =ROUND(IFERROR(VLOOKUP(_xlfn.CONCAT($B13,$C13,$D13),$A$80:$C$9996,3,FALSE),0),0) -> 2215 | I13: =ROUND(IFERROR(VLOOKUP(_xlfn.CONCAT($B13,$C13,$D13),$A$80:$C$9996,2,FALSE),0),0) -> 9346 | K13: 3000 | M13: 3000 | O13: =M13 -> 3000 | Q13: =O13 -> 3000
A14: On-Call | B14: 00109040 | C14: 501401 | E14: =_xlfn.CONCAT(B14,C14,D14) -> 00109040501401 | G14: =ROUND(IFERROR(VLOOKUP(_xlfn.CONCAT($B14,$C14,$D14),$A$80:$C$9996,3,FALSE),0),0) -> 0 | I14: =ROUND(IFERROR(VLOOKUP(_xlfn.CONCAT($B14,$C14,$D14),$A$80:$C$9996,2,FALSE),0),0) -> 0 | J14: =+F14+H14 -> 0 | K14: 0 | M14: 0 | O14: =M14 -> 0 | Q14: =O14 -> 0
A15: Add Pays | B15: 00109040 | C15: 501600 | E15: =_xlfn.CONCAT(B15,C15,D15) -> 00109040501600 | G15: =ROUND(IFERROR(VLOOKUP(_xlfn.CONCAT($B15,$C15,$D15),$A$80:$C$9996,3,FALSE),0),0) -> 4819 | I15: =ROUND(IFERROR(VLOOKUP(_xlfn.CONCAT($B15,$C15,$D15),$A$80:$C$9996,2,FALSE),0),0) -> 6281 | K15: 11700 | M15: ='[1]Payroll Summary by Department'!I54 -> 11700 | O15: =M15 -> 11700 | Q15: =O15 -> 11700
A16: Auto Allowance | B16: 00109040 | C16: 501701 | E16: =_xlfn.CONCAT(B16,C16,D16) -> 00109040501701 | G16: =ROUND(IFERROR(VLOOKUP(_xlfn.CONCAT($B16,$C16,$D16),$A$80:$C$9996,3,FALSE),0),0) -> 2408 | I16: =ROUND(IFERROR(VLOOKUP(_xlfn.CONCAT($B16,$C16,$D16),$A$80:$C$9996,2,FALSE),0),0) -> 1931 | K16: 2400 | M16: ='[1]Payroll Summary by Department'!K54 -> 2400 | O16: =M16 -> 2400 | Q16: =O16 -> 2400
A17: Cell Phone Allowance | B17: 00109040 | C17: 501702 | E17: =_xlfn.CONCAT(B17,C17,D17) -> 00109040501702 | G17: =ROUND(IFERROR(VLOOKUP(_xlfn.CONCAT($B17,$C17,$D17),$A$80:$C$9996,3,FALSE),0),0) -> 1204 | I17: =ROUND(IFERROR(VLOOKUP(_xlfn.CONCAT($B17,$C17,$D17),$A$80:$C$9996,2,FALSE),0),0) -> 1205 | K17: 1200 | M17: ='[1]Payroll Summary by Department'!L54 -> 1200 | O17: =M17 -> 1200 | Q17: =O17 -> 1200
A18: Uniform Allowance | B18: 00109040 | C18: 501800 | E18: =_xlfn.CONCAT(B18,C18,D18) -> 00109040501800 | G18: =ROUND(IFERROR(VLOOKUP(_xlfn.CONCAT($B18,$C18,$D18),$A$80:$C$9996,3,FALSE),0),0) -> 0 | I18: =ROUND(IFERROR(VLOOKUP(_xlfn.CONCAT($B18,$C18,$D18),$A$80:$C$9996,2,FALSE),0),0) -> 0 | K18: 100 | M18: 100 | O18: =M18 -> 100 | Q18: =O18 -> 100
A19: FICA Taxes | B19: 00109040 | C19: 502100 | E19: =_xlfn.CONCAT(B19,C19,D19) -> 00109040502100 | G19: =ROUND(IFERROR(VLOOKUP(_xlfn.CONCAT($B19,$C19,$D19),$A$80:$C$9996,3,FALSE),0),0) -> 43369 | I19: =ROUND(IFERROR(VLOOKUP(_xlfn.CONCAT($B19,$C19,$D19),$A$80:$C$9996,2,FALSE),0),0) -> 44565 | K19: 47253 | M19: ='[1]Payroll Summary by Department'!N54 -> 47253 | O19: ='[1]Payroll Summary by Department'!N54 -> 47253 | Q19: =O19 -> 47253
A20: Retirement Contributions | B20: 00109040 | C20: 502200 | E20: =_xlfn.CONCAT(B20,C20,D20) -> 00109040502200 | G20: =ROUND(IFERROR(VLOOKUP(_xlfn.CONCAT($B20,$C20,$D20),$A$80:$C$9996,3,FALSE),0),0) -> 56385 | I20: =ROUND(IFERROR(VLOOKUP(_xlfn.CONCAT($B20,$C20,$D20),$A$80:$C$9996,2,FALSE),0),0) -> 55340 | K20: 76715 | M20: ='[1]Payroll Summary by Department'!O54+'[1]Payroll Summary by Department'!P54 -> 76715 | O20: ='[1]Payroll Summary by Department'!O54+'[1]Payroll Summary by Department'!P54 -> 76715 | Q20: =O20 -> 76715
A21: Health Insurance | B21: 00109040 | C21: 502300 | E21: =_xlfn.CONCAT(B21,C21,D21) -> 00109040502300 | G21: =ROUND(IFERROR(VLOOKUP(_xlfn.CONCAT($B21,$C21,$D21),$A$80:$C$9996,3,FALSE),0),0) -> 104460 | I21: =ROUND(IFERROR(VLOOKUP(_xlfn.CONCAT($B21,$C21,$D21),$A$80:$C$9996,2,FALSE),0),0) -> 99940 | K21: 126698 | M21: ='[1]Payroll Summary by Department'!Q54 -> 126698 | O21: ='[1]Payroll Summary by Department'!Q54 -> 126698 | Q21: =O21 -> 126698
A22: Life Insurance | B22: 00109040 | C22: 502400 | E22: =_xlfn.CONCAT(B22,C22,D22) -> 00109040502400 | G22: =ROUND(IFERROR(VLOOKUP(_xlfn.CONCAT($B22,$C22,$D22),$A$80:$C$9996,3,FALSE),0),0) -> 1132 | I22: =ROUND(IFERROR(VLOOKUP(_xlfn.CONCAT($B22,$C22,$D22),$A$80:$C$9996,2,FALSE),0),0) -> 1165 | K22: 1141 | M22: ='[1]Payroll Summary by Department'!R54 -> 1141 | O22: ='[1]Payroll Summary by Department'!R54 -> 1141 | Q22: =O22 -> 1141
A23: Total Personnel Services | E23: =_xlfn.CONCAT(B23,C23,D23) | F23: $ | G23: =SUM(G12:G22) -> 773441 | H23: $ | I23: =SUM(I12:I22) -> 784558 | J23: $ | K23: =SUM(K12:K22) -> 873400 | L23: $ | M23: =SUM(M12:M22) -> 873400 | N23: $ | O23: =SUM(O12:O22) -> 873400 | P23: $ | Q23: =SUM(Q12:Q22) -> 873400
A24: POSITION ROSTER | E24: =_xlfn.CONCAT(B24,C24,D24)
A25: Full-Time Employees | E25: =_xlfn.CONCAT(B25,C25,D25)
A26: Fleet Division Manager | C26: 3D | E26: =_xlfn.CONCAT(B26,C26,D26) -> 3D | G26: 1 | I26: 1 | K26: 1 | M26: 1 | O26: =M26 -> 1 | Q26: =O26 -> 1
A27: Heavy Equip. Tech IV - Master | C27: 6C | E27: =_xlfn.CONCAT(B27,C27,D27) -> 6C | G27: =ROUND(S27,0) -> 0 | I27: 1 | K27: 1 | M27: 1 | O27: =M27 -> 1 | Q27: =O27 -> 1
A28: Auto Service Writer | C28: 6B | E28: =_xlfn.CONCAT(B28,C28,D28) -> 6B | G28: 1 | I28: 1 | K28: 1 | M28: 1 | O28: =M28 -> 1 | Q28: =O28 -> 1
A29: Automotive Technician | C29: 6A, 6B | E29: =_xlfn.CONCAT(B29,C29,D29) -> 6A, 6B | G29: 2 | I29: 2 | K29: 2 | M29: 2 | O29: =M29 -> 2 | Q29: =O29 -> 2
A30: Heavy Equipment Technician | C30: 6B | E30: =_xlfn.CONCAT(B30,C30,D30) -> 6B | G30: 2 | I30: 1 | K30: 1 | M30: 1 | O30: =M30 -> 1 | Q30: =O30 -> 1
A31: Equipment Installation Technician | C31: 6B | E31: =_xlfn.CONCAT(B31,C31,D31) -> 6B | G31: 1 | I31: 1 | K31: 1 | M31: 1 | O31: =M31 -> 1 | Q31: =O31 -> 1
A32: Small Engine Technician | C32: 3A | E32: =_xlfn.CONCAT(B32,C32,D32) -> 3A | G32: 2 | I32: 2 | K32: 1 | M32: 1 | O32: 1 | Q32: =O32 -> 1
A33: Preventive Maint Mechanic | C33: 3A | E33: =_xlfn.CONCAT(B33,C33,D33) -> 3A | G33: 1 | I33: 1 | K33: 1 | M33: 1 | O33: =M33 -> 1 | Q33: =O33 -> 1
A34: Staff Assistant | C34: 4C | E34: =_xlfn.CONCAT(B34,C34,D34) -> 4C | G34: 1 | I34: 1 | K34: 1 | M34: 1 | O34: =M34 -> 1 | Q34: =O34 -> 1
A35: Auto Parts Specialist | C35: 4C | E35: =_xlfn.CONCAT(B35,C35,D35) -> 4C | G35: 1 | I35: 1 | K35: 1 | M35: 1 | O35: =M35 -> 1 | Q35: =O35 -> 1
A36: Total Positions | E36: =_xlfn.CONCAT(B36,C36,D36) | G36: =SUM(G26:G35) -> 12 | I36: =SUM(I26:I35) -> 12 | K36: =SUM(K26:K35) -> 11 | M36: =SUM(M26:M35) -> 11 | O36: =SUM(O26:O35) -> 11 | Q36: =SUM(Q26:Q35) -> 11
A37: OPERATING EXPENDITURES | E37: =_xlfn.CONCAT(B37,C37,D37)
A38: Professional Services-Consulting | B38: 00109040 | C38: 503120 | E38: =_xlfn.CONCAT(B38,C38,D38) -> 00109040503120 | F38: $ | G38: =ROUND(IFERROR(VLOOKUP(_xlfn.CONCAT($B38,$C38,$D38),$A$80:$C$9996,3,FALSE),0),0) -> 0 | H38: $ | I38: =ROUND(IFERROR(VLOOKUP(_xlfn.CONCAT($B38,$C38,$D38),$A$80:$C$9996,2,FALSE),0),0) -> 1279 | J38: $ | K38: 0 | L38: $ | M38: 0 | N38: $ | O38: =M38 -> 0 | P38: $ | Q38: =O38 -> 0
A39: Professional Services-Architectural | B39: 00109040 | C39: 503140 | E39: =_xlfn.CONCAT(B39,C39,D39) -> 00109040503140 | G39: =ROUND(IFERROR(VLOOKUP(_xlfn.CONCAT($B39,$C39,$D39),$A$80:$C$9996,3,FALSE),0),0) -> 0 | I39: =ROUND(IFERROR(VLOOKUP(_xlfn.CONCAT($B39,$C39,$D39),$A$80:$C$9996,2,FALSE),0),0) -> 0 | K39: 0 | M39: 0 | O39: =M39 -> 0 | Q39: =O39 -> 0
A40: Other Services-Software Subscriptions | B40: 00109040 | C40: 503403 | E40: =_xlfn.CONCAT(B40,C40,D40) -> 00109040503403 | F40: $ | G40: =ROUND(IFERROR(VLOOKUP(_xlfn.CONCAT($B40,$C40,$D40),$A$80:$C$9996,3,FALSE),0),0) -> 10443 | H40: $ | I40: =ROUND(IFERROR(VLOOKUP(_xlfn.CONCAT($B40,$C40,$D40),$A$80:$C$9996,2,FALSE),0),0) -> 0 | J40: $ | K40: 0 | L40: $ | M40: 0 | N40: $ | O40: =M40 -> 0 | P40: $ | Q40: =O40 -> 0
A41: Other Services-Trash Disposal | B41: 00109040 | C41: 503460 | E41: =_xlfn.CONCAT(B41,C41,D41) -> 00109040503460 | G41: =ROUND(IFERROR(VLOOKUP(_xlfn.CONCAT($B41,$C41,$D41),$A$80:$C$9996,3,FALSE),0),0) -> 1031 | I41: =ROUND(IFERROR(VLOOKUP(_xlfn.CONCAT($B41,$C41,$D41),$A$80:$C$9996,2,FALSE),0),0) -> 1437 | K41: 1500 | M41: 1500 | O41: =M41 -> 1500 | Q41: =O41 -> 1500
A42: Other Contractual Services | B42: 00109040 | C42: 503499 | E42: =_xlfn.CONCAT(B42,C42,D42) -> 00109040503499 | G42: =ROUND(IFERROR(VLOOKUP(_xlfn.CONCAT($B42,$C42,$D42),$A$80:$C$9996,3,FALSE),0),0) -> 0 | I42: =ROUND(IFERROR(VLOOKUP(_xlfn.CONCAT($B42,$C42,$D42),$A$80:$C$9996,2,FALSE),0),0) -> 0 | K42: 0 | M42: 0 | O42: =M42 -> 0 | Q42: =O42 -> 0
A43: Educational Incentive | B43: 00109040 | C43: 503901 | E43: =_xlfn.CONCAT(B43,C43,D43) -> 00109040503901 | G43: =ROUND(IFERROR(VLOOKUP(_xlfn.CONCAT($B43,$C43,$D43),$A$80:$C$9996,3,FALSE),0),0) -> 0 | I43: =ROUND(IFERROR(VLOOKUP(_xlfn.CONCAT($B43,$C43,$D43),$A$80:$C$9996,2,FALSE),0),0) -> 0 | K43: 0 | M43: 0 | O43: =M43 -> 0 | Q43: =O43 -> 0
A44: Professional Training | B44: 00109040 | E44: =_xlfn.CONCAT(B44,C44,D44) -> 00109040 | G44: =ROUND(IFERROR(VLOOKUP(_xlfn.CONCAT($B44,$C44,$D44),$A$80:$C$9996,3,FALSE),0),0) -> 0 | I44: =ROUND(IFERROR(VLOOKUP(_xlfn.CONCAT($B44,$C44,$D44),$A$80:$C$9996,2,FALSE),0),0) -> 0 | K44: 0 | M44: 0 | O44: =M44 -> 0 | Q44: =O44 -> 0
A45: Certifications | B45: 00109040 | E45: =_xlfn.CONCAT(B45,C45,D45) -> 00109040 | G45: =ROUND(IFERROR(VLOOKUP(_xlfn.CONCAT($B45,$C45,$D45),$A$80:$C$9996,3,FALSE),0),0) -> 0 | I45: =ROUND(IFERROR(VLOOKUP(_xlfn.CONCAT($B45,$C45,$D45),$A$80:$C$9996,2,FALSE),0),0) -> 0 | K45: 0 | M45: 0 | O45: =M45 -> 0 | Q45: =O45 -> 0
A46: Non-Travel Training | B46: 00109040 | C46: 504060 | E46: =_xlfn.CONCAT(B46,C46,D46) -> 00109040504060 | G46: =ROUND(IFERROR(VLOOKUP(_xlfn.CONCAT($B46,$C46,$D46),$A$80:$C$9996,3,FALSE),0),0) -> 1386 | I46: =ROUND(IFERROR(VLOOKUP(_xlfn.CONCAT($B46,$C46,$D46),$A$80:$C$9996,2,FALSE),0),0) -> 1675 | K46: 2000 | M46: 2000 | O46: =M46 -> 2000 | Q46: =O46 -> 2000
A47: Travel Training | B47: 00109040 | C47: 504070 | E47: =_xlfn.CONCAT(B47,C47,D47) -> 00109040504070 | G47: =ROUND(IFERROR(VLOOKUP(_xlfn.CONCAT($B47,$C47,$D47),$A$80:$C$9996,3,FALSE),0),0) -> 1734 | I47: =ROUND(IFERROR(VLOOKUP(_xlfn.CONCAT($B47,$C47,$D47),$A$80:$C$9996,2,FALSE),0),0) -> 2866 | K47: 2500 | M47: 2500 | O47: =M47 -> 2500 | Q47: =O47 -> 2500
A48: Rentals & Leases-Other | B48: 00109040 | C48: 504401 | E48: =_xlfn.CONCAT(B48,C48,D48) -> 00109040504401 | G48: =ROUND(IFERROR(VLOOKUP(_xlfn.CONCAT($B48,$C48,$D48),$A$80:$C$9996,3,FALSE),0),0) -> 2067 | I48: =ROUND(IFERROR(VLOOKUP(_xlfn.CONCAT($B48,$C48,$D48),$A$80:$C$9996,2,FALSE),0),0) -> 2028 | K48: 2100 | M48: 2100 | O48: =M48 -> 2100 | Q48: =O48 -> 2100
A49: Rental/Lease-Equipment | B49: 00109040 | C49: 504430 | E49: =_xlfn.CONCAT(B49,C49,D49) -> 00109040504430 | G49: =ROUND(IFERROR(VLOOKUP(_xlfn.CONCAT($B49,$C49,$D49),$A$80:$C$9996,3,FALSE),0),0) -> 0 | I49: =ROUND(IFERROR(VLOOKUP(_xlfn.CONCAT($B49,$C49,$D49),$A$80:$C$9996,2,FALSE),0),0) -> 162 | K49: 1500 | M49: 1500 | O49: =M49 -> 1500 | Q49: =O49 -> 1500
A50: Repair/Maint-Bldgs/ Facilities | B50: 00109040 | C50: 504601 | E50: =_xlfn.CONCAT(B50,C50,D50) -> 00109040504601 | G50: =ROUND(IFERROR(VLOOKUP(_xlfn.CONCAT($B50,$C50,$D50),$A$80:$C$9996,3,FALSE),0),0) -> 0 | I50: =ROUND(IFERROR(VLOOKUP(_xlfn.CONCAT($B50,$C50,$D50),$A$80:$C$9996,2,FALSE),0),0) -> 0 | K50: 0 | M50: 0 | O50: =M50 -> 0 | Q50: =O50 -> 0
A51: Repair/Maint-Equipment | B51: 00109040 | C51: 504620 | E51: =_xlfn.CONCAT(B51,C51,D51) -> 00109040504620 | G51: =ROUND(IFERROR(VLOOKUP(_xlfn.CONCAT($B51,$C51,$D51),$A$80:$C$9996,3,FALSE),0),0) -> 9864 | I51: =ROUND(IFERROR(VLOOKUP(_xlfn.CONCAT($B51,$C51,$D51),$A$80:$C$9996,2,FALSE),0),0) -> 4868 | K51: 0 | M51: 0 | O51: =M51 -> 0 | Q51: =O51 -> 0
A52: Lift Inspections and Repairs | B52: 00109040 | E52: =_xlfn.CONCAT(B52,C52,D52) -> 00109040 | G52: =ROUND(IFERROR(VLOOKUP(_xlfn.CONCAT($B52,$C52,$D52),$A$80:$C$9996,3,FALSE),0),0) -> 0 | I52: =ROUND(IFERROR(VLOOKUP(_xlfn.CONCAT($B52,$C52,$D52),$A$80:$C$9996,2,FALSE),0),0) -> 0 | K52: 5500 | M52: 5500 | O52: =M52 -> 5500 | Q52: =O52 -> 5500
A53: Repair/Maint-Service Contracts | B53: 00109040 | C53: 504680 | E53: =_xlfn.CONCAT(B53,C53,D53) -> 00109040504680 | G53: =ROUND(IFERROR(VLOOKUP(_xlfn.CONCAT($B53,$C53,$D53),$A$80:$C$9996,3,FALSE),0),0) -> 5121 | I53: =ROUND(IFERROR(VLOOKUP(_xlfn.CONCAT($B53,$C53,$D53),$A$80:$C$9996,2,FALSE),0),0) -> 1741 | K53: 10000 | M53: 10000 | O53: =M53 -> 10000 | Q53: =O53 -> 10000
A54: Repair/Maint-Vehicle | B54: 00109040 | C54: 504690 | E54: =_xlfn.CONCAT(B54,C54,D54) -> 00109040504690 | G54: =ROUND(IFERROR(VLOOKUP(_xlfn.CONCAT($B54,$C54,$D54),$A$80:$C$9996,3,FALSE),0),0) -> 94473 | I54: =ROUND(IFERROR(VLOOKUP(_xlfn.CONCAT($B54,$C54,$D54),$A$80:$C$9996,2,FALSE),0),0) -> 84081 | K54: 80000 | M54: 80000 | O54: =M54 -> 80000 | Q54: =O54 -> 80000
A55: Printing and Binding | B55: 00109040 | C55: 504710 | E55: =_xlfn.CONCAT(B55,C55,D55) -> 00109040504710 | G55: =ROUND(IFERROR(VLOOKUP(_xlfn.CONCAT($B55,$C55,$D55),$A$80:$C$9996,3,FALSE),0),0) -> 324 | I55: =ROUND(IFERROR(VLOOKUP(_xlfn.CONCAT($B55,$C55,$D55),$A$80:$C$9996,2,FALSE),0),0) -> 138 | K55: 400 | M55: 400 | O55: =M55 -> 400 | Q55: =O55 -> 400
A56: Office Supplies | B56: 00109040 | C56: 505101 | E56: =_xlfn.CONCAT(B56,C56,D56) -> 00109040505101 | G56: =ROUND(IFERROR(VLOOKUP(_xlfn.CONCAT($B56,$C56,$D56),$A$80:$C$9996,3,FALSE),0),0) -> 0 | I56: =ROUND(IFERROR(VLOOKUP(_xlfn.CONCAT($B56,$C56,$D56),$A$80:$C$9996,2,FALSE),0),0) -> 0 | K56: 0 | M56: 0 | O56: =M56 -> 0 | Q56: =O56 -> 0
A57: Operating Supplies | B57: 00109040 | C57: 505201 | E57: =_xlfn.CONCAT(B57,C57,D57) -> 00109040505201 | G57: =ROUND(IFERROR(VLOOKUP(_xlfn.CONCAT($B57,$C57,$D57),$A$80:$C$9996,3,FALSE),0),0) -> 9094 | I57: =ROUND(IFERROR(VLOOKUP(_xlfn.CONCAT($B57,$C57,$D57),$A$80:$C$9996,2,FALSE),0),0) -> 6749 | K57: 12000 | M57: 12000 | O57: =M57 -> 12000 | Q57: =O57 -> 12000
A58: Fleet Inventory Parts | B58: 00109040 | C58: 505270 | E58: =_xlfn.CONCAT(B58,C58,D58) -> 00109040505270 | G58: =ROUND(IFERROR(VLOOKUP(_xlfn.CONCAT($B58,$C58,$D58),$A$80:$C$9996,3,FALSE),0),0) -> 275239 | I58: =ROUND(IFERROR(VLOOKUP(_xlfn.CONCAT($B58,$C58,$D58),$A$80:$C$9996,2,FALSE),0),0) -> 251258 | K58: 250000 | M58: 250000 | O58: =M58 -> 250000 | Q58: =O58 -> 250000
A59: Books/Pubs/Subscrs/Membs | B59: 00109040 | C59: 505401 | E59: =_xlfn.CONCAT(B59,C59,D59) -> 00109040505401 | G59: =ROUND(IFERROR(VLOOKUP(_xlfn.CONCAT($B59,$C59,$D59),$A$80:$C$9996,3,FALSE),0),0) -> 549 | I59: =ROUND(IFERROR(VLOOKUP(_xlfn.CONCAT($B59,$C59,$D59),$A$80:$C$9996,2,FALSE),0),0) -> 199 | K59: 1350 | M59: 1350 | O59: =M59 -> 1350 | Q59: =O59 -> 1350
A60: Warehouse Issued Uniforms | B60: 00109040 | E60: =_xlfn.CONCAT(B60,C60,D60) -> 00109040 | G60: =ROUND(IFERROR(VLOOKUP(_xlfn.CONCAT($B60,$C60,$D60),$A$80:$C$9996,3,FALSE),0),0) -> 0 | I60: =ROUND(IFERROR(VLOOKUP(_xlfn.CONCAT($B60,$C60,$D60),$A$80:$C$9996,2,FALSE),0),0) -> 0 | K60: 0 | M60: 0 | O60: =M60 -> 0 | Q60: =O60 -> 0
A61: Rental Uniforms | B61: 00109040 | C61: 505505 | E61: =_xlfn.CONCAT(B61,C61,D61) -> 00109040505505 | G61: =ROUND(IFERROR(VLOOKUP(_xlfn.CONCAT($B61,$C61,$D61),$A$80:$C$9996,3,FALSE),0),0) -> 6729 | I61: =ROUND(IFERROR(VLOOKUP(_xlfn.CONCAT($B61,$C61,$D61),$A$80:$C$9996,2,FALSE),0),0) -> 6494 | K61: 7800 | M61: 7800 | O61: =M61 -> 7800 | Q61: =O61 -> 7800
